Workbook

Sheet PRIOVOT
A2: PRIOVOT VCV Sáng | D2: PRIOVOT VCV Chiều | G2: PRIOVOT Dầu Giây Sáng
A3: Row Labels | B3: Sum of Total meals per day | D3: Row Labels | E3: Sum of Total meals per day | G3: Row Labels | H3: Sum of Total meals per day
A4: COO - Assistant | B4: 23 | D4: COO - Maintenance | E4: 51 | G4: COO - Maintenance | H4: 13
A5: COO - Exim | B5: 23 | D5: COO - WWT | E5: 3 | G5: HHVCV | H5: 131
A6: COO - IT | B6: 39 | D6: PMC - Quality | E6: 124 | G6: PMC - Quality | H6: 12
A7: COO - Maintenance | B7: 70 | D7: PMC - WH | E7: 103 | G7: PMC - WH | H7: 72
A8: COO - Purchasing | B8: 71 | D8: Pro - Aging | E8: 768 | G8: Subcontractor | H8: 19
A9: COO - WWT | B9: 23 | D9: Pro - Auto Polishing | E9: 44 | G9: (blank) | H9: 0
A10: COO Assistant | B10: 24 | D10: Pro - CNC | E10: 341 | G10: Pro - Expat | H10: 107
A11: COO Office | B11: 112 | D11: Pro - Data | E11: 84 | G11: Pro - Aging | H11: 2
A12: Finance - Accounting | B12: 148 | D12: Pro - Fabrication | E12: 167 | G12: Pro - Painting | H12: 1
A13: HR Admin | B13: 92 | D13: Pro - Gold Applying | E13: 13 | G13: Pro - Packaging | H13: 52
A14: PMC - Plan | B14: 46 | D14: Pro - Manual Lathe | E14: 29 | G14: Pro - Polishing | H14: 8
A15: PMC - Quality | B15: 487 | D15: Pro - Manual Polishing | E15: 13 | G15: Pro - CNC | H15: 11
... A17: PMC Staff | B17: 48 | D17: Pro - Painting | E17: 152 | G17: Grand Total | H17: 430
A18: Pro - Aging | B18: 1828 | D18: Pro - Polishing | E18: 169
A19: Pro - Auto Polishing | B19: 69 | D19: Pro - Welding | E19: 99
A20: Pro - CNC | B20: 216 | D20: Production | E20: 6
A21: Pro - Data | B21: 398 | D21: SubContractor | E21: 47
A22: Pro - Expat | B22: 619 | D22: (blank) | E22: 0
A23: Pro - Fabrication | B23: 324 | D23: Grand Total | E23: 3469
A24: Pro - Gold Applying | B24: 607 | G24: PRIOVOT Dầu Giây Chiều
A25: Pro - Manual Lathe | B25: 70 | G25: Row Labels | H25: Sum of Total meals per day
A26: Pro - Packaging | B26: 2012 | G26: COO - Maintenance | H26: 0
A27: Pro - Painting | B27: 353 | G27: HHVCV | H27: 55
A28: Pro - Polishing | B28: 269 | G28: PMC - Quality | H28: 0
A29: Pro - Welding | B29: 176 | G29: PMC - WH | H29: 8
A30: Production | B30: 14 | G30: Pro - Expat | H30: 67
A31: Purchase Staff | B31: 24 | G31: Subcontractor | H31: 2
A32: Subcontractor | B32: 176 | G32: (blank) | H32: 0
A33: (blank) | B33: 0 | G33: Grand Total | H33: 132
A34: Grand Total | B34: 8812
A39: Grand Total | B39: =GETPIVOTDATA("Total meals per day",$A$3)+GETPIVOTDATA("Total meals per day",$D$3)+GETPIVOTDATA("Total meals per day",$G$25)+GETPIVOTDATA("Total meals per day",$G$3) -> 12843
B40: =GETPIVOTDATA("Total meals per day",$A$3,"Department","Pro - Expat")+GETPIVOTDATA("Total meals per day",$G$3,"Department","Pro - Expat")+GETPIVOTDATA("Total meals per day",$G$25,"Department","Pro - Expat") -> 793

Sheet VP SÁNG 
I1: 46266 | J1: 46267 | K1: 46268 | L1: 46269 | M1: 46270 | N1: 46271 | O1: 46272 | P1: 46273 | Q1: 46274 | R1: 46275 | S1: 46276 | T1: 46277 | U1: 46278 | V1: 46279 | W1: 46280 | X1: 46281 | Y1: 46282 | Z1: 46283 | AA1: 46284 | AB1: 46285 | AC1: 46286 | AD1: 46287 | AE1: 46288 | AF1: 46289 | AG1: 46290 | AH1: 46291 | AI1: 46292 | AJ1: 46293 | AK1: 46294 | AL1: 46295
G2: Shift 1 + normal shift | H2: Ca sáng | I2: =SUM(I3:I7) -> 361 | J2: =SUM(J3:J7) -> 0 | K2: =SUM(K3:K7) -> 0 | L2: =SUM(L3:L7) -> 358 | M2: =SUM(M3:M7) -> 363 | N2: =SUM(N3:N7) -> 72 | O2: =SUM(O3:O7) -> 370 | P2: =SUM(P3:P7) -> 329 | ... AL2: =SUM(AL3:AL7) -> 364
G3: DS- CN food | H3: Sáng - Trung | I3: =COUNTIFS(I$13:I$663,$H3) -> 25 | J3: =COUNTIFS(J$13:J$663,$H3) -> 0 | K3: =COUNTIFS(K$13:K$663,$H3) -> 0 | L3: =COUNTIFS(L$13:L$663,$H3) -> 25 | M3: =COUNTIFS(M$13:M$663,$H3) -> 24 | N3: =COUNTIFS(N$13:N$663,$H3) -> 5 | O3: =COUNTIFS(O$13:O$663,$H3) -> 25 | P3: =COUNTIFS(P$13:P$663,$H3) -> 25 | ... AL3: =COUNTIFS(AL$13:AL$663,$H3) -> 25
D4: backup | E4: 1 | G4: DS- VN food - Office | H4: Sáng - Mặn - VP | I4: =COUNTIFS(I$13:I$663,$H4) -> 28 | J4: =COUNTIFS(J$13:J$663,$H4) -> 0 | K4: =COUNTIFS(K$13:K$663,$H4) -> 0 | L4: =COUNTIFS(L$13:L$663,$H4) -> 29 | M4: =COUNTIFS(M$13:M$663,$H4) -> 29 | N4: =COUNTIFS(N$13:N$663,$H4) -> 0 | O4: =COUNTIFS(O$13:O$663,$H4) -> 32 | P4: =COUNTIFS(P$13:P$663,$H4) -> 30 | ... AL4: =COUNTIFS(AL$13:AL$663,$H4) -> 29
G5: DS- Vegetarian rice - Office | H5: Sáng - Chay - VP | I5: =COUNTIFS(I$13:I$663,$H5) -> 2 | J5: =COUNTIFS(J$13:J$663,$H5) -> 0 | K5: =COUNTIFS(K$13:K$663,$H5) -> 0 | L5: =COUNTIFS(L$13:L$663,$H5) -> 6 | M5: =COUNTIFS(M$13:M$663,$H5) -> 4 | N5: =COUNTIFS(N$13:N$663,$H5) -> 0 | O5: =COUNTIFS(O$13:O$663,$H5) -> 4 | P5: =COUNTIFS(P$13:P$663,$H5) -> 4 | ... AL5: =COUNTIFS(AL$13:AL$663,$H5) -> 5
G6: DS- VN food | H6: Sáng - Mặn - Xưởng | I6: =COUNTIFS(I$13:I$663,$H6)-I7 -> 253 | J6: =COUNTIFS(J$13:J$663,$H6)-J7 -> 0 | K6: =COUNTIFS(K$13:K$663,$H6)-K7 -> 0 | L6: =COUNTIFS(L$13:L$663,$H6)-L7 -> 254 | M6: =COUNTIFS(M$13:M$663,$H6)-M7 -> 263 | N6: =COUNTIFS(N$13:N$663,$H6)-N7 -> 67 | O6: =COUNTIFS(O$13:O$663,$H6)-O7 -> 269 | P6: =COUNTIFS(P$13:P$663,$H6)-P7 -> 238 | ... AL6: =COUNTIFS(AL$13:AL$663,$H6)-AL7 -> 268
G7: DS- Vegetarian rice | H7: Sáng - Chay - Xưởng | I7: =3+1+37+12 -> 53 | L7: =1+3+28+12 -> 44 | M7: =1+12+28+2 -> 43 | O7: =10+27+1+2 -> 40 | P7: 32 | Q7: =3+13+1+12 -> 29 | R7: =14+2+14+1 -> 31 | S7: =2+1+22+13 -> 38 | T7: =12+1 -> 13 | V7: =2+10+26+1 -> 39 | W7: =23+2+10+1 -> 36 | X7: =1+10+2+25 -> 38 | Y7: =39 -> 39 | Z7: =2+24+1+13 -> 40 | AA7: =35+12+1+2 -> 50 | AB7: =10 -> 10 | AC7: =1+11+2+24 -> 38 | AD7: =1+12+2+24 -> 39 | AE7: =11+2+23+1 -> 37 | AF7: =1+24+2+12 -> 39 | AG7: =12+1+26+2 -> 41 | AH7: =10+1+2+25 -> 38 | AI7: =8 -> 8 | AJ7: =2+11+23 -> 36 | AK7: =11+1+1+24 -> 37 | AL7: =25+1+1+10 -> 37
E8: =SUM(I8:AL8) -> 8812 | I8: =SUM(I9:I10) -> 361 | J8: =SUM(J9:J10) -> 0 | K8: =SUM(K9:K10) -> 0 | L8: =SUM(L9:L10) -> 358 | M8: =SUM(M9:M10) -> 363 | N8: =SUM(N9:N10) -> 72 | O8: =SUM(O9:O10) -> 370 | P8: =SUM(P9:P10) -> 329 | ... AL8: =SUM(AL9:AL10) -> 364
E9: =SUM(I9:AL9) -> 619 | G9: Total Expat Meals | I9: =I3 -> 25 | J9: =J3 -> 0 | K9: =K3 -> 0 | L9: =L3 -> 25 | M9: =M3 -> 24 | N9: =N3 -> 5 | O9: =O3 -> 25 | P9: =P3 -> 25 | ... AL9: =AL3 -> 25
E10: =SUM(I10:AL10) -> 8193 | G10: Total Vietnamese Meals | I10: =I2-I3 -> 336 | J10: =J2-J3 -> 0 | K10: =K2-K3 -> 0 | L10: =L2-L3 -> 333 | M10: =M2-M3 -> 339 | N10: =N2-N3 -> 67 | O10: =O2-O3 -> 345 | P10: =P2-P3 -> 304 | ... AL10: =AL2-AL3 -> 339
AM12: =E8-SUM(AM14:AM353) -> 1825
A13: Status | B13: Code | C13: Fullname VN | D13: Department | E13: Section | F13: Place | H13: Last day | AM13: Total meals per day
A14: Active | B14: HOLA001 | C14: Trần Thị Thúy Phượng | D14: Subcontractor | E14: Subcontractor | F14: Factory | I14: Sáng - Mặn - Xưởng | L14: Sáng - Mặn - Xưởng | M14: Sáng - Mặn - Xưởng | O14: Sáng - Mặn - Xưởng | P14: Sáng - Mặn - Xưởng | Q14: Sáng - Mặn - Xưởng | R14: Sáng - Mặn - Xưởng | S14: Sáng - Mặn - Xưởng | T14: Sáng - Mặn - Xưởng | V14: Sáng - Mặn - Xưởng | W14: Sáng - Mặn - Xưởng | X14: Sáng - Mặn - Xưởng | Y14: Sáng - Mặn - Xưởng | Z14: Sáng - Mặn - Xưởng | AA14: Sáng - Mặn - Xưởng | AC14: Sáng - Mặn - Xưởng | AD14: Sáng - Mặn - Xưởng | AE14: Sáng - Mặn - Xưởng | AF14: Sáng - Mặn - Xưởng | AG14: Sáng - Mặn - Xưởng | AH14: Sáng - Mặn - Xưởng | AJ14: Sáng - Mặn - Xưởng | AK14: Sáng - Mặn - Xưởng | AL14: Sáng - Mặn - Xưởng | AM14: =COUNTA(I14:AL14)-COUNTIF(I14:AL14,"CT") -> 24
A15: Active | B15: HOLA003 | C15: Trần Thị Lệ Sáng | D15: Subcontractor | E15: Subcontractor | F15: Factory | I15: Sáng - Mặn - Xưởng | L15: Sáng - Mặn - Xưởng | M15: Sáng - Mặn - Xưởng | O15: Sáng - Mặn - Xưởng | P15: Sáng - Mặn - Xưởng | Q15: Sáng - Mặn - Xưởng | R15: Sáng - Mặn - Xưởng | S15: Sáng - Mặn - Xưởng | T15: Sáng - Mặn - Xưởng | V15: Sáng - Mặn - Xưởng | W15: Sáng - Mặn - Xưởng | X15: Sáng - Mặn - Xưởng | Y15: Sáng - Mặn - Xưởng | Z15: Sáng - Mặn - Xưởng | AA15: Sáng - Mặn - Xưởng | AC15: Sáng - Mặn - Xưởng | AD15: Sáng - Mặn - Xưởng | AE15: Sáng - Mặn - Xưởng | AF15: Sáng - Mặn - Xưởng | AG15: Sáng - Mặn - Xưởng | AH15: Sáng - Mặn - Xưởng | AK15: Sáng - Mặn - Xưởng | AL15: Sáng - Mặn - Xưởng | AM15: =COUNTA(I15:AL15)-COUNTIF(I15:AL15,"CT") -> 23
A16: Active | B16: HOLA004 | C16: Nguyễn Thị Chỉnh | D16: Subcontractor | E16: Subcontractor | F16: Office | G16: Chay | L16: Sáng - Chay - VP | M16: Sáng - Chay - VP | O16: Sáng - Chay - VP | P16: Sáng - Chay - VP | Q16: Sáng - Chay - VP | R16: Sáng - Chay - VP | S16: Sáng - Chay - VP | T16: Sáng - Chay - VP | V16: Sáng - Chay - VP | W16: Sáng - Chay - VP | X16: Sáng - Chay - VP | Y16: Sáng - Chay - VP | Z16: Sáng - Chay - VP | AA16: Sáng - Chay - VP | AC16: Sáng - Chay - VP | AD16: Sáng - Chay - VP | AE16: Sáng - Chay - VP | AF16: Sáng - Chay - VP | AG16: Sáng - Chay - VP | AH16: Sáng - Chay - VP | AJ16: Sáng - Chay - VP | AK16: Sáng - Chay - VP | AL16: Sáng - Chay - VP | AM16: =COUNTA(I16:AL16)-COUNTIF(I16:AL16,"CT") -> 23
A17: Active | B17: HOLA005 | C17: Nguyễn Thị Chín | D17: Subcontractor | E17: Subcontractor | F17: Factory | I17: Sáng - Mặn - Xưởng | L17: Sáng - Mặn - Xưởng | M17: Sáng - Mặn - Xưởng | O17: Sáng - Mặn - Xưởng | P17: Sáng - Mặn - Xưởng | Q17: Sáng - Mặn - Xưởng | R17: Sáng - Mặn - Xưởng | S17: Sáng - Mặn - Xưởng | T17: Sáng - Mặn - Xưởng | V17: Sáng - Mặn - Xưởng | W17: Sáng - Mặn - Xưởng | X17: Sáng - Mặn - Xưởng | Y17: Sáng - Mặn - Xưởng | Z17: Sáng - Mặn - Xưởng | AA17: Sáng - Mặn - Xưởng | AC17: Sáng - Mặn - Xưởng | AD17: Sáng - Mặn - Xưởng | AE17: Sáng - Mặn - Xưởng | AF17: Sáng - Mặn - Xưởng | AG17: Sáng - Mặn - Xưởng | AH17: Sáng - Mặn - Xưởng | AJ17: Sáng - Mặn - Xưởng | AK17: Sáng - Mặn - Xưởng | AL17: Sáng - Mặn - Xưởng | AM17: =COUNTA(I17:AL17)-COUNTIF(I17:AL17,"CT") -> 24
A18: Active | B18: PTT0451 | C18: Trần Huy Cường | D18: Pro - Packaging | E18: Pro - Packaging | F18: Factory | I18: Sáng - Mặn - Xưởng | M18: Sáng - Mặn - Xưởng | AM18: =COUNTA(I18:AL18)-COUNTIF(I18:AL18,"CT") -> 2
A19: Active | B19: PTT0583 | C19: Võ Thị Ánh Nguyệt | D19: Pro - Aging | E19: Pro - Aging | F19: Factory | I19: Sáng - Mặn - Xưởng | M19: Sáng - Mặn - Xưởng | N19: Sáng - Mặn - Xưởng | AM19: =COUNTA(I19:AL19)-COUNTIF(I19:AL19,"CT") -> 3
A20: Active | B20: PTT0591 | C20: Nguyễn Thị Thủy | D20: Pro - Aging | E20: Pro - Aging | F20: Factory | I20: Sáng - Mặn - Xưởng | AM20: =COUNTA(I20:AL20)-COUNTIF(I20:AL20,"CT") -> 1
A21: Active | B21: PTT0592 | C21: Nguyễn Thị Hương | D21: Pro - Aging | E21: Pro - Aging | F21: Factory | I21: Sáng - Mặn - Xưởng | L21: Sáng - Mặn - Xưởng | M21: Sáng - Mặn - Xưởng | AM21: =COUNTA(I21:AL21)-COUNTIF(I21:AL21,"CT") -> 3
A22: Active | B22: PTT0593 | C22: Nguyễn Thị Thanh Huyền | D22: Pro - Aging | E22: Pro - Aging | F22: Factory | I22: Sáng - Mặn - Xưởng | L22: Sáng - Mặn - Xưởng | AM22: =COUNTA(I22:AL22)-COUNTIF(I22:AL22,"CT") -> 2
A23: Active | B23: PTT0598 | C23: Nguyễn Hải Yến | D23: Pro - Packaging | E23: Pro - Packaging | F23: Factory | I23: Sáng - Mặn - Xưởng | M23: Sáng - Mặn - Xưởng | N23: Sáng - Mặn - Xưởng | AM23: =COUNTA(I23:AL23)-COUNTIF(I23:AL23,"CT") -> 3
A24: Active | B24: PTT0599 | C24: Trịnh Thị Nương Em | D24: Pro - Packaging | E24: Pro - Packaging | F24: Factory | I24: Sáng - Mặn - Xưởng | AM24: =COUNTA(I24:AL24)-COUNTIF(I24:AL24,"CT") -> 1
A25: Active | B25: PTT0615 | C25: Nguyễn Văn Phước | D25: Pro - Packaging | E25: Pro - Packaging | F25: Factory | I25: Sáng - Mặn - Xưởng | M25: Sáng - Mặn - Xưởng | N25: Sáng - Mặn - Xưởng | AM25: =COUNTA(I25:AL25)-COUNTIF(I25:AL25,"CT") -> 3
A26: Active | B26: VCV0797 | C26: Từ Tuấn Tú | D26: Pro - Packaging | E26: Pro - Packaging | F26: Factory | I26: Sáng - Mặn - Xưởng | L26: Sáng - Mặn - Xưởng | M26: Sáng - Mặn - Xưởng | N26: Sáng - Mặn - Xưởng | O26: Sáng - Mặn - Xưởng | P26: Sáng - Mặn - Xưởng | Q26: Sáng - Mặn - Xưởng | R26: Sáng - Mặn - Xưởng | S26: Sáng - Mặn - Xưởng | T26: Sáng - Mặn - Xưởng | V26: Sáng - Mặn - Xưởng | W26: Sáng - Mặn - Xưởng | X26: Sáng - Mặn - Xưởng | Y26: Sáng - Mặn - Xưởng | Z26: Sáng - Mặn - Xưởng | AA26: Sáng - Mặn - Xưởng | AB26: Sáng - Mặn - Xưởng | AC26: Sáng - Mặn - Xưởng | AD26: Sáng - Mặn - Xưởng | AE26: Sáng - Mặn - Xưởng | AG26: Sáng - Mặn - Xưởng | AH26: Sáng - Mặn - Xưởng | AJ26: Sáng - Mặn - Xưởng | AK26: Sáng - Mặn - Xưởng | AL26: Sáng - Mặn - Xưởng | AM26: =COUNTA(I26:AL26)-COUNTIF(I26:AL26,"CT") -> 25
A27: Active | B27: VCV0796 | C27: Lý Văn Luôl | D27: Pro - Packaging | E27: Pro - Packaging | F27: Factory | I27: Sáng - Mặn - Xưởng | L27: Sáng - Mặn - Xưởng | M27: Sáng - Mặn - Xưởng | N27: Sáng - Mặn - Xưởng | O27: Sáng - Mặn - Xưởng | P27: Sáng - Mặn - Xưởng | Q27: Sáng - Mặn - Xưởng | R27: Sáng - Mặn - Xưởng | S27: Sáng - Mặn - Xưởng | T27: Sáng - Mặn - Xưởng | V27: Sáng - Mặn - Xưởng | W27: Sáng - Mặn - Xưởng | X27: Sáng - Mặn - Xưởng | Y27: Sáng - Mặn - Xưởng | Z27: Sáng - Mặn - Xưởng | AA27: Sáng - Mặn - Xưởng | AB27: Sáng - Mặn - Xưởng | AC27: Sáng - Mặn - Xưởng | AD27: Sáng - Mặn - Xưởng | AE27: Sáng - Mặn - Xưởng | AF27: Sáng - Mặn - Xưởng | AG27: Sáng - Mặn - Xưởng | AH27: Sáng - Mặn - Xưởng | AJ27: Sáng - Mặn - Xưởng | AK27: Sáng - Mặn - Xưởng | AL27: Sáng - Mặn - Xưởng | AM27: =COUNTA(I27:AL27)-COUNTIF(I27:AL27,"CT") -> 26
A28: Active | B28: VCV0794 | C28: Khưu Thị Cẩm Lai | D28: Pro - Packaging | E28: Pro - Packaging | F28: Factory | I28: Sáng - Mặn - Xưởng | L28: Sáng - Mặn - Xưởng | M28: Sáng - Mặn - Xưởng | N28: Sáng - Mặn - Xưởng | O28: Sáng - Mặn - Xưởng | P28: Sáng - Mặn - Xưởng | Q28: Sáng - Mặn - Xưởng | R28: Sáng - Mặn - Xưởng | T28: Sáng - Mặn - Xưởng | V28: Sáng - Mặn - Xưởng | W28: Sáng - Mặn - Xưởng | X28: Sáng - Mặn - Xưởng | Y28: Sáng - Mặn - Xưởng | Z28: Sáng - Mặn - Xưởng | AA28: Sáng - Mặn - Xưởng | AC28: Sáng - Mặn - Xưởng | AD28: Sáng - Mặn - Xưởng | AE28: Sáng - Mặn - Xưởng | AF28: Sáng - Mặn - Xưởng | AG28: Sáng - Mặn - Xưởng | AH28: Sáng - Mặn - Xưởng | AI28: Sáng - Mặn - Xưởng | AJ28: Sáng - Mặn - Xưởng | AK28: Sáng - Mặn - Xưởng | AL28: Sáng - Mặn - Xưởng | AM28: =COUNTA(I28:AL28)-COUNTIF(I28:AL28,"CT") -> 25
A29: Active | B29: PTT0636 | C29: Hà Thị Thanh | D29: Pro - Aging | E29: Pro - Aging | F29: Factory | I29: Sáng - Mặn - Xưởng | L29: Sáng - Mặn - Xưởng | M29: Sáng - Mặn - Xưởng | AM29: =COUNTA(I29:AL29)-COUNTIF(I29:AL29,"CT") -> 3
A30: Active | B30: PTT0637 | C30: Đào Thị Kim Oanh | D30: Pro - Aging | E30: Pro - Aging | F30: Factory | I30: Sáng - Mặn - Xưởng | L30: Sáng - Mặn - Xưởng | M30: Sáng - Mặn - Xưởng | AM30: =COUNTA(I30:AL30)-COUNTIF(I30:AL30,"CT") -> 3
A31: Active | B31: VCV0795 | C31: Trần Thị Quỳnh Như | D31: Pro - Packaging | E31: Pro - Packaging | F31: Factory | I31: Sáng - Mặn - Xưởng | L31: Sáng - Mặn - Xưởng | M31: Sáng - Mặn - Xưởng | O31: Sáng - Mặn - Xưởng | P31: Sáng - Mặn - Xưởng | Q31: Sáng - Mặn - Xưởng | R31: Sáng - Mặn - Xưởng | S31: Sáng - Mặn - Xưởng | T31: Sáng - Mặn - Xưởng | V31: Sáng - Mặn - Xưởng | W31: Sáng - Mặn - Xưởng | X31: Sáng - Mặn - Xưởng | Y31: Sáng - Mặn - Xưởng | Z31: Sáng - Mặn - Xưởng | AA31: Sáng - Mặn - Xưởng | AC31: Sáng - Mặn - Xưởng | AD31: Sáng - Mặn - Xưởng | AE31: Sáng - Mặn - Xưởng | AF31: Sáng - Mặn - Xưởng | AG31: Sáng - Mặn - Xưởng | AH31: Sáng - Mặn - Xưởng | AI31: Sáng - Mặn - Xưởng | AJ31: Sáng - Mặn - Xưởng | AK31: Sáng - Mặn - Xưởng | AL31: Sáng - Mặn - Xưởng | AM31: =COUNTA(I31:AL31)-COUNTIF(I31:AL31,"CT") -> 25
A32: Active | B32: VCV0793 | C32: Võ Thị Kim Chung | D32: Pro - Packaging | E32: Pro - Packaging | F32: Factory | I32: Sáng - Mặn - Xưởng | L32: Sáng - Mặn - Xưởng | M32: Sáng - Mặn - Xưởng | N32: Sáng - Mặn - Xưởng | O32: Sáng - Mặn - Xưởng | P32: Sáng - Mặn - Xưởng | Q32: Sáng - Mặn - Xưởng | R32: Sáng - Mặn - Xưởng | AM32: =COUNTA(I32:AL32)-COUNTIF(I32:AL32,"CT") -> 8
A33: Active | B33: TNBH0020 | C33: Lê Tuyết Anh | D33: Pro - Packaging | E33: Pro - Packaging | F33: Factory | I33: Sáng - Mặn - Xưởng | M33: Sáng - Mặn - Xưởng | N33: Sáng - Mặn - Xưởng | AM33: =COUNTA(I33:AL33)-COUNTIF(I33:AL33,"CT") -> 3
A34: Active | B34: VCV0002 | C34: Dương Thị Vy Thảo | D34: HR Admin | E34: HR Admin | F34: Factory | I34: Sáng - Mặn - Xưởng | L34: Sáng - Mặn - Xưởng | M34: Sáng - Mặn - Xưởng | O34: Sáng - Mặn - Xưởng | P34: Sáng - Mặn - Xưởng | Q34: Sáng - Mặn - Xưởng | R34: Sáng - Mặn - Xưởng | S34: Sáng - Mặn - Xưởng | T34: Sáng - Mặn - Xưởng | V34: Sáng - Mặn - Xưởng | W34: Sáng - Mặn - Xưởng | X34: Sáng - Mặn - Xưởng | Y34: Sáng - Mặn - Xưởng | Z34: Sáng - Mặn - Xưởng | AA34: Sáng - Mặn - Xưởng | AC34: Sáng - Mặn - Xưởng | AD34: Sáng - Mặn - Xưởng | AE34: Sáng - Mặn - Xưởng | AF34: Sáng - Mặn - Xưởng | AG34: Sáng - Mặn - Xưởng | AH34: Sáng - Mặn - Xưởng | AJ34: Sáng - Mặn - Xưởng | AK34: Sáng - Mặn - Xưởng | AL34: Sáng - Mặn - Xưởng | AM34: =COUNTA(I34:AL34)-COUNTIF(I34:AL34,"CT") -> 24
A35: Active | B35: VCV0752 | C35: Dương Anh Thư | D35: HR Admin | E35: HR Admin | F35: Office | I35: Sáng - Mặn - VP | L35: Sáng - Mặn - VP | M35: Sáng - Mặn - VP | O35: Sáng - Mặn - VP | Q35: Sáng - Mặn - VP | R35: Sáng - Mặn - VP | S35: Sáng - Mặn - VP | T35: Sáng - Mặn - VP | V35: Sáng - Mặn - VP | W35: Sáng - Mặn - VP | X35: Sáng - Mặn - VP | Y35: Sáng - Mặn - VP | Z35: Sáng - Mặn - VP | AA35: Sáng - Mặn - VP | AC35: Sáng - Mặn - VP | AD35: Sáng - Mặn - VP | AE35: Sáng - Mặn - VP | AF35: Sáng - Mặn - VP | AG35: Sáng - Mặn - VP | AH35: Sáng - Mặn - VP | AJ35: Sáng - Mặn - VP | AK35: Sáng - Mặn - VP | AL35: Sáng - Mặn - VP | AM35: =COUNTA(I35:AL35)-COUNTIF(I35:AL35,"CT") -> 23
A36: Active | B36: VCV0004 | C36: Trần Thu Thủy | D36: PMC - Quality | E36: PMC - Quality | F36: Factory | O36: Sáng - Mặn - VP | Q36: Sáng - Mặn - VP | R36: Sáng - Mặn - VP | S36: Sáng - Mặn - VP | T36: Sáng - Mặn - VP | V36: Sáng - Mặn - VP | W36: Sáng - Mặn - VP | X36: Sáng - Mặn - Xưởng | Y36: Sáng - Mặn - Xưởng | Z36: Sáng - Mặn - Xưởng | AA36: Sáng - Mặn - Xưởng | AC36: Sáng - Mặn - Xưởng | AD36: Sáng - Mặn - Xưởng | AE36: Sáng - Mặn - Xưởng | AF36: Sáng - Mặn - Xưởng | AG36: Sáng - Mặn - Xưởng | AH36: Sáng - Mặn - Xưởng | AJ36: Sáng - Mặn - Xưởng | AK36: Sáng - Mặn - Xưởng | AL36: CT | AM36: =COUNTA(I36:AL36)-COUNTIF(I36:AL36,"CT") -> 19
A37: Active | B37: VCV0007 | C37: Hoàng Thị Thanh Xuân | D37: COO - Assistant | E37: COO Office | F37: Office | I37: Sáng - Mặn - VP | L37: Sáng - Mặn - VP | M37: Sáng - Mặn - VP | O37: Sáng - Mặn - VP | P37: Sáng - Mặn - VP | R37: Sáng - Mặn - VP | S37: Sáng - Mặn - VP | T37: Sáng - Mặn - VP | V37: Sáng - Mặn - VP | W37: Sáng - Mặn - VP | X37: Sáng - Mặn - VP | Y37: Sáng - Mặn - VP | Z37: Sáng - Mặn - VP | AA37: Sáng - Mặn - VP | AC37: Sáng - Mặn - VP | AD37: Sáng - Mặn - VP | AE37: Sáng - Mặn - VP | AF37: Sáng - Mặn - VP | AG37: Sáng - Mặn - VP | AH37: Sáng - Mặn - VP | AJ37: Sáng - Mặn - VP | AK37: Sáng - Mặn - VP | AL37: Sáng - Mặn - VP | AM37: =COUNTA(I37:AL37)-COUNTIF(I37:AL37,"CT") -> 23
A38: Active | B38: VCV0009 | C38: Nguyễn Hoàng Khang | D38: COO - Maintenance | E38: COO Office | F38: Factory | I38: Sáng - Mặn - Xưởng | L38: Sáng - Mặn - Xưởng | M38: Sáng - Mặn - Xưởng | O38: Sáng - Mặn - Xưởng | P38: Sáng - Mặn - Xưởng | Q38: Sáng - Mặn - Xưởng | R38: Sáng - Mặn - Xưởng | S38: Sáng - Mặn - Xưởng | T38: Sáng - Mặn - Xưởng | V38: Sáng - Mặn - Xưởng | W38: Sáng - Mặn - Xưởng | X38: Sáng - Mặn - Xưởng | Y38: Sáng - Mặn - Xưởng | Z38: Sáng - Mặn - Xưởng | AA38: Sáng - Mặn - Xưởng | AC38: Sáng - Mặn - Xưởng | AD38: Sáng - Mặn - Xưởng | AF38: Sáng - Mặn - Xưởng | AG38: Sáng - Mặn - Xưởng | AH38: Sáng - Mặn - Xưởng | AJ38: Sáng - Mặn - Xưởng | AK38: Sáng - Mặn - Xưởng | AL38: Sáng - Mặn - Xưởng | AM38: =COUNTA(I38:AL38)-COUNTIF(I38:AL38,"CT") -> 23
A39: Active | B39: VCV0011 | C39: Nguyễn Thị Minh Hiền | D39: COO - Purchasing | E39: COO Office | F39: Factory | I39: Sáng - Mặn - Xưởng | L39: Sáng - Mặn - Xưởng | M39: Sáng - Mặn - Xưởng | O39: Sáng - Mặn - Xưởng | P39: Sáng - Mặn - Xưởng | Q39: Sáng - Mặn - Xưởng | R39: Sáng - Mặn - Xưởng | S39: Sáng - Mặn - Xưởng | T39: Sáng - Mặn - Xưởng | V39: Sáng - Mặn - Xưởng | W39: Sáng - Mặn - Xưởng | X39: Sáng - Mặn - Xưởng | Y39: Sáng - Mặn - Xưởng | Z39: Sáng - Mặn - Xưởng | AA39: Sáng - Mặn - Xưởng | AC39: Sáng - Mặn - Xưởng | AD39: Sáng - Mặn - Xưởng | AE39: Sáng - Mặn - Xưởng | AF39: Sáng - Mặn - Xưởng | AG39: Sáng - Mặn - Xưởng | AH39: Sáng - Mặn - Xưởng | AJ39: Sáng - Mặn - Xưởng | AK39: Sáng - Mặn - Xưởng | AL39: Sáng - Mặn - Xưởng | AM39: =COUNTA(I39:AL39)-COUNTIF(I39:AL39,"CT") -> 24
A40: Active | B40: VCV0012 | C40: Nguyễn Kim Chi | D40: PMC - Plan | E40: PMC - Plan | F40: Office | I40: Sáng - Mặn - VP | L40: Sáng - Mặn - VP | M40: Sáng - Mặn - VP | O40: Sáng - Mặn - VP | P40: Sáng - Mặn - VP | Q40: Sáng - Mặn - VP | R40: Sáng - Mặn - VP | S40: Sáng - Mặn - VP | T40: Sáng - Mặn - VP | V40: Sáng - Mặn - VP | W40: Sáng - Mặn - VP | X40: Sáng - Mặn - VP | Y40: Sáng - Mặn - VP | Z40: Sáng - Mặn - VP | AC40: Sáng - Mặn - VP | AD40: Sáng - Mặn - VP | AE40: Sáng - Mặn - VP | AF40: Sáng - Mặn - VP | AG40: Sáng - Mặn - VP | AH40: Sáng - Mặn - VP | AK40: Sáng - Mặn - VP | AL40: Sáng - Mặn - VP | AM40: =COUNTA(I40:AL40)-COUNTIF(I40:AL40,"CT") -> 22
A41: Active | B41: VCV0015 | C41: Trương Phát Minh | D41: COO - IT | E41: COO Office | F41: Factory | M41: Sáng - Mặn - Xưởng | O41: Sáng - Mặn - Xưởng | P41: Sáng - Mặn - Xưởng | Q41: Sáng - Mặn - Xưởng | R41: Sáng - Mặn - Xưởng | S41: Sáng - Mặn - Xưởng | T41: Sáng - Mặn - Xưởng | W41: Sáng - Mặn - Xưởng | X41: Sáng - Mặn - Xưởng | Y41: Sáng - Mặn - Xưởng | AA41: Sáng - Mặn - Xưởng | AC41: Sáng - Mặn - Xưởng | AD41: Sáng - Mặn - Xưởng | AE41: Sáng - Mặn - Xưởng | AF41: Sáng - Mặn - VP | AG41: Sáng - Mặn - VP | AH41: Sáng - Mặn - Xưởng | AJ41: Sáng - Mặn - VP | AK41: Sáng - Mặn - VP | AL41: Sáng - Mặn - VP | AM41: =COUNTA(I41:AL41)-COUNTIF(I41:AL41,"CT") -> 20
A42: Active | B42: VCV0018 | C42: Vương Nhựt Lân | D42: Pro - Welding | E42: Pro - Welding | F42: Factory | I42: Sáng - Mặn - Xưởng | L42: Sáng - Mặn - Xưởng | M42: Sáng - Mặn - Xưởng | O42: Sáng - Mặn - Xưởng | P42: Sáng - Mặn - Xưởng | Q42: Sáng - Mặn - Xưởng | R42: Sáng - Mặn - Xưởng | S42: Sáng - Mặn - Xưởng | T42: Sáng - Mặn - Xưởng | V42: Sáng - Mặn - Xưởng | W42: Sáng - Mặn - Xưởng | X42: Sáng - Mặn - Xưởng | Y42: Sáng - Mặn - Xưởng | Z42: Sáng - Mặn - Xưởng | AA42: Sáng - Mặn - Xưởng | AC42: Sáng - Mặn - Xưởng | AD42: Sáng - Mặn - Xưởng | AE42: Sáng - Mặn - Xưởng | AF42: Sáng - Mặn - Xưởng | AG42: Sáng - Mặn - Xưởng | AH42: Sáng - Mặn - Xưởng | AJ42: Sáng - Mặn - Xưởng | AK42: Sáng - Mặn - Xưởng | AL42: Sáng - Mặn - Xưởng | AM42: =COUNTA(I42:AL42)-COUNTIF(I42:AL42,"CT") -> 24
A43: Active | B43: VCV0019 | C43: Nguyễn Quốc Anh | D43: Pro - Welding | E43: Pro - Welding | F43: Factory | I43: Sáng - Mặn - Xưởng | L43: Sáng - Mặn - Xưởng | M43: Sáng - Mặn - Xưởng | O43: Sáng - Mặn - Xưởng | P43: Sáng - Mặn - Xưởng | Q43: Sáng - Mặn - Xưởng | R43: Sáng - Mặn - Xưởng | S43: Sáng - Mặn - Xưởng | T43: Sáng - Mặn - Xưởng | V43: Sáng - Mặn - Xưởng | W43: Sáng - Mặn - Xưởng | X43: Sáng - Mặn - Xưởng | Y43: Sáng - Mặn - Xưởng | Z43: Sáng - Mặn - Xưởng | AA43: Sáng - Mặn - Xưởng | AC43: Sáng - Mặn - Xưởng | AD43: Sáng - Mặn - Xưởng | AE43: Sáng - Mặn - Xưởng | AF43: Sáng - Mặn - Xưởng | AH43: Sáng - Mặn - Xưởng | AJ43: Sáng - Mặn - Xưởng | AK43: Sáng - Mặn - Xưởng | AL43: Sáng - Mặn - Xưởng | AM43: =COUNTA(I43:AL43)-COUNTIF(I43:AL43,"CT") -> 23
A44: Active | B44: VCV0024 | C44: Huỳnh Thị Huyền Trang | D44: PMC - Quality | E44: PMC - Quality | F44: Factory | I44: Sáng - Mặn - Xưởng | L44: CT | M44: CT | O44: Sáng - Mặn - Xưởng | P44: Sáng - Mặn - Xưởng | Q44: Sáng - Mặn - Xưởng | R44: CT | T44: CT | V44: CT | W44: CT | X44: CT | Y44: CT | Z44: CT | AA44: CT | AC44: CT | AD44: CT | AE44: CT | AF44: CT | AG44: CT | AH44: CT | AJ44: CT | AK44: CT | AL44: Sáng - Mặn - Xưởng | AM44: =COUNTA(I44:AL44)-COUNTIF(I44:AL44,"CT") -> 5
A45: Active | B45: VCV0025 | C45: Phạm Thị Ngọc Diễm | D45: Pro - Data | E45: Pro - Data | F45: Office | I45: Sáng - Mặn - VP | L45: Sáng - Mặn - VP | M45: Sáng - Mặn - VP | O45: Sáng - Mặn - VP | P45: Sáng - Mặn - VP | Q45: Sáng - Mặn - VP | R45: Sáng - Mặn - VP | S45: Sáng - Mặn - VP | T45: Sáng - Mặn - VP | V45: Sáng - Mặn - VP | W45: Sáng - Mặn - VP | X45: Sáng - Mặn - VP | Y45: Sáng - Mặn - VP | Z45: Sáng - Mặn - VP | AA45: Sáng - Mặn - VP | AC45: Sáng - Mặn - VP | AD45: Sáng - Mặn - VP | AF45: Sáng - Mặn - VP | AG45: Sáng - Mặn - VP | AH45: Sáng - Mặn - VP | AI45: Sáng - Mặn - Xưởng | AJ45: Sáng - Mặn - VP | AK45: Sáng - Mặn - VP | AL45: Sáng - Mặn - VP | AM45: =COUNTA(I45:AL45)-COUNTIF(I45:AL45,"CT") -> 24
A46: Active | B46: VCV0028 | C46: Bùi Long Phi | D46: Pro - Polishing | E46: Pro - Polishing | F46: Factory | I46: Sáng - Mặn - Xưởng | L46: Sáng - Mặn - Xưởng | M46: Sáng - Mặn - Xưởng | O46: Sáng - Mặn - Xưởng | P46: Sáng - Mặn - Xưởng | Q46: Sáng - Mặn - Xưởng | R46: Sáng - Mặn - Xưởng | S46: Sáng - Mặn - Xưởng | T46: Sáng - Mặn - Xưởng | V46: Sáng - Mặn - Xưởng | W46: Sáng - Mặn - Xưởng | AM46: =COUNTA(I46:AL46)-COUNTIF(I46:AL46,"CT") -> 11
A47: Active | B47: VCV0029 | C47: Đoàn Thị Chút | D47: Pro - Packaging | E47: Pro - Packaging | F47: Factory | I47: Sáng - Mặn - Xưởng | L47: Sáng - Mặn - Xưởng | M47: Sáng - Mặn - Xưởng | N47: Sáng - Mặn - Xưởng | O47: Sáng - Mặn - Xưởng | P47: Sáng - Mặn - Xưởng | Q47: Sáng - Mặn - Xưởng | R47: Sáng - Mặn - Xưởng | S47: Sáng - Mặn - Xưởng | T47: Sáng - Mặn - Xưởng | V47: Sáng - Mặn - Xưởng | W47: Sáng - Mặn - Xưởng | X47: Sáng - Mặn - Xưởng | Y47: Sáng - Mặn - Xưởng | Z47: Sáng - Mặn - Xưởng | AA47: Sáng - Mặn - Xưởng | AB47: Sáng - Mặn - Xưởng | AC47: Sáng - Mặn - Xưởng | AD47: Sáng - Mặn - Xưởng | AE47: Sáng - Mặn - Xưởng | AF47: Sáng - Mặn - Xưởng | AG47: Sáng - Mặn - Xưởng | AH47: Sáng - Mặn - Xưởng | AI47: Sáng - Mặn - Xưởng | AJ47: Sáng - Mặn - Xưởng | AK47: Sáng - Mặn - Xưởng | AL47: Sáng - Mặn - Xưởng | AM47: =COUNTA(I47:AL47)-COUNTIF(I47:AL47,"CT") -> 27
A48: Active | B48: VCV0031 | C48: Thòng Cooc Làn | D48: Pro - Aging | E48: Pro - Aging | F48: Factory | I48: Sáng - Mặn - Xưởng | L48: Sáng - Mặn - Xưởng | M48: Sáng - Mặn - Xưởng | O48: Sáng - Mặn - Xưởng | T48: Sáng - Mặn - Xưởng | V48: Sáng - Mặn - Xưởng | W48: Sáng - Mặn - Xưởng | X48: Sáng - Mặn - Xưởng | Y48: Sáng - Mặn - Xưởng | Z48: Sáng - Mặn - Xưởng | AA48: Sáng - Mặn - Xưởng | AC48: Sáng - Mặn - Xưởng | AD48: Sáng - Mặn - Xưởng | AE48: Sáng - Mặn - Xưởng | AF48: Sáng - Mặn - Xưởng | AG48: Sáng - Mặn - Xưởng | AH48: Sáng - Mặn - Xưởng | AJ48: Sáng - Mặn - Xưởng | AK48: Sáng - Mặn - Xưởng | AL48: Sáng - Mặn - Xưởng | AM48: =COUNTA(I48:AL48)-COUNTIF(I48:AL48,"CT") -> 20
A49: Active | B49: VCV0032 | C49: Nguyễn Thị Ngọc Trâm | D49: Pro - Aging | E49: Pro - Aging | F49: Factory | I49: Sáng - Mặn - Xưởng | L49: Sáng - Mặn - Xưởng | M49: Sáng - Mặn - Xưởng | O49: Sáng - Mặn - Xưởng | P49: Sáng - Mặn - Xưởng | Q49: Sáng - Mặn - Xưởng | R49: Sáng - Mặn - Xưởng | V49: Sáng - Mặn - Xưởng | W49: Sáng - Mặn - Xưởng | X49: Sáng - Mặn - Xưởng | Y49: Sáng - Mặn - Xưởng | Z49: Sáng - Mặn - Xưởng | AA49: Sáng - Mặn - Xưởng | AC49: Sáng - Mặn - Xưởng | AD49: Sáng - Mặn - Xưởng | AE49: Sáng - Mặn - Xưởng | AF49: Sáng - Mặn - Xưởng | AG49: Sáng - Mặn - Xưởng | AH49: Sáng - Mặn - Xưởng | AJ49: Sáng - Mặn - Xưởng | AK49: Sáng - Mặn - Xưởng | AL49: Sáng - Mặn - Xưởng | AM49: =COUNTA(I49:AL49)-COUNTIF(I49:AL49,"CT") -> 22
A50: Active | B50: VCV0033 | C50: Nguyễn Phương Thanh | D50: Pro - Aging | E50: Pro - Aging | F50: Factory | I50: Sáng - Mặn - Xưởng | L50: Sáng - Mặn - Xưởng | M50: Sáng - Mặn - Xưởng | O50: Sáng - Mặn - Xưởng | P50: Sáng - Mặn - Xưởng | Q50: Sáng - Mặn - Xưởng | R50: Sáng - Mặn - Xưởng | V50: Sáng - Mặn - Xưởng | W50: Sáng - Mặn - Xưởng | X50: Sáng - Mặn - Xưởng | Y50: Sáng - Mặn - Xưởng | Z50: Sáng - Mặn - Xưởng | AA50: Sáng - Mặn - Xưởng | AC50: Sáng - Mặn - Xưởng | AD50: Sáng - Mặn - Xưởng | AE50: Sáng - Mặn - Xưởng | AG50: Sáng - Mặn - Xưởng | AH50: Sáng - Mặn - Xưởng | AJ50: Sáng - Mặn - Xưởng | AK50: Sáng - Mặn - Xưởng | AL50: Sáng - Mặn - Xưởng | AM50: =COUNTA(I50:AL50)-COUNTIF(I50:AL50,"CT") -> 21
A51: Active | B51: VCV0036 | C51: Bùi Hồng Giang | D51: Pro - Aging | E51: Pro - Aging | F51: Factory | I51: Sáng - Mặn - Xưởng | L51: Sáng - Mặn - Xưởng | M51: Sáng - Mặn - Xưởng | O51: Sáng - Mặn - Xưởng | S51: Sáng - Mặn - Xưởng | T51: Sáng - Mặn - Xưởng | V51: Sáng - Mặn - Xưởng | W51: Sáng - Mặn - Xưởng | X51: Sáng - Mặn - Xưởng | Y51: Sáng - Mặn - Xưởng | Z51: Sáng - Mặn - Xưởng | AA51: Sáng - Mặn - Xưởng | AC51: Sáng - Mặn - Xưởng | AD51: Sáng - Mặn - Xưởng | AE51: Sáng - Mặn - Xưởng | AG51: Sáng - Mặn - Xưởng | AH51: Sáng - Mặn - Xưởng | AJ51: Sáng - Mặn - Xưởng | AK51: Sáng - Mặn - Xưởng | AL51: Sáng - Mặn - Xưởng | AM51: =COUNTA(I51:AL51)-COUNTIF(I51:AL51,"CT") -> 20
A52: Active | B52: VCV0037 | C52: Hồ Thị Quỳnh Thoa | D52: Pro - Aging | E52: Pro - Aging | F52: Factory | I52: Sáng - Mặn - Xưởng | L52: Sáng - Mặn - Xưởng | M52: Sáng - Mặn - Xưởng | O52: Sáng - Mặn - Xưởng | S52: Sáng - Mặn - Xưởng | T52: Sáng - Mặn - Xưởng | V52: Sáng - Mặn - Xưởng | W52: Sáng - Mặn - Xưởng | X52: Sáng - Mặn - Xưởng | Y52: Sáng - Mặn - Xưởng | Z52: Sáng - Mặn - Xưởng | AA52: Sáng - Mặn - Xưởng | AC52: Sáng - Mặn - Xưởng | AD52: Sáng - Mặn - Xưởng | AE52: Sáng - Mặn - Xưởng | AG52: Sáng - Mặn - Xưởng | AH52: Sáng - Mặn - Xưởng | AJ52: Sáng - Mặn - Xưởng | AK52: Sáng - Mặn - Xưởng | AL52: Sáng - Mặn - Xưởng | AM52: =COUNTA(I52:AL52)-COUNTIF(I52:AL52,"CT") -> 20
A53: Active | B53: VCV0041 | C53: Yan Wei | D53: Pro - Expat | E53: Pro - Expat | F53: Chinese | I53: Sáng - Trung | L53: Sáng - Trung | M53: Sáng - Trung | N53: Sáng - Trung | O53: Sáng - Trung | P53: Sáng - Trung | Q53: Sáng - Trung | R53: Sáng - Trung | S53: Sáng - Trung | T53: Sáng - Trung | V53: Sáng - Trung | W53: Sáng - Trung | X53: Sáng - Trung | Y53: Sáng - Trung | Z53: Sáng - Trung | AA53: Sáng - Trung | AB53: Sáng - Trung | AC53: Sáng - Trung | AD53: Sáng - Trung | AE53: Sáng - Trung | AF53: Sáng - Trung | AG53: Sáng - Trung | AH53: Sáng - Trung | AJ53: Sáng - Trung | AK53: Sáng - Trung | AL53: Sáng - Trung | AM53: =COUNTA(I53:AL53)-COUNTIF(I53:AL53,"CT") -> 26
A54: Active | B54: VCV0042 | C54: Chen Jianyun | D54: Pro - Expat | E54: Pro - Expat | F54: Chinese | N54: Sáng - Trung | W54: Sáng - Trung | X54: Sáng - Trung | Y54: Sáng - Trung | Z54: Sáng - Trung | AA54: Sáng - Trung | AC54: Sáng - Trung | AD54: Sáng - Trung | AE54: Sáng - Trung | AF54: Sáng - Trung | AG54: Sáng - Trung | AH54: Sáng - Trung | AJ54: Sáng - Trung | AK54: Sáng - Trung | AL54: Sáng - Trung | AM54: =COUNTA(I54:AL54)-COUNTIF(I54:AL54,"CT") -> 15
A55: Active | B55: VCV0043 | C55: Lu Changxi | D55: Pro - Expat | E55: Pro - Expat | F55: Chinese | I55: CT | L55: CT | M55: CT | O55: CT | P55: CT | Q55: CT | R55: CT | S55: CT | T55: CT | V55: CT | W55: CT | X55: CT | Y55: CT | Z55: CT | AA55: CT | AC55: CT | AD55: CT | AE55: CT | AF55: Sáng - Trung | AG55: CT | AH55: CT | AJ55: CT | AK55: Sáng - Trung | AL55: CT | AM55: =COUNTA(I55:AL55)-COUNTIF(I55:AL55,"CT") -> 2
A56: Active | B56: VCV0044 | C56: Yu Zichun | D56: Pro - Expat | E56: Pro - Expat | F56: Chinese | I56: Sáng - Trung | L56: Sáng - Trung | M56: Sáng - Trung | O56: Sáng - Trung | P56: Sáng - Trung | Q56: Sáng - Trung | R56: Sáng - Trung | S56: Sáng - Trung | T56: Sáng - Trung | V56: Sáng - Trung | W56: Sáng - Trung | X56: Sáng - Trung | Y56: Sáng - Trung | Z56: Sáng - Trung | AA56: Sáng - Trung | AC56: Sáng - Trung | AD56: Sáng - Trung | AE56: Sáng - Trung | AF56: Sáng - Trung | AG56: Sáng - Trung | AH56: Sáng - Trung | AJ56: Sáng - Trung | AK56: Sáng - Trung | AL56: Sáng - Trung | AM56: =COUNTA(I56:AL56)-COUNTIF(I56:AL56,"CT") -> 24
A57: Active | B57: VCV0047 | C57: Chen Xiaojun | D57: Pro - Expat | E57: Pro - Expat | F57: Chinese | I57: Sáng - Trung | L57: Sáng - Trung | M57: Sáng - Trung | O57: Sáng - Trung | P57: Sáng - Trung | Q57: Sáng - Trung | R57: Sáng - Trung | S57: Sáng - Trung | T57: Sáng - Trung | V57: Sáng - Trung | W57: Sáng - Trung | X57: Sáng - Trung | Y57: Sáng - Trung | Z57: Sáng - Trung | AC57: Sáng - Trung | AD57: Sáng - Trung | AE57: Sáng - Trung | AF57: Sáng - Trung | AG57: Sáng - Trung | AH57: Sáng - Trung | AJ57: Sáng - Trung | AK57: Sáng - Trung | AL57: Sáng - Trung | AM57: =COUNTA(I57:AL57)-COUNTIF(I57:AL57,"CT") -> 23
A58: Active | B58: VCV0048 | C58: Ren Mingguang | D58: Pro - Expat | E58: Pro - Expat | F58: Chinese | I58: Sáng - Trung | L58: Sáng - Trung | M58: Sáng - Trung | O58: Sáng - Trung | P58: Sáng - Trung | Q58: Sáng - Trung | R58: Sáng - Trung | S58: Sáng - Trung | T58: Sáng - Trung | V58: Sáng - Trung | W58: Sáng - Trung | X58: Sáng - Trung | Y58: Sáng - Trung | Z58: Sáng - Trung | AA58: Sáng - Trung | AC58: Sáng - Trung | AD58: Sáng - Trung | AE58: Sáng - Trung | AF58: Sáng - Trung | AG58: Sáng - Trung | AH58: Sáng - Trung | AJ58: Sáng - Trung | AK58: Sáng - Trung | AL58: Sáng - Trung | AM58: =COUNTA(I58:AL58)-COUNTIF(I58:AL58,"CT") -> 24
A59: Active | B59: VCV0049 | C59: Yang Xingwen | D59: Pro - Expat | E59: Pro - Expat | F59: Chinese | I59: Sáng - Trung | L59: Sáng - Trung | M59: Sáng - Trung | O59: Sáng - Trung | P59: Sáng - Trung | Q59: Sáng - Trung | R59: Sáng - Trung | S59: Sáng - Trung | T59: Sáng - Trung | V59: Sáng - Trung | W59: Sáng - Trung | X59: Sáng - Trung | Y59: Sáng - Trung | Z59: Sáng - Trung | AA59: Sáng - Trung | AC59: Sáng - Trung | AD59: Sáng - Trung | AE59: Sáng - Trung | AF59: Sáng - Trung | AG59: Sáng - Trung | AH59: Sáng - Trung | AJ59: Sáng - Trung | AK59: Sáng - Trung | AL59: Sáng - Trung | AM59: =COUNTA(I59:AL59)-COUNTIF(I59:AL59,"CT") -> 24
A60: Active | B60: VCV0050 | C60: Luo Goutian | D60: Pro - Expat | E60: Pro - Expat | F60: Chinese | I60: Sáng - Trung | L60: Sáng - Trung | M60: Sáng - Trung | O60: Sáng - Trung | P60: Sáng - Trung | Q60: Sáng - Trung | R60: Sáng - Trung | S60: Sáng - Trung | T60: Sáng - Trung | V60: Sáng - Trung | W60: Sáng - Trung | X60: Sáng - Trung | Y60: Sáng - Trung | Z60: Sáng - Trung | AA60: Sáng - Trung | AC60: Sáng - Trung | AD60: Sáng - Trung | AE60: Sáng - Trung | AF60: Sáng - Trung | AG60: Sáng - Trung | AH60: Sáng - Trung | AJ60: Sáng - Trung | AK60: Sáng - Trung | AL60: Sáng - Trung | AM60: =COUNTA(I60:AL60)-COUNTIF(I60:AL60,"CT") -> 24
A61: Active | B61: VCV0051 | C61: Xu Jingang | D61: Pro - Expat | E61: Pro - Expat | F61: Chinese | I61: Sáng - Trung | L61: Sáng - Trung | M61: Sáng - Trung | O61: Sáng - Trung | P61: Sáng - Trung | Q61: Sáng - Trung | R61: Sáng - Trung | S61: Sáng - Trung | T61: Sáng - Trung | V61: Sáng - Trung | W61: Sáng - Trung | X61: Sáng - Trung | Y61: Sáng - Trung | Z61: Sáng - Trung | AA61: Sáng - Trung | AC61: Sáng - Trung | AD61: Sáng - Trung | AE61: Sáng - Trung | AF61: Sáng - Trung | AG61: Sáng - Trung | AH61: Sáng - Trung | AI61: Sáng - Trung | AJ61: Sáng - Trung | AK61: Sáng - Trung | AL61: Sáng - Trung | AM61: =COUNTA(I61:AL61)-COUNTIF(I61:AL61,"CT") -> 25
A62: Active | B62: VCV0052 | C62: Chen Fengliang | D62: Pro - Expat | E62: Pro - Expat | F62: Chinese | I62: Sáng - Trung | L62: Sáng - Trung | M62: Sáng - Trung | O62: Sáng - Trung | P62: Sáng - Trung | Q62: Sáng - Trung | R62: Sáng - Trung | S62: Sáng - Trung | T62: Sáng - Trung | V62: Sáng - Trung | W62: Sáng - Trung | X62: Sáng - Trung | Y62: Sáng - Trung | Z62: Sáng - Trung | AA62: Sáng - Trung | AC62: Sáng - Trung | AD62: Sáng - Trung | AE62: Sáng - Trung | AF62: Sáng - Trung | AG62: Sáng - Trung | AH62: Sáng - Trung | AJ62: Sáng - Trung | AK62: Sáng - Trung | AL62: Sáng - Trung | AM62: =COUNTA(I62:AL62)-COUNTIF(I62:AL62,"CT") -> 24
A63: Active | B63: VCV0059 | C63: Nguyễn Thị Kiều Nga | D63: COO - Exim | E63: COO Office | F63: Office | I63: Sáng - Mặn - VP | L63: Sáng - Mặn - VP | M63: Sáng - Mặn - VP | O63: Sáng - Mặn - VP | P63: Sáng - Mặn - VP | Q63: Sáng - Mặn - VP | R63: Sáng - Mặn - VP | S63: Sáng - Mặn - VP | T63: Sáng - Mặn - VP | W63: Sáng - Mặn - VP | X63: Sáng - Mặn - VP | Y63: Sáng - Mặn - VP | Z63: Sáng - Mặn - VP | AA63: Sáng - Mặn - VP | AC63: Sáng - Mặn - VP | AD63: Sáng - Mặn - VP | AE63: Sáng - Mặn - VP | AF63: Sáng - Mặn - VP | AG63: Sáng - Mặn - VP | AH63: Sáng - Mặn - VP | AJ63: Sáng - Mặn - VP | AK63: Sáng - Mặn - VP | AL63: Sáng - Mặn - VP | AM63: =COUNTA(I63:AL63)-COUNTIF(I63:AL63,"CT") -> 23
A64: Active | B64: VCV0060 | C64: Vũ Văn Dần | D64: Pro - CNC | E64: Pro - CNC | F64: Factory | I64: Sáng - Mặn - Xưởng | L64: Sáng - Mặn - Xưởng | M64: Sáng - Mặn - Xưởng | V64: Sáng - Mặn - Xưởng | W64: Sáng - Mặn - Xưởng | Y64: Sáng - Mặn - Xưởng | AA64: Sáng - Mặn - Xưởng | AC64: Sáng - Mặn - Xưởng | AD64: Sáng - Mặn - Xưởng | AE64: Sáng - Mặn - Xưởng | AG64: Sáng - Mặn - Xưởng | AH64: Sáng - Mặn - Xưởng | AL64: Sáng - Mặn - Xưởng | AM64: =COUNTA(I64:AL64)-COUNTIF(I64:AL64,"CT") -> 13
A65: Active | B65: VCV0061 | C65: Trần Minh Công | D65: Pro - CNC | E65: Pro - CNC | F65: Factory | I65: Sáng - Mặn - Xưởng | L65: Sáng - Mặn - Xưởng | M65: Sáng - Mặn - Xưởng | P65: Sáng - Mặn - Xưởng | Q65: Sáng - Mặn - Xưởng | R65: Sáng - Mặn - Xưởng | S65: Sáng - Mặn - Xưởng | T65: Sáng - Mặn - Xưởng | V65: Sáng - Mặn - Xưởng | W65: Sáng - Mặn - Xưởng | X65: Sáng - Mặn - Xưởng | Y65: Sáng - Mặn - Xưởng | Z65: Sáng - Mặn - Xưởng | AA65: Sáng - Mặn - Xưởng | AD65: Sáng - Mặn - Xưởng | AG65: Sáng - Mặn - Xưởng | AH65: Sáng - Mặn - Xưởng | AK65: Sáng - Mặn - Xưởng | AL65: Sáng - Mặn - Xưởng | AM65: =COUNTA(I65:AL65)-COUNTIF(I65:AL65,"CT") -> 19
A66: Active | B66: VCV0063 | C66: Trần Cường | D66: PMC - Quality | E66: PMC - Quality | F66: Factory | I66: Sáng - Mặn - Xưởng | L66: Sáng - Mặn - Xưởng | M66: Sáng - Mặn - Xưởng | O66: Sáng - Mặn - Xưởng | P66: Sáng - Mặn - Xưởng | Q66: Sáng - Mặn - Xưởng | R66: Sáng - Mặn - Xưởng | S66: Sáng - Mặn - Xưởng | T66: Sáng - Mặn - Xưởng | V66: Sáng - Mặn - Xưởng | W66: Sáng - Mặn - Xưởng | X66: Sáng - Mặn - Xưởng | Y66: Sáng - Mặn - Xưởng | Z66: Sáng - Mặn - Xưởng | AA66: Sáng - Mặn - Xưởng | AC66: Sáng - Mặn - Xưởng | AD66: Sáng - Mặn - Xưởng | AE66: Sáng - Mặn - Xưởng | AG66: Sáng - Mặn - Xưởng | AH66: Sáng - Mặn - Xưởng | AJ66: Sáng - Mặn - Xưởng | AK66: Sáng - Mặn - Xưởng | AL66: Sáng - Mặn - Xưởng | AM66: =COUNTA(I66:AL66)-COUNTIF(I66:AL66,"CT") -> 23
A67: Active | B67: VCV0065 | C67: Nguyễn Hoàng Vũ | D67: Pro - Manual Lathe | E67: Pro - Manual Lathe | F67: Factory | I67: Sáng - Mặn - Xưởng | L67: Sáng - Mặn - Xưởng | M67: Sáng - Mặn - Xưởng | O67: Sáng - Mặn - Xưởng | P67: Sáng - Mặn - Xưởng | Q67: Sáng - Mặn - Xưởng | R67: Sáng - Mặn - Xưởng | S67: Sáng - Mặn - Xưởng | T67: Sáng - Mặn - Xưởng | V67: Sáng - Mặn - Xưởng | W67: Sáng - Mặn - Xưởng | X67: Sáng - Mặn - Xưởng | Y67: Sáng - Mặn - Xưởng | Z67: Sáng - Mặn - Xưởng | AA67: Sáng - Mặn - Xưởng | AC67: Sáng - Mặn - Xưởng | AD67: Sáng - Mặn - Xưởng | AE67: Sáng - Mặn - Xưởng | AG67: Sáng - Mặn - Xưởng | AH67: Sáng - Mặn - Xưởng | AJ67: Sáng - Mặn - Xưởng | AK67: Sáng - Mặn - Xưởng | AL67: Sáng - Mặn - Xưởng | AM67: =COUNTA(I67:AL67)-COUNTIF(I67:AL67,"CT") -> 23
A68: Active | B68: VCV0069 | C68: Đinh Thị Ngọc Thùy | D68: Pro - Painting | E68: Pro - Painting | F68: Factory | I68: Sáng - Mặn - Xưởng | L68: Sáng - Mặn - Xưởng | M68: Sáng - Mặn - Xưởng | O68: Sáng - Mặn - Xưởng | P68: Sáng - Mặn - Xưởng | Q68: Sáng - Mặn - Xưởng | R68: Sáng - Mặn - Xưởng | S68: Sáng - Mặn - Xưởng | T68: Sáng - Mặn - Xưởng | V68: Sáng - Mặn - Xưởng | W68: Sáng - Mặn - Xưởng | X68: Sáng - Mặn - Xưởng | Y68: Sáng - Mặn - Xưởng | Z68: Sáng - Mặn - Xưởng | AA68: Sáng - Mặn - Xưởng | AC68: Sáng - Mặn - Xưởng | AD68: Sáng - Mặn - Xưởng | AE68: Sáng - Mặn - Xưởng | AG68: Sáng - Mặn - Xưởng | AH68: Sáng - Mặn - Xưởng | AJ68: Sáng - Mặn - Xưởng | AK68: Sáng - Mặn - Xưởng | AM68: =COUNTA(I68:AL68)-COUNTIF(I68:AL68,"CT") -> 22
A69: Active | B69: VCV0072 | C69: Trương Thị Hóa | D69: Pro - Aging | E69: Pro - Aging | F69: Factory | I69: Sáng - Mặn - Xưởng | O69: Sáng - Mặn - Xưởng | S69: Sáng - Mặn - Xưởng | T69: Sáng - Mặn - Xưởng | V69: Sáng - Mặn - Xưởng | W69: Sáng - Mặn - Xưởng | X69: Sáng - Mặn - Xưởng | Y69: Sáng - Mặn - Xưởng | Z69: Sáng - Mặn - Xưởng | AA69: Sáng - Mặn - Xưởng | AC69: Sáng - Mặn - Xưởng | AD69: Sáng - Mặn - Xưởng | AE69: Sáng - Mặn - Xưởng | AG69: Sáng - Mặn - Xưởng | AH69: Sáng - Mặn - Xưởng | AJ69: Sáng - Mặn - Xưởng | AK69: Sáng - Mặn - Xưởng | AL69: Sáng - Mặn - Xưởng | AM69: =COUNTA(I69:AL69)-COUNTIF(I69:AL69,"CT") -> 18
A70: Active | B70: VCV0073 | C70: Nguyễn Thành Dư | D70: Pro - Painting | E70: Pro - Painting | F70: Factory | I70: Sáng - Mặn - Xưởng | L70: Sáng - Mặn - Xưởng | M70: Sáng - Mặn - Xưởng | O70: Sáng - Mặn - Xưởng | P70: Sáng - Mặn - Xưởng | Q70: Sáng - Mặn - Xưởng | R70: Sáng - Mặn - Xưởng | S70: Sáng - Mặn - Xưởng | T70: Sáng - Mặn - Xưởng | V70: Sáng - Mặn - Xưởng | W70: Sáng - Mặn - Xưởng | X70: Sáng - Mặn - Xưởng | Y70: Sáng - Mặn - Xưởng | Z70: Sáng - Mặn - Xưởng | AA70: Sáng - Mặn - Xưởng | AC70: Sáng - Mặn - Xưởng | AD70: Sáng - Mặn - Xưởng | AF70: Sáng - Mặn - Xưởng | AG70: Sáng - Mặn - Xưởng | AH70: Sáng - Mặn - Xưởng | AJ70: Sáng - Mặn - Xưởng | AK70: Sáng - Mặn - Xưởng | AL70: Sáng - Mặn - Xưởng | AM70: =COUNTA(I70:AL70)-COUNTIF(I70:AL70,"CT") -> 23
A71: Active | B71: VCV0085 | C71: Yang Defen | D71: Pro - Expat | E71: Pro - Expat | F71: Chinese | I71: Sáng - Trung | L71: Sáng - Trung | M71: Sáng - Trung | N71: Sáng - Trung | O71: Sáng - Trung | P71: Sáng - Trung | Q71: Sáng - Trung | R71: Sáng - Trung | S71: Sáng - Trung | T71: Sáng - Trung | V71: Sáng - Trung | W71: Sáng - Trung | X71: Sáng - Trung | Y71: Sáng - Trung | Z71: Sáng - Trung | AA71: Sáng - Trung | AC71: Sáng - Trung | AD71: Sáng - Trung | AE71: Sáng - Trung | AF71: Sáng - Trung | AG71: Sáng - Trung | AH71: Sáng - Trung | AJ71: Sáng - Trung | AK71: Sáng - Trung | AL71: Sáng - Trung | AM71: =COUNTA(I71:AL71)-COUNTIF(I71:AL71,"CT") -> 25
A72: Active | B72: VCV0088 | C72: Bùi Thị Vân Anh | D72: Pro - Data | E72: Pro - Data | F72: Factory | I72: Sáng - Mặn - Xưởng | L72: Sáng - Mặn - Xưởng | M72: Sáng - Mặn - Xưởng | O72: Sáng - Mặn - Xưởng | P72: Sáng - Mặn - Xưởng | Q72: Sáng - Mặn - Xưởng | R72: Sáng - Mặn - Xưởng | S72: Sáng - Mặn - Xưởng | T72: Sáng - Mặn - Xưởng | V72: Sáng - Mặn - Xưởng | W72: Sáng - Mặn - Xưởng | X72: Sáng - Mặn - Xưởng | Y72: Sáng - Mặn - Xưởng | Z72: Sáng - Mặn - Xưởng | AA72: Sáng - Mặn - Xưởng | AC72: Sáng - Mặn - Xưởng | AD72: Sáng - Mặn - Xưởng | AE72: Sáng - Mặn - Xưởng | AF72: Sáng - Mặn - Xưởng | AG72: Sáng - Mặn - Xưởng | AH72: Sáng - Mặn - Xưởng | AJ72: Sáng - Mặn - Xưởng | AK72: Sáng - Mặn - Xưởng | AL72: Sáng - Mặn - Xưởng | AM72: =COUNTA(I72:AL72)-COUNTIF(I72:AL72,"CT") -> 24
A73: Active | B73: VCV0091 | C73: Vòng Quyền Chi | D73: Pro - Polishing | E73: Pro - Polishing | F73: Factory | I73: Sáng - Mặn - Xưởng | L73: Sáng - Mặn - Xưởng | M73: Sáng - Mặn - Xưởng | O73: Sáng - Mặn - Xưởng | Q73: Sáng - Mặn - Xưởng | R73: Sáng - Mặn - Xưởng | S73: Sáng - Mặn - Xưởng | T73: Sáng - Mặn - Xưởng | V73: Sáng - Mặn - Xưởng | W73: Sáng - Mặn - Xưởng | X73: Sáng - Mặn - Xưởng | AM73: =COUNTA(I73:AL73)-COUNTIF(I73:AL73,"CT") -> 11
A74: Active | B74: VCV0095 | C74: Siu Dôi | D74: Pro - Manual Lathe | E74: Pro - Manual Lathe | F74: Factory | I74: Sáng - Mặn - Xưởng | L74: Sáng - Mặn - Xưởng | M74: Sáng - Mặn - Xưởng | O74: Sáng - Mặn - Xưởng | P74: Sáng - Mặn - Xưởng | Q74: Sáng - Mặn - Xưởng | R74: Sáng - Mặn - Xưởng | S74: Sáng - Mặn - Xưởng | T74: Sáng - Mặn - Xưởng | V74: Sáng - Mặn - Xưởng | W74: Sáng - Mặn - Xưởng | X74: Sáng - Mặn - Xưởng | Y74: Sáng - Mặn - Xưởng | Z74: Sáng - Mặn - Xưởng | AA74: Sáng - Mặn - Xưởng | AC74: Sáng - Mặn - Xưởng | AD74: Sáng - Mặn - Xưởng | AE74: Sáng - Mặn - Xưởng | AF74: Sáng - Mặn - Xưởng | AG74: Sáng - Mặn - Xưởng | AH74: Sáng - Mặn - Xưởng | AJ74: Sáng - Mặn - Xưởng | AK74: Sáng - Mặn - Xưởng | AL74: Sáng - Mặn - Xưởng | AM74: =COUNTA(I74:AL74)-COUNTIF(I74:AL74,"CT") -> 24
A75: Active | B75: VCV0099 | C75: Lê Thị Kim Hoàng | D75: Pro - Aging | E75: Pro - Aging | F75: Factory | I75: Sáng - Mặn - Xưởng | L75: Sáng - Mặn - Xưởng | M75: Sáng - Mặn - Xưởng | O75: Sáng - Mặn - Xưởng | P75: Sáng - Mặn - Xưởng | Q75: Sáng - Mặn - Xưởng | R75: Sáng - Mặn - Xưởng | V75: Sáng - Mặn - Xưởng | W75: Sáng - Mặn - Xưởng | X75: Sáng - Mặn - Xưởng | Y75: Sáng - Mặn - Xưởng | Z75: Sáng - Mặn - Xưởng | AA75: Sáng - Mặn - Xưởng | AC75: Sáng - Mặn - Xưởng | AD75: Sáng - Mặn - Xưởng | AE75: Sáng - Mặn - Xưởng | AF75: Sáng - Mặn - Xưởng | AG75: Sáng - Mặn - Xưởng | AH75: Sáng - Mặn - Xưởng | AJ75: Sáng - Mặn - Xưởng | AK75: Sáng - Mặn - Xưởng | AL75: Sáng - Mặn - Xưởng | AM75: =COUNTA(I75:AL75)-COUNTIF(I75:AL75,"CT") -> 22
A76: Active | B76: VCV0103 | C76: Lê Thị Hải | D76: Pro - Painting | E76: Pro - Painting | F76: Factory | I76: Sáng - Mặn - Xưởng | L76: Sáng - Mặn - Xưởng | M76: Sáng - Mặn - Xưởng | O76: Sáng - Mặn - Xưởng | P76: Sáng - Mặn - Xưởng | Q76: Sáng - Mặn - Xưởng | R76: Sáng - Mặn - Xưởng | S76: Sáng - Mặn - Xưởng | T76: Sáng - Mặn - Xưởng | V76: Sáng - Mặn - Xưởng | W76: Sáng - Mặn - Xưởng | X76: Sáng - Mặn - Xưởng | Y76: Sáng - Mặn - Xưởng | Z76: Sáng - Mặn - Xưởng | AA76: Sáng - Mặn - Xưởng | AC76: Sáng - Mặn - Xưởng | AD76: Sáng - Mặn - Xưởng | AE76: Sáng - Mặn - Xưởng | AF76: Sáng - Mặn - Xưởng | AG76: Sáng - Mặn - Xưởng | AH76: Sáng - Mặn - Xưởng | AJ76: Sáng - Mặn - Xưởng | AK76: Sáng - Mặn - Xưởng | AL76: Sáng - Mặn - Xưởng | AM76: =COUNTA(I76:AL76)-COUNTIF(I76:AL76,"CT") -> 24
A77: Active | B77: VCV0106 | C77: Phạm Thị Nhung | D77: Pro - Aging | E77: Pro - Aging | F77: Factory | I77: Sáng - Mặn - Xưởng | L77: Sáng - Mặn - Xưởng | M77: Sáng - Mặn - Xưởng | O77: Sáng - Mặn - Xưởng | S77: Sáng - Mặn - Xưởng | T77: Sáng - Mặn - Xưởng | V77: Sáng - Mặn - Xưởng | W77: Sáng - Mặn - Xưởng | X77: Sáng - Mặn - Xưởng | Y77: Sáng - Mặn - Xưởng | Z77: Sáng - Mặn - Xưởng | AA77: Sáng - Mặn - Xưởng | AC77: Sáng - Mặn - Xưởng | AD77: Sáng - Mặn - Xưởng | AE77: Sáng - Mặn - Xưởng | AF77: Sáng - Mặn - Xưởng | AH77: Sáng - Mặn - Xưởng | AJ77: Sáng - Mặn - Xưởng | AK77: Sáng - Mặn - Xưởng | AL77: Sáng - Mặn - Xưởng | AM77: =COUNTA(I77:AL77)-COUNTIF(I77:AL77,"CT") -> 20
A78: Active | B78: VCV0108 | C78: Li WenQiang | D78: Pro - Expat | E78: Pro - Expat | F78: Chinese | I78: Sáng - Trung | L78: Sáng - Trung | M78: Sáng - Trung | O78: Sáng - Trung | P78: Sáng - Trung | Q78: Sáng - Trung | R78: Sáng - Trung | S78: Sáng - Trung | T78: Sáng - Trung | V78: Sáng - Trung | W78: Sáng - Trung | X78: Sáng - Trung | Y78: Sáng - Trung | Z78: Sáng - Trung | AA78: Sáng - Trung | AC78: Sáng - Trung | AD78: Sáng - Trung | AE78: Sáng - Trung | AF78: Sáng - Trung | AG78: Sáng - Trung | AH78: Sáng - Trung | AI78: Sáng - Trung | AJ78: Sáng - Trung | AK78: Sáng - Trung | AL78: Sáng - Trung | AM78: =COUNTA(I78:AL78)-COUNTIF(I78:AL78,"CT") -> 25
A79: Active | B79: VCV0109 | C79: Nguyễn Thị Vân | D79: Pro - Aging | E79: Pro - Aging | F79: Factory | I79: Sáng - Mặn - Xưởng | L79: Sáng - Mặn - Xưởng | M79: Sáng - Mặn - Xưởng | O79: Sáng - Mặn - Xưởng | Q79: Sáng - Mặn - Xưởng | R79: Sáng - Mặn - Xưởng | V79: Sáng - Mặn - Xưởng | W79: Sáng - Mặn - Xưởng | X79: Sáng - Mặn - Xưởng | Y79: Sáng - Mặn - Xưởng | Z79: Sáng - Mặn - Xưởng | AA79: Sáng - Mặn - Xưởng | AC79: Sáng - Mặn - Xưởng | AD79: Sáng - Mặn - Xưởng | AE79: Sáng - Mặn - Xưởng | AF79: Sáng - Mặn - Xưởng | AG79: Sáng - Mặn - Xưởng | AH79: Sáng - Mặn - Xưởng | AJ79: Sáng - Mặn - Xưởng | AK79: Sáng - Mặn - Xưởng | AL79: Sáng - Mặn - Xưởng | AM79: =COUNTA(I79:AL79)-COUNTIF(I79:AL79,"CT") -> 21
A80: Active | B80: VCV0113 | C80: Trần Văn Luyện | D80: Pro - Polishing | E80: Pro - Polishing | F80: Factory | I80: Sáng - Mặn - Xưởng | L80: Sáng - Mặn - Xưởng | M80: Sáng - Mặn - Xưởng | O80: Sáng - Mặn - Xưởng | P80: Sáng - Mặn - Xưởng | Q80: Sáng - Mặn - Xưởng | R80: Sáng - Mặn - Xưởng | S80: Sáng - Mặn - Xưởng | T80: Sáng - Mặn - Xưởng | V80: Sáng - Mặn - Xưởng | W80: Sáng - Mặn - Xưởng | X80: Sáng - Mặn - Xưởng | Y80: Sáng - Mặn - Xưởng | Z80: Sáng - Mặn - Xưởng | AC80: Sáng - Mặn - Xưởng | AD80: Sáng - Mặn - Xưởng | AE80: Sáng - Mặn - Xưởng | AF80: Sáng - Mặn - Xưởng | AG80: Sáng - Mặn - Xưởng | AH80: Sáng - Mặn - Xưởng | AJ80: Sáng - Mặn - Xưởng | AK80: Sáng - Mặn - Xưởng | AL80: Sáng - Mặn - Xưởng | AM80: =COUNTA(I80:AL80)-COUNTIF(I80:AL80,"CT") -> 23
A81: Active | B81: VCV0115 | C81: Phạm Thị Hồng | D81: PMC - Quality | E81: PMC - Quality | F81: Factory | I81: Sáng - Mặn - Xưởng | L81: Sáng - Mặn - Xưởng | M81: Sáng - Mặn - Xưởng | O81: Sáng - Mặn - Xưởng | P81: Sáng - Mặn - Xưởng | Q81: Sáng - Mặn - Xưởng | R81: Sáng - Mặn - Xưởng | S81: Sáng - Mặn - Xưởng | T81: Sáng - Mặn - Xưởng | V81: Sáng - Mặn - Xưởng | W81: Sáng - Mặn - Xưởng | X81: Sáng - Mặn - Xưởng | Y81: Sáng - Mặn - Xưởng | Z81: Sáng - Mặn - Xưởng | AA81: Sáng - Mặn - Xưởng | AC81: Sáng - Mặn - Xưởng | AD81: Sáng - Mặn - Xưởng | AE81: Sáng - Mặn - Xưởng | AF81: Sáng - Mặn - Xưởng | AG81: Sáng - Mặn - Xưởng | AH81: Sáng - Mặn - Xưởng | AJ81: Sáng - Mặn - Xưởng | AK81: Sáng - Mặn - Xưởng | AL81: Sáng - Mặn - Xưởng | AM81: =COUNTA(I81:AL81)-COUNTIF(I81:AL81,"CT") -> 24
A82: Active | B82: VCV0116 | C82: Nguyễn Văn Giang | D82: PMC - Quality | E82: PMC - Quality | F82: Factory | I82: Sáng - Mặn - Xưởng | L82: Sáng - Mặn - Xưởng | M82: Sáng - Mặn - Xưởng | O82: Sáng - Mặn - Xưởng | P82: Sáng - Mặn - Xưởng | Q82: Sáng - Mặn - Xưởng | R82: Sáng - Mặn - Xưởng | S82: Sáng - Mặn - Xưởng | T82: Sáng - Mặn - Xưởng | V82: Sáng - Mặn - Xưởng | W82: Sáng - Mặn - Xưởng | X82: Sáng - Mặn - Xưởng | Y82: Sáng - Mặn - Xưởng | Z82: Sáng - Mặn - Xưởng | AA82: Sáng - Mặn - Xưởng | AC82: Sáng - Mặn - Xưởng | AD82: Sáng - Mặn - Xưởng | AE82: Sáng - Mặn - Xưởng | AF82: Sáng - Mặn - Xưởng | AG82: Sáng - Mặn - Xưởng | AH82: Sáng - Mặn - Xưởng | AJ82: Sáng - Mặn - Xưởng | AK82: Sáng - Mặn - Xưởng | AL82: Sáng - Mặn - Xưởng | AM82: =COUNTA(I82:AL82)-COUNTIF(I82:AL82,"CT") -> 24
A83: Active | B83: VCV0119 | C83: Rah Lan H in | D83: Pro - Aging | E83: Pro - Aging | F83: Factory | I83: Sáng - Mặn - Xưởng | L83: Sáng - Mặn - Xưởng | M83: Sáng - Mặn - Xưởng | O83: Sáng - Mặn - Xưởng | S83: Sáng - Mặn - Xưởng | T83: Sáng - Mặn - Xưởng | V83: Sáng - Mặn - Xưởng | W83: Sáng - Mặn - Xưởng | X83: Sáng - Mặn - Xưởng | Y83: Sáng - Mặn - Xưởng | Z83: Sáng - Mặn - Xưởng | AA83: Sáng - Mặn - Xưởng | AC83: Sáng - Mặn - Xưởng | AD83: Sáng - Mặn - Xưởng | AE83: Sáng - Mặn - Xưởng | AF83: Sáng - Mặn - Xưởng | AG83: Sáng - Mặn - Xưởng | AH83: Sáng - Mặn - Xưởng | AJ83: Sáng - Mặn - Xưởng | AK83: Sáng - Mặn - Xưởng | AL83: Sáng - Mặn - Xưởng | AM83: =COUNTA(I83:AL83)-COUNTIF(I83:AL83,"CT") -> 21
A84: Active | B84: VCV0121 | C84: Trần Thị Thủy | D84: Pro - Aging | E84: Pro - Aging | F84: Factory | I84: Sáng - Mặn - Xưởng | L84: Sáng - Mặn - Xưởng | M84: Sáng - Mặn - Xưởng | O84: Sáng - Mặn - Xưởng | S84: Sáng - Mặn - Xưởng | T84: Sáng - Mặn - Xưởng | V84: Sáng - Mặn - Xưởng | W84: Sáng - Mặn - Xưởng | X84: Sáng - Mặn - Xưởng | Y84: Sáng - Mặn - Xưởng | Z84: Sáng - Mặn - Xưởng | AA84: Sáng - Mặn - Xưởng | AC84: Sáng - Mặn - Xưởng | AD84: Sáng - Mặn - Xưởng | AF84: Sáng - Mặn - Xưởng | AG84: Sáng - Mặn - Xưởng | AH84: Sáng - Mặn - Xưởng | AJ84: Sáng - Mặn - Xưởng | AK84: Sáng - Mặn - Xưởng | AL84: Sáng - Mặn - Xưởng | AM84: =COUNTA(I84:AL84)-COUNTIF(I84:AL84,"CT") -> 20
A85: Active | B85: VCV0123 | C85: Bùi Văn Tâm | D85: Pro - Aging | E85: Pro - Aging | F85: Factory | I85: Sáng - Mặn - Xưởng | L85: Sáng - Mặn - Xưởng | M85: Sáng - Mặn - Xưởng | O85: Sáng - Mặn - Xưởng | S85: Sáng - Mặn - Xưởng | T85: Sáng - Mặn - Xưởng | V85: Sáng - Mặn - Xưởng | W85: Sáng - Mặn - Xưởng | X85: Sáng - Mặn - Xưởng | Y85: Sáng - Mặn - Xưởng | Z85: Sáng - Mặn - Xưởng | AC85: Sáng - Mặn - Xưởng | AD85: Sáng - Mặn - Xưởng | AE85: Sáng - Mặn - Xưởng | AF85: Sáng - Mặn - Xưởng | AG85: Sáng - Mặn - Xưởng | AH85: Sáng - Mặn - Xưởng | AJ85: Sáng - Mặn - Xưởng | AK85: Sáng - Mặn - Xưởng | AL85: Sáng - Mặn - Xưởng | AM85: =COUNTA(I85:AL85)-COUNTIF(I85:AL85,"CT") -> 20
A86: Active | B86: VCV0124 | C86: Nguyễn Thị Kim Thanh | D86: Pro - Aging | E86: Pro - Aging | F86: Factory | I86: Sáng - Mặn - Xưởng | L86: Sáng - Mặn - Xưởng | M86: Sáng - Mặn - Xưởng | O86: Sáng - Mặn - Xưởng | P86: Sáng - Mặn - Xưởng | Q86: Sáng - Mặn - Xưởng | R86: Sáng - Mặn - Xưởng | V86: Sáng - Mặn - Xưởng | W86: Sáng - Mặn - Xưởng | X86: Sáng - Mặn - Xưởng | Y86: Sáng - Mặn - Xưởng | Z86: Sáng - Mặn - Xưởng | AA86: Sáng - Mặn - Xưởng | AC86: Sáng - Mặn - Xưởng | AD86: Sáng - Mặn - Xưởng | AE86: Sáng - Mặn - Xưởng | AF86: Sáng - Mặn - Xưởng | AG86: Sáng - Mặn - Xưởng | AH86: Sáng - Mặn - Xưởng | AJ86: Sáng - Mặn - Xưởng | AK86: Sáng - Mặn - Xưởng | AL86: Sáng - Mặn - Xưởng | AM86: =COUNTA(I86:AL86)-COUNTIF(I86:AL86,"CT") -> 22
A87: Active | B87: VCV0128 | C87: Đoàn Gia Hào | D87: Pro - Data | E87: Pro - Data | F87: Factory | I87: Sáng - Mặn - Xưởng | L87: Sáng - Mặn - Xưởng | M87: Sáng - Mặn - Xưởng | O87: Sáng - Mặn - Xưởng | R87: Sáng - Mặn - Xưởng | S87: Sáng - Mặn - Xưởng | T87: Sáng - Mặn - Xưởng | V87: Sáng - Mặn - Xưởng | W87: Sáng - Mặn - Xưởng | X87: Sáng - Mặn - Xưởng | Y87: Sáng - Mặn - Xưởng | Z87: Sáng - Mặn - Xưởng | AA87: Sáng - Mặn - Xưởng | AC87: Sáng - Mặn - Xưởng | AD87: Sáng - Mặn - Xưởng | AE87: Sáng - Mặn - Xưởng | AF87: Sáng - Mặn - Xưởng | AG87: Sáng - Mặn - Xưởng | AH87: Sáng - Mặn - Xưởng | AJ87: Sáng - Mặn - Xưởng | AK87: Sáng - Mặn - Xưởng | AL87: Sáng - Mặn - Xưởng | AM87: =COUNTA(I87:AL87)-COUNTIF(I87:AL87,"CT") -> 22
A88: Active | B88: VCV0132 | C88: Võ Thị Kim Thủy | D88: Pro - Aging | E88: Pro - Aging | F88: Factory | I88: Sáng - Mặn - Xưởng | L88: Sáng - Mặn - Xưởng | M88: Sáng - Mặn - Xưởng | O88: Sáng - Mặn - Xưởng | S88: Sáng - Mặn - Xưởng | T88: Sáng - Mặn - Xưởng | V88: Sáng - Mặn - Xưởng | W88: Sáng - Mặn - Xưởng | X88: Sáng - Mặn - Xưởng | Y88: Sáng - Mặn - Xưởng | Z88: Sáng - Mặn - Xưởng | AA88: Sáng - Mặn - Xưởng | AC88: Sáng - Mặn - Xưởng | AD88: Sáng - Mặn - Xưởng | AE88: Sáng - Mặn - Xưởng | AF88: Sáng - Mặn - Xưởng | AG88: Sáng - Mặn - Xưởng | AH88: Sáng - Mặn - Xưởng | AJ88: Sáng - Mặn - Xưởng | AK88: Sáng - Mặn - Xưởng | AL88: Sáng - Mặn - Xưởng | AM88: =COUNTA(I88:AL88)-COUNTIF(I88:AL88,"CT") -> 21
A89: Active | B89: VCV0133 | C89: Ngô Thị Kim Thao | D89: Pro - Aging | E89: Pro - Aging | F89: Factory | I89: Sáng - Mặn - Xưởng | L89: Sáng - Mặn - Xưởng | M89: Sáng - Mặn - Xưởng | O89: Sáng - Mặn - Xưởng | Q89: Sáng - Mặn - Xưởng | R89: Sáng - Mặn - Xưởng | S89: Sáng - Mặn - Xưởng | T89: Sáng - Mặn - Xưởng | V89: Sáng - Mặn - Xưởng | Y89: Sáng - Mặn - Xưởng | Z89: Sáng - Mặn - Xưởng | AA89: Sáng - Mặn - Xưởng | AC89: Sáng - Mặn - Xưởng | AD89: Sáng - Mặn - Xưởng | AE89: Sáng - Mặn - Xưởng | AF89: Sáng - Mặn - Xưởng | AG89: Sáng - Mặn - Xưởng | AH89: Sáng - Mặn - Xưởng | AJ89: Sáng - Mặn - Xưởng | AK89: Sáng - Mặn - Xưởng | AL89: Sáng - Mặn - Xưởng | AM89: =COUNTA(I89:AL89)-COUNTIF(I89:AL89,"CT") -> 21
A90: Active | B90: VCV0134 | C90: Đặng Thị Nhân | D90: Pro - Aging | E90: Pro - Aging | F90: Factory | I90: Sáng - Mặn - Xưởng | L90: Sáng - Mặn - Xưởng | M90: Sáng - Mặn - Xưởng | O90: Sáng - Mặn - Xưởng | P90: Sáng - Mặn - Xưởng | Q90: Sáng - Mặn - Xưởng | R90: Sáng - Mặn - Xưởng | V90: Sáng - Mặn - Xưởng | W90: Sáng - Mặn - Xưởng | X90: Sáng - Mặn - Xưởng | Y90: Sáng - Mặn - Xưởng | Z90: Sáng - Mặn - Xưởng | AA90: Sáng - Mặn - Xưởng | AC90: Sáng - Mặn - Xưởng | AD90: Sáng - Mặn - Xưởng | AE90: Sáng - Mặn - Xưởng | AF90: Sáng - Mặn - Xưởng | AG90: Sáng - Mặn - Xưởng | AH90: Sáng - Mặn - Xưởng | AJ90: Sáng - Mặn - Xưởng | AK90: Sáng - Mặn - Xưởng | AL90: Sáng - Mặn - Xưởng | AM90: =COUNTA(I90:AL90)-COUNTIF(I90:AL90,"CT") -> 22
A91: Active | B91: VCV0136 | C91: Lương Ngọc Cẩm Hà | D91: Pro - Data | E91: Pro - Data | F91: Office | I91: Sáng - Mặn - VP | L91: Sáng - Mặn - VP | M91: Sáng - Mặn - VP | O91: Sáng - Mặn - VP | P91: Sáng - Mặn - VP | Q91: Sáng - Mặn - VP | R91: Sáng - Mặn - VP | S91: Sáng - Mặn - VP | T91: Sáng - Mặn - VP | V91: Sáng - Mặn - VP | W91: Sáng - Mặn - VP | X91: Sáng - Mặn - VP | Y91: Sáng - Mặn - VP | Z91: Sáng - Mặn - VP | AA91: Sáng - Mặn - VP | AC91: Sáng - Mặn - VP | AD91: Sáng - Mặn - VP | AE91: Sáng - Mặn - VP | AF91: Sáng - Mặn - VP | AG91: Sáng - Mặn - VP | AH91: Sáng - Mặn - VP | AK91: Sáng - Mặn - VP | AL91: Sáng - Mặn - VP | AM91: =COUNTA(I91:AL91)-COUNTIF(I91:AL91,"CT") -> 23
A92: Active | B92: VCV0137 | C92: Kim Thanh Hiệp | D92: Pro - Aging | E92: Pro - Aging | F92: Factory | I92: Sáng - Mặn - Xưởng | L92: Sáng - Mặn - Xưởng | M92: Sáng - Mặn - Xưởng | O92: Sáng - Mặn - Xưởng | P92: Sáng - Mặn - Xưởng | Q92: Sáng - Mặn - Xưởng | R92: Sáng - Mặn - Xưởng | V92: Sáng - Mặn - Xưởng | W92: Sáng - Mặn - Xưởng | X92: Sáng - Mặn - Xưởng | Y92: Sáng - Mặn - Xưởng | Z92: Sáng - Mặn - Xưởng | AA92: Sáng - Mặn - Xưởng | AC92: Sáng - Mặn - Xưởng | AD92: Sáng - Mặn - Xưởng | AE92: Sáng - Mặn - Xưởng | AF92: Sáng - Mặn - Xưởng | AG92: Sáng - Mặn - Xưởng | AH92: Sáng - Mặn - Xưởng | AJ92: Sáng - Mặn - Xưởng | AK92: Sáng - Mặn - Xưởng | AL92: Sáng - Mặn - Xưởng | AM92: =COUNTA(I92:AL92)-COUNTIF(I92:AL92,"CT") -> 22
A93: Active | B93: VCV0138 | C93: Lê Thị Lệ Quyên | D93: Pro - Aging | E93: Pro - Aging | F93: Factory | I93: Sáng - Mặn - Xưởng | L93: Sáng - Mặn - Xưởng | M93: Sáng - Mặn - Xưởng | O93: Sáng - Mặn - Xưởng | P93: Sáng - Mặn - Xưởng | Q93: Sáng - Mặn - Xưởng | R93: Sáng - Mặn - Xưởng | V93: Sáng - Mặn - Xưởng | W93: Sáng - Mặn - Xưởng | X93: Sáng - Mặn - Xưởng | Y93: Sáng - Mặn - Xưởng | Z93: Sáng - Mặn - Xưởng | AA93: Sáng - Mặn - Xưởng | AC93: Sáng - Mặn - Xưởng | AD93: Sáng - Mặn - Xưởng | AF93: Sáng - Mặn - Xưởng | AG93: Sáng - Mặn - Xưởng | AH93: Sáng - Mặn - Xưởng | AJ93: Sáng - Mặn - Xưởng | AK93: Sáng - Mặn - Xưởng | AL93: Sáng - Mặn - Xưởng | AM93: =COUNTA(I93:AL93)-COUNTIF(I93:AL93,"CT") -> 21
A94: Active | B94: VCV0140 | C94: Phạm Thành Đạt | D94: COO - WWT | E94: COO Office | F94: Office | G94: Chay | I94: Sáng - Chay - VP | L94: Sáng - Chay - VP | M94: Sáng - Chay - VP | O94: Sáng - Chay - VP | P94: Sáng - Chay - VP | Q94: Sáng - Chay - VP | R94: Sáng - Chay - VP | S94: Sáng - Chay - VP | T94: Sáng - Chay - VP | V94: Sáng - Chay - VP | X94: Sáng - Chay - VP | Y94: Sáng - Chay - VP | Z94: Sáng - Chay - VP | AA94: Sáng - Chay - VP | AC94: Sáng - Chay - VP | AD94: Sáng - Chay - VP | AE94: Sáng - Chay - VP | AF94: Sáng - Chay - VP | AG94: Sáng - Chay - VP | AH94: Sáng - Chay - VP | AJ94: Sáng - Chay - VP | AK94: Sáng - Chay - VP | AL94: Sáng - Chay - VP | AM94: =COUNTA(I94:AL94)-COUNTIF(I94:AL94,"CT") -> 23
A95: Active | B95: VCV0141 | C95: Nguyễn Thị Hiền | D95: Pro - Aging | E95: Pro - Aging | F95: Factory | I95: Sáng - Mặn - Xưởng | L95: Sáng - Mặn - Xưởng | M95: Sáng - Mặn - Xưởng | O95: Sáng - Mặn - Xưởng | S95: Sáng - Mặn - Xưởng | T95: Sáng - Mặn - Xưởng | V95: Sáng - Mặn - Xưởng | X95: Sáng - Mặn - Xưởng | Y95: Sáng - Mặn - Xưởng | Z95: Sáng - Mặn - Xưởng | AA95: Sáng - Mặn - Xưởng | AC95: Sáng - Mặn - Xưởng | AD95: Sáng - Mặn - Xưởng | AE95: Sáng - Mặn - Xưởng | AF95: Sáng - Mặn - Xưởng | AH95: Sáng - Mặn - Xưởng | AJ95: Sáng - Mặn - Xưởng | AK95: Sáng - Mặn - Xưởng | AL95: Sáng - Mặn - Xưởng | AM95: =COUNTA(I95:AL95)-COUNTIF(I95:AL95,"CT") -> 19
A96: Active | B96: VCV0143 | C96: Phan Thị Lục | D96: Pro - Painting | E96: Pro - Painting | F96: Factory | I96: Sáng - Mặn - Xưởng | L96: Sáng - Mặn - Xưởng | M96: Sáng - Mặn - Xưởng | O96: Sáng - Mặn - Xưởng | P96: Sáng - Mặn - Xưởng | Q96: Sáng - Mặn - Xưởng | R96: Sáng - Mặn - Xưởng | S96: Sáng - Mặn - Xưởng | T96: Sáng - Mặn - Xưởng | V96: Sáng - Mặn - Xưởng | W96: Sáng - Mặn - Xưởng | X96: Sáng - Mặn - Xưởng | Y96: Sáng - Mặn - Xưởng | Z96: Sáng - Mặn - Xưởng | AA96: Sáng - Mặn - Xưởng | AC96: Sáng - Mặn - Xưởng | AD96: Sáng - Mặn - Xưởng | AE96: Sáng - Mặn - Xưởng | AF96: Sáng - Mặn - Xưởng | AG96: Sáng - Mặn - Xưởng | AH96: Sáng - Mặn - Xưởng | AJ96: Sáng - Mặn - Xưởng | AK96: Sáng - Mặn - Xưởng | AL96: Sáng - Mặn - Xưởng | AM96: =COUNTA(I96:AL96)-COUNTIF(I96:AL96,"CT") -> 24
A97: Active | B97: VCV0145 | C97: Lâm Thị Ra | D97: Pro - Packaging | E97: Pro - Packaging | F97: Factory | I97: Sáng - Mặn - Xưởng | L97: Sáng - Mặn - Xưởng | M97: Sáng - Mặn - Xưởng | O97: Sáng - Mặn - Xưởng | P97: Sáng - Mặn - Xưởng | Q97: Sáng - Mặn - Xưởng | R97: Sáng - Mặn - Xưởng | S97: Sáng - Mặn - Xưởng | T97: Sáng - Mặn - Xưởng | V97: Sáng - Mặn - Xưởng | W97: Sáng - Mặn - Xưởng | X97: Sáng - Mặn - Xưởng | Y97: Sáng - Mặn - Xưởng | Z97: Sáng - Mặn - Xưởng | AA97: Sáng - Mặn - Xưởng | AB97: Sáng - Mặn - Xưởng | AC97: Sáng - Mặn - Xưởng | AD97: Sáng - Mặn - Xưởng | AF97: Sáng - Mặn - Xưởng | AG97: Sáng - Mặn - Xưởng | AH97: Sáng - Mặn - Xưởng | AJ97: Sáng - Mặn - Xưởng | AK97: Sáng - Mặn - Xưởng | AL97: Sáng - Mặn - Xưởng | AM97: =COUNTA(I97:AL97)-COUNTIF(I97:AL97,"CT") -> 24
A98: Active | B98: VCV0148 | C98: Thái Thị Mến | D98: Pro - Aging | E98: Pro - Aging | F98: Factory | I98: Sáng - Mặn - Xưởng | L98: Sáng - Mặn - Xưởng | M98: Sáng - Mặn - Xưởng | O98: Sáng - Mặn - Xưởng | P98: Sáng - Mặn - Xưởng | Q98: Sáng - Mặn - Xưởng | R98: Sáng - Mặn - Xưởng | V98: Sáng - Mặn - Xưởng | W98: Sáng - Mặn - Xưởng | X98: Sáng - Mặn - Xưởng | Y98: Sáng - Mặn - Xưởng | Z98: Sáng - Mặn - Xưởng | AA98: Sáng - Mặn - Xưởng | AC98: Sáng - Mặn - Xưởng | AD98: Sáng - Mặn - Xưởng | AE98: Sáng - Mặn - Xưởng | AF98: Sáng - Mặn - Xưởng | AG98: Sáng - Mặn - Xưởng | AH98: Sáng - Mặn - Xưởng | AJ98: Sáng - Mặn - Xưởng | AK98: Sáng - Mặn - Xưởng | AL98: Sáng - Mặn - Xưởng | AM98: =COUNTA(I98:AL98)-COUNTIF(I98:AL98,"CT") -> 22
A99: Active | B99: VCV0149 | C99: Phạm Văn Khoai | D99: Pro - Polishing | E99: Pro - Polishing | F99: Factory | I99: Sáng - Mặn - Xưởng | L99: Sáng - Mặn - Xưởng | O99: Sáng - Mặn - Xưởng | Q99: Sáng - Mặn - Xưởng | R99: Sáng - Mặn - Xưởng | S99: Sáng - Mặn - Xưởng | T99: Sáng - Mặn - Xưởng | V99: Sáng - Mặn - Xưởng | W99: Sáng - Mặn - Xưởng | X99: Sáng - Mặn - Xưởng | Y99: Sáng - Mặn - Xưởng | Z99: Sáng - Mặn - Xưởng | AA99: Sáng - Mặn - Xưởng | AM99: =COUNTA(I99:AL99)-COUNTIF(I99:AL99,"CT") -> 13
A100: Active | B100: VCV0154 | C100: Nguyễn Thị Nghĩa | D100: Pro - Fabrication | E100: Pro - Fabrication | F100: Factory | I100: Sáng - Mặn - Xưởng | L100: Sáng - Mặn - Xưởng | M100: Sáng - Mặn - Xưởng | O100: Sáng - Mặn - Xưởng | P100: Sáng - Mặn - Xưởng | Q100: Sáng - Mặn - Xưởng | R100: Sáng - Mặn - Xưởng | S100: Sáng - Mặn - Xưởng | T100: Sáng - Mặn - Xưởng | V100: Sáng - Mặn - Xưởng | W100: Sáng - Mặn - Xưởng | X100: Sáng - Mặn - Xưởng | Y100: Sáng - Mặn - Xưởng | Z100: Sáng - Mặn - Xưởng | AA100: Sáng - Mặn - Xưởng | AC100: Sáng - Mặn - Xưởng | AD100: Sáng - Mặn - Xưởng | AE100: Sáng - Mặn - Xưởng | AF100: Sáng - Mặn - Xưởng | AG100: Sáng - Mặn - Xưởng | AH100: Sáng - Mặn - Xưởng | AJ100: Sáng - Mặn - Xưởng | AK100: Sáng - Mặn - Xưởng | AL100: Sáng - Mặn - Xưởng | AM100: =COUNTA(I100:AL100)-COUNTIF(I100:AL100,"CT") -> 24
A101: Active | B101: VCV0156 | C101: Nguyễn Thị Ngọc Giàu | D101: Pro - Aging | E101: Pro - Aging | F101: Factory | I101: Sáng - Mặn - Xưởng | L101: Sáng - Mặn - Xưởng | M101: Sáng - Mặn - Xưởng | O101: Sáng - Mặn - Xưởng | P101: Sáng - Mặn - Xưởng | Q101: Sáng - Mặn - Xưởng | R101: Sáng - Mặn - Xưởng | V101: Sáng - Mặn - Xưởng | W101: Sáng - Mặn - Xưởng | X101: Sáng - Mặn - Xưởng | Y101: Sáng - Mặn - Xưởng | Z101: Sáng - Mặn - Xưởng | AA101: Sáng - Mặn - Xưởng | AC101: Sáng - Mặn - Xưởng | AD101: Sáng - Mặn - Xưởng | AE101: Sáng - Mặn - Xưởng | AF101: Sáng - Mặn - Xưởng | AG101: Sáng - Mặn - Xưởng | AH101: Sáng - Mặn - Xưởng | AJ101: Sáng - Mặn - Xưởng | AK101: Sáng - Mặn - Xưởng | AL101: Sáng - Mặn - Xưởng | AM101: =COUNTA(I101:AL101)-COUNTIF(I101:AL101,"CT") -> 22
...

Sheet CHIỀU 
I1: 46266 | J1: 46267 | K1: 46268 | L1: 46269 | M1: 46270 | N1: 46271 | O1: 46272 | P1: 46273 | Q1: 46274 | R1: 46275 | S1: 46276 | T1: 46277 | U1: 46278 | V1: 46279 | W1: 46280 | X1: 46281 | Y1: 46282 | Z1: 46283 | AA1: 46284 | AB1: 46285 | AC1: 46286 | AD1: 46287 | AE1: 46288 | AF1: 46289 | AG1: 46290 | AH1: 46291 | AI1: 46292 | AJ1: 46293 | AK1: 46294 | AL1: 46295
J2: =SUM(J3:J7) -> 0 | K2: =SUM(K3:K7) -> 0 | L2: =SUM(L3:L7) -> 0 | N2: =SUM(N3:N7) -> 0 | O2: =SUM(O3:O7) -> 0 | P2: =SUM(P3:P7) -> 0 | Q2: =SUM(Q3:Q7) -> 0 | R2: =SUM(R3:R7) -> 0 | S2: =SUM(S3:S7) -> 0 | T2: =SUM(T3:T7) -> 0 | U2: =SUM(U3:U7) -> 0 | ... AK2: =SUM(AK3:AK7) -> 0
I3: =COUNTIFS(I$15:I$101,$H3) -> 0 | J3: =COUNTIFS(J$15:J$101,$H3) -> 0 | K3: =COUNTIFS(K$15:K$101,$H3) -> 0 | L3: =COUNTIFS(L$15:L$101,$H3) -> 0 | N3: =COUNTIFS(N$15:N$101,$H3) -> 0 | O3: =COUNTIFS(O$15:O$101,$H3) -> 0 | P3: =COUNTIFS(P$15:P$101,$H3) -> 0 | Q3: =COUNTIFS(Q$15:Q$101,$H3) -> 0 | R3: =COUNTIFS(R$15:R$101,$H3) -> 0 | S3: =COUNTIFS(S$15:S$101,$H3) -> 0 | T3: =COUNTIFS(T$15:T$101,$H3) -> 0 | U3: =COUNTIFS(U$15:U$101,$H3) -> 0 | ... AK3: =COUNTIFS(AK$15:AK$101,$H3) -> 0
I4: =COUNTIFS(I$15:I$101,$H4)-I5 -> 0 | J4: =COUNTIFS(J$15:J$101,$H4)-J5 -> 0 | K4: =COUNTIFS(K$15:K$101,$H4)-K5 -> 0 | L4: =COUNTIFS(L$15:L$101,$H4)-L5 -> 0 | N4: =COUNTIFS(N$15:N$101,$H4)-N5 -> 0 | O4: =COUNTIFS(O$15:O$101,$H4)-O5 -> 0 | P4: =COUNTIFS(P$15:P$101,$H4)-P5 -> 0 | Q4: =COUNTIFS(Q$15:Q$101,$H4)-Q5 -> 0 | R4: =COUNTIFS(R$15:R$101,$H4)-R5 -> 0 | S4: =COUNTIFS(S$15:S$101,$H4)-S5 -> 0 | T4: =COUNTIFS(T$15:T$101,$H4)-T5 -> 0 | U4: =COUNTIFS(U$15:U$101,$H4)-U5 -> 0 | ... AK4: =COUNTIFS(AK$15:AK$101,$H4)-AK5 -> 0
G7: DS- Vegetarian rice | H7: Cơm ca đêm
G8: Shift 2 | H8: Ca chiều | I8: =I9+I12 -> 16 | J8: =J9+J12 -> 0 | K8: =K9+K12 -> 0 | L8: =L9+L12 -> 130 | M8: =M9+M12 -> 18 | N8: =N9+N12 -> 0 | O8: =O9+O12 -> 124 | P8: =P9+P12 -> 133 | ... AL8: =AL9+AL12 -> 151
G9: Savory Dinner | H9: Cơm Chiều Mặn | I9: =SUM(I10:I11)-I12 -> 16 | J9: =SUM(J10:J11)-J12 -> 0 | K9: =SUM(K10:K11)-K12 -> 0 | L9: =SUM(L10:L11)-L12 -> 119 | M9: =SUM(M10:M11)-M12 -> 18 | N9: =SUM(N10:N11)-N12 -> 0 | O9: =SUM(O10:O11)-O12 -> 115 | P9: =SUM(P10:P11)-P12 -> 122 | ... AL9: =SUM(AL10:AL11)-AL12 -> 140
B10: giao | C10: Cơm Ca 2 | D10: 10 | F10: =SUM(I10:AK10) -> 171 | G10: Overtime meal | H10: Cơm Ca 2 | I10: =COUNTIFS($I15:I$455,$H$10) -> 3 | J10: =COUNTIFS(J16:J455,$H$10) -> 0 | K10: =COUNTIFS(K16:K280,$H$10) -> 0 | L10: =COUNTIFS(L16:L479,$H$10) -> 3 | M10: =COUNTIFS(M16:M479,$H$10) -> 3 | N10: =COUNTIFS(N16:N479,$H$10) -> 0 | O10: =COUNTIFS(O16:O479,$H$10) -> 3 | P10: =COUNTIFS(P16:P479,$H$10) -> 10 | Q10: =COUNTIFS(Q16:Q552,$H$10) -> 11 | R10: =COUNTIFS(R16:R479,$H$10) -> 10 | S10: =COUNTIFS(S16:S479,$H$10) -> 7 | T10: =COUNTIFS(T16:T479,$H$10) -> 11 | U10: =COUNTIFS(U16:U479,$H$10) -> 0 | V10: =COUNTIFS(V16:V479,$H$10) -> 3 | W10: =COUNTIFS(W16:W479,$H$10) -> 11 | X10: =COUNTIFS(X16:X479,$H$10) -> 9 | Y10: =COUNTIFS(Y16:Y479,$H$10) -> 9 | ... AL10: =COUNTIFS(AL16:AL479,$H$10) -> 3
B11: ca 18 | C11: Cơm Tăng Ca | D11: 95 | F11: =SUM(I11:AK11) -> 3147 | G11: Overtime meal | H11: Cơm Tăng Ca | I11: =COUNTIFS(I16:I455,$H$11) -> 13 | J11: =COUNTIFS(J16:J280,$H$11) -> 0 | K11: =COUNTIFS(K16:K280,$H$11) -> 0 | L11: =COUNTIFS(L16:L479,$H$11) -> 127 | M11: =COUNTIFS(M16:M479,$H$11) -> 15 | N11: =COUNTIFS(N16:N479,$H$11) -> 0 | O11: =COUNTIFS(O16:O479,$H$11) -> 121 | P11: =COUNTIFS(P16:P479,$H$11) -> 123 | Q11: =COUNTIFS(Q16:Q552,$H$11) -> 131 | R11: =COUNTIFS(R16:R479,$H$11) -> 103 | S11: =COUNTIFS(S16:S479,$H$11) -> 108 | T11: =COUNTIFS(T16:T479,$H$11) -> 17 | U11: =COUNTIFS(U16:U479,$H$11) -> 0 | V11: =COUNTIFS(V16:V479,$H$11) -> 116 | W11: =COUNTIFS(W16:W479,$H$11) -> 215 | X11: =COUNTIFS(X16:X479,$H$11) -> 221 | Y11: =COUNTIFS(Y16:Y479,$H$11) -> 229 | ... AL11: =COUNTIFS(AL16:AL479,$H$11) -> 148
G12: Vegan Dinner | H12: Cơm Chiều Chay | L12: =1+10 -> 11 | O12: =9 -> 9 | P12: =11 -> 11 | Q12: =11+1 -> 12 | R12: =4 -> 4 | S12: =11 -> 11 | V12: =8 -> 8 | W12: =5+7 -> 12 | X12: =11+6 -> 17 | Y12: =12+10 -> 22 | AC12: =15+9 -> 24 | AD12: =13+9 -> 22 | AE12: =14+8 -> 22 | AF12: =15+10 -> 25 | AG12: =8 -> 8 | AJ12: =12+7 -> 19 | AK12: =14+11 -> 25 | AL12: =1+10 -> 11
F13: =SUM(I13:AL13) -> 3469 | G13: Total | H13: Total | I13: =I9+I12 -> 16 | J13: =J9+J12 -> 0 | K13: =K9+K12 -> 0 | L13: =L9+L12 -> 130 | M13: =M9+M12 -> 18 | N13: =N9+N12 -> 0 | O13: =O9+O12 -> 124 | P13: =P9+P12 -> 133 | ... AL13: =AL9+AL12 -> 151 | AM13: =SUM(I13:AL13) -> 3469
A15: Status | B15: Code | C15: Fullname VN | D15: Department | E15: Section | F15: Place | I15: 34 | J15: 35 | K15: 36 | L15: 37 | N15: 40 | O15: 41 | P15: 42 | Q15: 43 | R15: 43 | S15: 44 | T15: 45 | U15: 46 | V15: 47 | W15: 48 | X15: 49 | Y15: 50 | Z15: 51 | AA15: 52 | AB15: 53 | AC15: 54 | AD15: 55 | AE15: 56 | AF15: 57 | AG15: 58 | AH15: 59 | AI15: 60 | AJ15: 61 | AK15: 62 | AM15: Total meals per day
A16: Active | B16: PTT0451 | C16: Trần Huy Cường | D16: Pro - Packaging | E16: Pro - Packaging | F16: Factory | L16: Cơm tăng ca | AM16: =COUNTA(I16:AL16) -> 1
A17: Active | B17: PTT0537 | C17: Nguyễn Quang Khải | D17: Pro - Aging | E17: Pro - Aging | F17: Factory | AH17: Cơm tăng ca | AM17: =COUNTA(I17:AL17) -> 1
A18: Active | B18: PTT0546 | C18: Nguyễn Phạm Kim Ngân | D18: Pro - Aging | E18: Pro - Aging | F18: Factory | AH18: Cơm tăng ca | AM18: =COUNTA(I18:AL18) -> 1
A19: Active | B19: PTT0556 | C19: Phan Thị Ngọc Mai | D19: Pro - Painting | E19: Pro - Painting | F19: Factory | AH19: Cơm tăng ca | AM19: =COUNTA(I19:AL19) -> 1
A20: Active | B20: PTT0572 | C20: Phan Tấn Hữu | D20: Pro - Packaging | E20: Pro - Packaging | F20: Factory | L20: Cơm tăng ca | AH20: Cơm tăng ca | AM20: =COUNTA(I20:AL20) -> 2
A21: Active | B21: PTT0583 | C21: Võ Thị Ánh Nguyệt | D21: Pro - Aging | E21: Pro - Aging | F21: Factory | L21: Cơm tăng ca | AM21: =COUNTA(I21:AL21) -> 1
A22: Active | B22: PTT0598 | C22: Nguyễn Hải Yến | D22: Pro - Packaging | E22: Pro - Packaging | F22: Factory | L22: Cơm tăng ca | AM22: =COUNTA(I22:AL22) -> 1
A23: Active | B23: PTT0615 | C23: Nguyễn Văn Phước | D23: Pro - Packaging | E23: Pro - Packaging | F23: Factory | L23: Cơm tăng ca | AM23: =COUNTA(I23:AL23) -> 1
A24: Active | B24: PTT0618 | C24: Từ Tuấn Tú | D24: Pro - Packaging | E24: Pro - Packaging | F24: Factory | L24: Cơm tăng ca | AM24: =COUNTA(I24:AL24) -> 1
A25: Active | B25: PTT0625 | C25: Nguyễn Thị Hồng Dung | D25: Pro - Packaging | E25: Pro - Packaging | F25: Factory | L25: Cơm tăng ca | AM25: =COUNTA(I25:AL25) -> 1
A26: Active | B26: PTT0633 | C26: Lý Văn Luôl | D26: Pro - Packaging | E26: Pro - Packaging | F26: Factory | L26: Cơm tăng ca | AM26: =COUNTA(I26:AL26) -> 1
A27: Active | B27: PTT0634 | C27: Khưu Thị Cẩm Lai | D27: Pro - Packaging | E27: Pro - Packaging | F27: Factory | L27: Cơm tăng ca | AM27: =COUNTA(I27:AL27) -> 1
A28: Active | B28: VCV0795 | C28: Trần Thị Quỳnh Như | D28: Pro - Packaging | E28: Pro - Packaging | F28: Factory | L28: Cơm tăng ca | Q28: Cơm tăng ca | V28: Cơm tăng ca | W28: Cơm tăng ca | Y28: Cơm tăng ca | Z28: Cơm tăng ca | AC28: Cơm tăng ca | AK28: Cơm tăng ca | AL28: Cơm tăng ca | AM28: =COUNTA(I28:AL28) -> 9
A29: Active | B29: PTT0639 | C29: Võ Thị Kim Chung | D29: Pro - Packaging | E29: Pro - Packaging | F29: Factory | L29: Cơm tăng ca | AM29: =COUNTA(I29:AL29) -> 1
A30: Active | B30: VCV0018 | C30: Vương Nhựt Lân | D30: Pro - Welding | E30: Pro - Welding | F30: Factory | L30: Cơm tăng ca | O30: Cơm tăng ca | P30: Cơm tăng ca | Q30: Cơm tăng ca | R30: Cơm tăng ca | S30: Cơm tăng ca | V30: Cơm tăng ca | W30: Cơm tăng ca | X30: Cơm tăng ca | Y30: Cơm tăng ca | Z30: Cơm tăng ca | AC30: Cơm tăng ca | AD30: Cơm tăng ca | AE30: Cơm tăng ca | AF30: Cơm tăng ca | AK30: Cơm tăng ca | AL30: Cơm tăng ca | AM30: =COUNTA(I30:AL30) -> 17
A31: Active | B31: VCV0025 | C31: Phạm Thị Ngọc Diễm | D31: Production | E31: Production | F31: Factory | P31: Cơm tăng ca | X31: Cơm tăng ca | Y31: Cơm tăng ca | Z31: Cơm tăng ca | AF31: Cơm tăng ca | AG31: Cơm tăng ca | AM31: =COUNTA(I31:AL31) -> 6
A32: Active | B32: VCV0028 | C32: Bùi Long Phi | D32: Pro - Polishing | E32: Pro - Polishing | F32: Factory | P32: Cơm tăng ca | R32: Cơm tăng ca | S32: Cơm tăng ca | V32: Cơm tăng ca | AC32: Cơm ca 2 | AD32: Cơm ca 2 | AE32: Cơm ca 2 | AF32: Cơm tăng ca | AG32: Cơm tăng ca | AH32: Cơm ca 2 | AJ32: Cơm ca 2 | AK32: Cơm ca 2 | AL32: Cơm tăng ca | AM32: =COUNTA(I32:AL32) -> 13
A33: Active | B33: VCV0029 | C33: Đoàn Thị Chút | D33: Pro - Packaging | E33: Pro - Packaging | F33: Factory | L33: Cơm tăng ca | O33: Cơm tăng ca | P33: Cơm tăng ca | Q33: Cơm tăng ca | S33: Cơm tăng ca | V33: Cơm tăng ca | W33: Cơm tăng ca | X33: Cơm tăng ca | Y33: Cơm tăng ca | Z33: Cơm tăng ca | AC33: Cơm tăng ca | AD33: Cơm tăng ca | AE33: Cơm tăng ca | AF33: Cơm tăng ca | AG33: Cơm tăng ca | AJ33: Cơm tăng ca | AK33: Cơm tăng ca | AL33: Cơm tăng ca | AM33: =COUNTA(I33:AL33) -> 18
A34: Active | B34: VCV0030 | C34: Thị Thủy | D34: Pro - Aging | E34: Pro - Aging | F34: Factory | W34: Cơm tăng ca | Y34: Cơm tăng ca | AC34: Cơm tăng ca | AD34: Cơm tăng ca | AE34: Cơm tăng ca | AF34: Cơm tăng ca | AJ34: Cơm tăng ca | AK34: Cơm tăng ca | AM34: =COUNTA(I34:AL34) -> 8
A35: Active | B35: VCV0031 | C35: Thòng Cooc Làn | D35: Pro - Aging | E35: Pro - Aging | F35: Factory | W35: Cơm tăng ca | Y35: Cơm tăng ca | AD35: Cơm tăng ca | AE35: Cơm tăng ca | AF35: Cơm tăng ca | AJ35: Cơm tăng ca | AK35: Cơm tăng ca | AM35: =COUNTA(I35:AL35) -> 7
A36: Active | B36: VCV0032 | C36: Nguyễn Thị Ngọc Trâm | D36: Pro - Aging | E36: Pro - Aging | F36: Factory | P36: Cơm Tăng Ca | W36: Cơm tăng ca | X36: Cơm tăng ca | Y36: Cơm tăng ca | AC36: Cơm tăng ca | AD36: Cơm tăng ca | AE36: Cơm tăng ca | AF36: Cơm tăng ca | AJ36: Cơm tăng ca | AK36: Cơm tăng ca | AM36: =COUNTA(I36:AL36) -> 10
A37: Active | B37: VCV0035 | C37: Hoàng Thanh Hoa | D37: Pro - Fabrication | E37: Pro - Fabrication | F37: Factory | O37: Cơm tăng ca | P37: Cơm Tăng Ca | Q37: Cơm tăng ca | S37: Cơm tăng ca | W37: Cơm tăng ca | Y37: Cơm tăng ca | Z37: Cơm tăng ca | AD37: Cơm tăng ca | AE37: Cơm tăng ca | AF37: Cơm tăng ca | AJ37: Cơm tăng ca | AL37: Cơm tăng ca | AM37: =COUNTA(I37:AL37) -> 12
A38: Active | B38: VCV0036 | C38: Bùi Hồng Giang | D38: Pro - Aging | E38: Pro - Aging | F38: Factory | W38: Cơm tăng ca | X38: Cơm tăng ca | Y38: Cơm tăng ca | AC38: Cơm tăng ca | AD38: Cơm tăng ca | AE38: Cơm tăng ca | AF38: Cơm tăng ca | AJ38: Cơm tăng ca | AK38: Cơm tăng ca | AM38: =COUNTA(I38:AL38) -> 9
A39: Active | B39: VCV0037 | C39: Hồ Thị Quỳnh Thoa | D39: Pro - Aging | E39: Pro - Aging | F39: Factory | W39: Cơm tăng ca | X39: Cơm tăng ca | Y39: Cơm tăng ca | AC39: Cơm tăng ca | AD39: Cơm tăng ca | AE39: Cơm tăng ca | AF39: Cơm tăng ca | AJ39: Cơm tăng ca | AK39: Cơm tăng ca | AM39: =COUNTA(I39:AL39) -> 9
A40: Active | B40: VCV0061 | C40: Trần Minh Công | D40: Pro - CNC | E40: Pro - CNC | F40: Factory | I40: Cơm tăng ca | L40: Cơm tăng ca | M40: Cơm tăng ca | O40: Cơm tăng ca | P40: Cơm tăng ca | Q40: Cơm tăng ca | S40: Cơm tăng ca | T40: Cơm tăng ca | V40: Cơm tăng ca | W40: Cơm tăng ca | X40: Cơm tăng ca | Y40: Cơm tăng ca | Z40: Cơm tăng ca | AA40: Cơm tăng ca | AD40: Cơm tăng ca | AE40: Cơm tăng ca | AF40: Cơm tăng ca | AG40: Cơm tăng ca | AH40: Cơm tăng ca | AJ40: Cơm tăng ca | AK40: Cơm tăng ca | AL40: Cơm tăng ca | AM40: =COUNTA(I40:AL40) -> 22
A41: Active | B41: VCV0063 | C41: Trần Cường | D41: PMC - Quality | E41: PMC - Quality | F41: Factory | L41: Cơm tăng ca | O41: Cơm tăng ca | T41: Cơm tăng ca | V41: Cơm tăng ca | X41: Cơm tăng ca | Z41: Cơm tăng ca | AC41: Cơm tăng ca | AE41: Cơm tăng ca | AG41: Cơm tăng ca | AJ41: Cơm tăng ca | AL41: Cơm tăng ca | AM41: =COUNTA(I41:AL41) -> 11
A42: Active | B42: VCV0065 | C42: Nguyễn Hoàng Vũ | D42: Pro - Manual Lathe | E42: Pro - Manual Lathe | F42: Factory | L42: Cơm tăng ca | O42: Cơm tăng ca | P42: Cơm tăng ca | Q42: Cơm tăng ca | R42: Cơm tăng ca | V42: Cơm tăng ca | W42: Cơm tăng ca | X42: Cơm tăng ca | Y42: Cơm tăng ca | Z42: Cơm tăng ca | AD42: Cơm tăng ca | AE42: Cơm tăng ca | AF42: Cơm tăng ca | AJ42: Cơm tăng ca | AK42: Cơm tăng ca | AL42: Cơm tăng ca | AM42: =COUNTA(I42:AL42) -> 16
A43: Active | B43: VCV0069 | C43: Đinh Thị Ngọc Thùy | D43: Pro - Painting | E43: Pro - Painting | F43: Factory | L43: Cơm tăng ca | O43: Cơm tăng ca | Y43: Cơm tăng ca | Z43: Cơm tăng ca | AC43: Cơm tăng ca | AD43: Cơm tăng ca | AE43: Cơm tăng ca | AF43: Cơm tăng ca | AJ43: Cơm tăng ca | AK43: Cơm tăng ca | AM43: =COUNTA(I43:AL43) -> 10
A44: Active | B44: VCV0072 | C44: Trương Thị Hóa | D44: Pro - Aging | E44: Pro - Aging | F44: Factory | W44: Cơm tăng ca | X44: Cơm tăng ca | Y44: Cơm tăng ca | AC44: Cơm tăng ca | AD44: Cơm tăng ca | AE44: Cơm tăng ca | AF44: Cơm tăng ca | AJ44: Cơm tăng ca | AK44: Cơm tăng ca | AM44: =COUNTA(I44:AL44) -> 9
A45: Active | B45: VCV0073 | C45: Nguyễn Thành Dư | D45: Pro - Painting | E45: Pro - Painting | F45: Factory | L45: Cơm tăng ca | AC45: Cơm tăng ca | AD45: Cơm tăng ca | AF45: Cơm tăng ca | AJ45: Cơm tăng ca | AK45: Cơm tăng ca | AM45: =COUNTA(I45:AL45) -> 6
A46: Active | B46: VCV0091 | C46: Vòng Quyền Chi | D46: Pro - Polishing | E46: Pro - Polishing | F46: Factory | P46: Cơm tăng ca | S46: Cơm tăng ca | V46: Cơm tăng ca | X46: Cơm tăng ca | Y46: Cơm ca 2 | AC46: Cơm ca 2 | AD46: Cơm ca 2 | AE46: Cơm ca 2 | AF46: Cơm tăng ca | AG46: Cơm tăng ca | AH46: Cơm ca 2 | AJ46: Cơm ca 2 | AK46: Cơm ca 2 | AL46: Cơm tăng ca | AM46: =COUNTA(I46:AL46) -> 14
A47: Active | B47: VCV0095 | C47: Siu Dôi | D47: Pro - Fabrication | E47: Pro - Fabrication | F47: Factory | L47: Cơm tăng ca | P47: Cơm tăng ca | Q47: Cơm tăng ca | R47: Cơm tăng ca | S47: Cơm tăng ca | V47: Cơm tăng ca | W47: Cơm tăng ca | X47: Cơm tăng ca | Z47: Cơm tăng ca | AC47: Cơm tăng ca | AD47: Cơm tăng ca | AE47: Cơm tăng ca | AF47: Cơm tăng ca | AJ47: Cơm tăng ca | AK47: Cơm tăng ca | AL47: Cơm tăng ca | AM47: =COUNTA(I47:AL47) -> 16
A48: Active | B48: VCV0099 | C48: Lê Thị Kim Hoàng | D48: Pro - Aging | E48: Pro - Aging | F48: Factory | W48: Cơm tăng ca | X48: Cơm tăng ca | Y48: Cơm tăng ca | AC48: Cơm tăng ca | AD48: Cơm tăng ca | AE48: Cơm tăng ca | AF48: Cơm tăng ca | AJ48: Cơm tăng ca | AK48: Cơm tăng ca | AM48: =COUNTA(I48:AL48) -> 9
A49: Active | B49: VCV0103 | C49: Lê Thị Hải | D49: Pro - Painting | E49: Pro - Painting | F49: Factory | L49: Cơm tăng ca | O49: Cơm tăng ca | Y49: Cơm tăng ca | Z49: Cơm tăng ca | AC49: Cơm tăng ca | AD49: Cơm tăng ca | AE49: Cơm tăng ca | AF49: Cơm tăng ca | AJ49: Cơm tăng ca | AK49: Cơm tăng ca | AM49: =COUNTA(I49:AL49) -> 10
A50: Active | B50: VCV0109 | C50: Nguyễn Thị Vân | D50: Pro - Aging | E50: Pro - Aging | F50: Factory | W50: Cơm tăng ca | X50: Cơm tăng ca | Y50: Cơm tăng ca | AC50: Cơm tăng ca | AD50: Cơm tăng ca | AE50: Cơm tăng ca | AF50: Cơm tăng ca | AJ50: Cơm tăng ca | AK50: Cơm tăng ca | AM50: =COUNTA(I50:AL50) -> 9
A51: Active | B51: VCV0111 | C51: Phạm Thị Xuân Liễu | D51: Pro - Painting | E51: Pro - Painting | F51: Factory | O51: Cơm tăng ca | Y51: Cơm tăng ca | Z51: Cơm tăng ca | AC51: Cơm tăng ca | AD51: Cơm tăng ca | AE51: Cơm tăng ca | AF51: Cơm tăng ca | AJ51: Cơm tăng ca | AK51: Cơm tăng ca | AM51: =COUNTA(I51:AL51) -> 9
A52: Active | B52: VCV0113 | C52: Trần Văn Luyện | D52: Pro - Auto Polishing | E52: Pro - Auto Polishing | F52: Factory | L52: Cơm tăng ca | P52: Cơm tăng ca | Q52: Cơm tăng ca | R52: Cơm tăng ca | S52: Cơm tăng ca | W52: Cơm tăng ca | X52: Cơm tăng ca | AA52: Cơm tăng ca | AD52: Cơm tăng ca | AE52: Cơm tăng ca | AF52: Cơm tăng ca | AK52: Cơm tăng ca | AL52: Cơm tăng ca | AM52: =COUNTA(I52:AL52) -> 13
A53: Active | B53: VCV0116 | C53: Nguyễn Văn Giang | D53: PMC - Quality | E53: PMC - Quality | F53: Factory | P53: Cơm tăng ca | Q53: Cơm tăng ca | R53: Cơm tăng ca | V53: Cơm tăng ca | W53: Cơm tăng ca | X53: Cơm tăng ca | Y53: Cơm tăng ca | Z53: Cơm tăng ca | AC53: Cơm tăng ca | AD53: Cơm tăng ca | AE53: Cơm tăng ca | AF53: Cơm tăng ca | AG53: Cơm tăng ca | AH53: Cơm tăng ca | AJ53: Cơm tăng ca | AK53: Cơm tăng ca | AL53: Cơm tăng ca | AM53: =COUNTA(I53:AL53) -> 17
A54: Active | B54: VCV0119 | C54: Rah Lan H in | D54: Pro - Aging | E54: Pro - Aging | F54: Factory | W54: Cơm tăng ca | X54: Cơm tăng ca | Y54: Cơm tăng ca | AC54: Cơm tăng ca | AD54: Cơm tăng ca | AE54: Cơm tăng ca | AF54: Cơm tăng ca | AJ54: Cơm tăng ca | AK54: Cơm tăng ca | AM54: =COUNTA(I54:AL54) -> 9
A55: Active | B55: VCV0121 | C55: Trần Thị Thủy | D55: Pro - Aging | E55: Pro - Aging | F55: Factory | W55: Cơm tăng ca | X55: Cơm tăng ca | Y55: Cơm tăng ca | AC55: Cơm tăng ca | AD55: Cơm tăng ca | AF55: Cơm tăng ca | AJ55: Cơm tăng ca | AK55: Cơm tăng ca | AM55: =COUNTA(I55:AL55) -> 8
A56: Active | B56: VCV0123 | C56: Bùi Văn Tâm | D56: Pro - Aging | E56: Pro - Aging | F56: Factory | W56: Cơm tăng ca | X56: Cơm tăng ca | Y56: Cơm tăng ca | AC56: Cơm tăng ca | AD56: Cơm tăng ca | AE56: Cơm tăng ca | AF56: Cơm tăng ca | AJ56: Cơm tăng ca | AK56: Cơm tăng ca | AM56: =COUNTA(I56:AL56) -> 9
A57: Active | B57: VCV0124 | C57: Nguyễn Thị Kim Thanh | D57: Pro - Aging | E57: Pro - Aging | F57: Factory | W57: Cơm tăng ca | X57: Cơm tăng ca | Y57: Cơm tăng ca | AC57: Cơm tăng ca | AD57: Cơm tăng ca | AE57: Cơm tăng ca | AF57: Cơm tăng ca | AJ57: Cơm tăng ca | AK57: Cơm tăng ca | AM57: =COUNTA(I57:AL57) -> 9
A58: Active | B58: VCV0128 | C58: Đoàn Gia Hào | D58: Pro - Data | E58: Pro - Data | F58: Factory | W58: Cơm tăng ca | X58: Cơm tăng ca | Y58: Cơm tăng ca | AC58: Cơm tăng ca | AD58: Cơm tăng ca | AE58: Cơm tăng ca | AF58: Cơm tăng ca | AJ58: Cơm tăng ca | AK58: Cơm tăng ca | AM58: =COUNTA(I58:AL58) -> 9
A59: Active | B59: VCV0132 | C59: Võ Thị Kim Thủy | D59: Pro - Aging | E59: Pro - Aging | F59: Factory | W59: Cơm tăng ca | X59: Cơm tăng ca | Y59: Cơm tăng ca | AC59: Cơm tăng ca | AD59: Cơm tăng ca | AE59: Cơm tăng ca | AF59: Cơm tăng ca | AJ59: Cơm tăng ca | AK59: Cơm tăng ca | AM59: =COUNTA(I59:AL59) -> 9
A60: Active | B60: VCV0133 | C60: Ngô Thị Kim Thao | D60: Pro - Aging | E60: Pro - Aging | F60: Factory | Y60: Cơm tăng ca | AC60: Cơm tăng ca | AD60: Cơm tăng ca | AE60: Cơm tăng ca | AF60: Cơm tăng ca | AJ60: Cơm tăng ca | AK60: Cơm tăng ca | AM60: =COUNTA(I60:AL60) -> 7
A61: Active | B61: VCV0134 | C61: Đặng Thị Nhân | D61: Pro - Aging | E61: Pro - Aging | F61: Factory | W61: Cơm tăng ca | X61: Cơm tăng ca | Y61: Cơm tăng ca | AC61: Cơm tăng ca | AD61: Cơm tăng ca | AE61: Cơm tăng ca | AF61: Cơm tăng ca | AJ61: Cơm tăng ca | AK61: Cơm tăng ca | AM61: =COUNTA(I61:AL61) -> 9
A62: Active | B62: VCV0138 | C62: Lê Thị Lệ Quyên | D62: Pro - Aging | E62: Pro - Aging | F62: Factory | W62: Cơm tăng ca | X62: Cơm tăng ca | Y62: Cơm tăng ca | AC62: Cơm tăng ca | AF62: Cơm tăng ca | AJ62: Cơm tăng ca | AK62: Cơm tăng ca | AM62: =COUNTA(I62:AL62) -> 7
A63: Active | B63: VCV0141 | C63: Nguyễn Thị Hiền | D63: Pro - Aging | E63: Pro - Aging | F63: Factory | X63: Cơm tăng ca | Y63: Cơm tăng ca | AC63: Cơm tăng ca | AD63: Cơm tăng ca | AE63: Cơm tăng ca | AF63: Cơm tăng ca | AJ63: Cơm tăng ca | AK63: Cơm tăng ca | AM63: =COUNTA(I63:AL63) -> 8
A64: Active | B64: VCV0143 | C64: Phan Thị Lục | D64: Pro - Painting | E64: Pro - Painting | F64: Factory | L64: Cơm tăng ca | O64: Cơm tăng ca | Y64: Cơm tăng ca | Z64: Cơm tăng ca | AC64: Cơm tăng ca | AD64: Cơm tăng ca | AE64: Cơm tăng ca | AF64: Cơm tăng ca | AJ64: Cơm tăng ca | AK64: Cơm tăng ca | AM64: =COUNTA(I64:AL64) -> 10
A65: Active | B65: VCV0145 | C65: Lâm Thị Ra | D65: Pro - Packaging | E65: Pro - Packaging | F65: Factory | L65: Cơm tăng ca | O65: Cơm tăng ca | P65: Cơm tăng ca | Q65: Cơm tăng ca | V65: Cơm tăng ca | W65: Cơm tăng ca | X65: Cơm tăng ca | Y65: Cơm tăng ca | Z65: Cơm tăng ca | AC65: Cơm tăng ca | AD65: Cơm tăng ca | AF65: Cơm tăng ca | AG65: Cơm tăng ca | AJ65: Cơm tăng ca | AK65: Cơm tăng ca | AM65: =COUNTA(I65:AL65) -> 15
A66: Active | B66: VCV0148 | C66: Thái Thị Mến | D66: Pro - Aging | E66: Pro - Aging | F66: Factory | W66: Cơm tăng ca | X66: Cơm tăng ca | Y66: Cơm tăng ca | AC66: Cơm tăng ca | AD66: Cơm tăng ca | AE66: Cơm tăng ca | AF66: Cơm tăng ca | AJ66: Cơm tăng ca | AK66: Cơm tăng ca | AM66: =COUNTA(I66:AL66) -> 9
A67: Active | B67: VCV0149 | C67: Phạm Văn Khoai | D67: Pro - Polishing | E67: Pro - Polishing | F67: Factory | X67: Cơm tăng ca | Y67: Cơm tăng ca | Z67: Cơm tăng ca | AC67: Cơm ca 2 | AD67: Cơm ca 2 | AE67: Cơm ca 2 | AF67: Cơm tăng ca | AG67: Cơm tăng ca | AH67: Cơm ca 2 | AJ67: Cơm ca 2 | AK67: Cơm ca 2 | AL67: Cơm tăng ca | AM67: =COUNTA(I67:AL67) -> 12
A68: Active | B68: VCV0156 | C68: Nguyễn Thị Ngọc Giàu | D68: Pro - Aging | E68: Pro - Aging | F68: Factory | W68: Cơm tăng ca | X68: Cơm tăng ca | Y68: Cơm tăng ca | AC68: Cơm tăng ca | AD68: Cơm tăng ca | AE68: Cơm tăng ca | AF68: Cơm tăng ca | AJ68: Cơm tăng ca | AK68: Cơm tăng ca | AM68: =COUNTA(I68:AL68) -> 9
A69: Active | B69: VCV0157 | C69: Lê Thị Thu Hà | D69: Pro - Aging | E69: Pro - Aging | F69: Factory | W69: Cơm tăng ca | X69: Cơm tăng ca | Y69: Cơm tăng ca | AC69: Cơm tăng ca | AD69: Cơm tăng ca | AE69: Cơm tăng ca | AF69: Cơm tăng ca | AJ69: Cơm tăng ca | AK69: Cơm tăng ca | AM69: =COUNTA(I69:AL69) -> 9
A70: Active | B70: VCV0159 | C70: Đinh Thị Giáng Xuân | D70: Pro - Aging | E70: Pro - Aging | F70: Factory | W70: Cơm tăng ca | X70: Cơm tăng ca | Y70: Cơm tăng ca | AD70: Cơm tăng ca | AE70: Cơm tăng ca | AF70: Cơm tăng ca | AJ70: Cơm tăng ca | AK70: Cơm tăng ca | AM70: =COUNTA(I70:AL70) -> 8
A71: Active | B71: VCV0160 | C71: Trần Cỏng Dếnh | D71: Pro - Aging | E71: Pro - Aging | F71: Factory | W71: Cơm tăng ca | X71: Cơm tăng ca | Y71: Cơm tăng ca | AD71: Cơm tăng ca | AE71: Cơm tăng ca | AF71: Cơm tăng ca | AJ71: Cơm tăng ca | AK71: Cơm tăng ca | AM71: =COUNTA(I71:AL71) -> 8
A72: Active | B72: VCV0163 | C72: Đinh Văn Thiết | D72: Pro - Welding | E72: Pro - Welding | F72: Factory | P72: Cơm ca 2 | Q72: Cơm ca 2 | R72: Cơm ca 2 | S72: Cơm ca 2 | T72: Cơm Ca 2 | W72: Cơm ca 2 | X72: Cơm ca 2 | Y72: Cơm ca 2 | AD72: Cơm tăng ca | AM72: =COUNTA(I72:AL72) -> 9
A73: Active | B73: VCV0165 | C73: Nguyễn Trường Chính | D73: Pro - Fabrication | E73: Pro - Fabrication | F73: Factory | L73: Cơm tăng ca | O73: Cơm tăng ca | P73: Cơm tăng ca | Q73: Cơm tăng ca | R73: Cơm tăng ca | S73: Cơm tăng ca | V73: Cơm tăng ca | W73: Cơm tăng ca | X73: Cơm tăng ca | Y73: Cơm tăng ca | Z73: Cơm tăng ca | AD73: Cơm tăng ca | AE73: Cơm tăng ca | AF73: Cơm tăng ca | AK73: Cơm tăng ca | AL73: Cơm tăng ca | AM73: =COUNTA(I73:AL73) -> 16
A74: Active | B74: VCV0166 | C74: Trương Thị Đào | D74: Pro - Fabrication | E74: Pro - Fabrication | F74: Factory | L74: Cơm tăng ca | O74: Cơm tăng ca | P74: Cơm tăng ca | Q74: Cơm tăng ca | R74: Cơm tăng ca | V74: Cơm tăng ca | W74: Cơm tăng ca | X74: Cơm tăng ca | AC74: Cơm tăng ca | AD74: Cơm tăng ca | AE74: Cơm tăng ca | AK74: Cơm tăng ca | AL74: Cơm tăng ca | AM74: =COUNTA(I74:AL74) -> 13
A75: Active | B75: VCV0169 | C75: Hà Thị Hồng | D75: Pro - Painting | E75: Pro - Painting | F75: Factory | L75: Cơm tăng ca | O75: Cơm tăng ca | Z75: Cơm tăng ca | AC75: Cơm tăng ca | AD75: Cơm tăng ca | AE75: Cơm tăng ca | AF75: Cơm tăng ca | AJ75: Cơm tăng ca | AK75: Cơm tăng ca | AM75: =COUNTA(I75:AL75) -> 9
A76: Active | B76: VCV0171 | C76: Bùi Thị Thanh Liễu | D76: Pro - Aging | E76: Pro - Aging | F76: Factory | X76: Cơm tăng ca | Y76: Cơm tăng ca | AC76: Cơm tăng ca | AD76: Cơm tăng ca | AF76: Cơm tăng ca | AJ76: Cơm tăng ca | AM76: =COUNTA(I76:AL76) -> 6
A77: Active | B77: VCV0172 | C77: Phạm Thị Ngọc Hà | D77: Pro - Aging | E77: Pro - Aging | F77: Factory | W77: Cơm tăng ca | X77: Cơm tăng ca | Y77: Cơm tăng ca | AD77: Cơm tăng ca | AE77: Cơm tăng ca | AF77: Cơm tăng ca | AJ77: Cơm tăng ca | AK77: Cơm tăng ca | AM77: =COUNTA(I77:AL77) -> 8
A78: Active | B78: VCV0178 | C78: Nguyễn Hoàng Văn | D78: Pro - Polishing | E78: Pro - Polishing | F78: Factory | P78: Cơm ca 2 | Q78: Cơm ca 2 | R78: Cơm ca 2 | S78: Cơm ca 2 | T78: Cơm Ca 2 | W78: Cơm ca 2 | Y78: Cơm ca 2 | AC78: Cơm tăng ca | AD78: Cơm tăng ca | AE78: Cơm tăng ca | AG78: Cơm tăng ca | AK78: Cơm tăng ca | AL78: Cơm tăng ca | AM78: =COUNTA(I78:AL78) -> 13
A79: Active | B79: VCV0181 | C79: Dương Thành Sang | D79: Pro - Fabrication | E79: Pro - Fabrication | F79: Factory | L79: Cơm tăng ca | P79: Cơm tăng ca | R79: Cơm tăng ca | V79: Cơm tăng ca | X79: Cơm tăng ca | AC79: Cơm tăng ca | AK79: Cơm tăng ca | AM79: =COUNTA(I79:AL79) -> 7
A80: Active | B80: VCV0183 | C80: Phạm Văn Giang | D80: Pro - Fabrication | E80: Pro - Fabrication | F80: Factory | L80: Cơm tăng ca | X80: Cơm tăng ca | AC80: Cơm tăng ca | AF80: Cơm tăng ca | AJ80: Cơm tăng ca | AK80: Cơm tăng ca | AL80: Cơm tăng ca | AM80: =COUNTA(I80:AL80) -> 7
A81: Active | B81: VCV0193 | C81: Triệu Minh Tiền | D81: Pro - Aging | E81: Pro - Aging | F81: Factory | W81: Cơm tăng ca | X81: Cơm tăng ca | Y81: Cơm tăng ca | AD81: Cơm tăng ca | AE81: Cơm tăng ca | AF81: Cơm tăng ca | AJ81: Cơm tăng ca | AK81: Cơm tăng ca | AM81: =COUNTA(I81:AL81) -> 8
A82: Active | B82: VCV0194 | C82: Triệu Minh Tài | D82: Pro - Packaging | E82: Pro - Packaging | F82: Factory | L82: Cơm tăng ca | O82: Cơm tăng ca | P82: Cơm tăng ca | Q82: Cơm tăng ca | R82: Cơm tăng ca | S82: Cơm tăng ca | V82: Cơm tăng ca | W82: Cơm tăng ca | Y82: Cơm tăng ca | Z82: Cơm tăng ca | AD82: Cơm tăng ca | AE82: Cơm tăng ca | AF82: Cơm tăng ca | AG82: Cơm tăng ca | AJ82: Cơm tăng ca | AK82: Cơm tăng ca | AL82: Cơm tăng ca | AM82: =COUNTA(I82:AL82) -> 17
A83: Active | B83: VCV0195 | C83: Trần Thiện Duy | D83: Pro - Packaging | E83: Pro - Packaging | F83: Factory | L83: Cơm tăng ca | O83: Cơm tăng ca | P83: Cơm tăng ca | Q83: Cơm tăng ca | R83: Cơm tăng ca | S83: Cơm tăng ca | W83: Cơm tăng ca | X83: Cơm tăng ca | Y83: Cơm tăng ca | Z83: Cơm tăng ca | AC83: Cơm tăng ca | AD83: Cơm tăng ca | AE83: Cơm tăng ca | AF83: Cơm tăng ca | AG83: Cơm tăng ca | AJ83: Cơm tăng ca | AK83: Cơm tăng ca | AL83: Cơm tăng ca | AM83: =COUNTA(I83:AL83) -> 18
A84: Active | B84: VCV0196 | C84: Hồ Anh Khương | D84: Pro - Aging | E84: Pro - Aging | F84: Factory | W84: Cơm tăng ca | X84: Cơm tăng ca | Y84: Cơm tăng ca | AC84: Cơm tăng ca | AD84: Cơm tăng ca | AE84: Cơm tăng ca | AF84: Cơm tăng ca | AJ84: Cơm tăng ca | AK84: Cơm tăng ca | AM84: =COUNTA(I84:AL84) -> 9
A85: Active | B85: VCV0198 | C85: Lã Công Trung | D85: PMC - Quality | E85: PMC - Quality | F85: Factory | O85: Cơm tăng ca | AC85: Cơm tăng ca | AE85: Cơm tăng ca | AJ85: Cơm tăng ca | AK85: Cơm tăng ca | AL85: Cơm tăng ca | AM85: =COUNTA(I85:AL85) -> 6
A86: Active | B86: VCV0201 | C86: Đào Văn Tuyển | D86: Pro - CNC | E86: Pro - CNC | F86: Factory | I86: Cơm tăng ca | L86: Cơm tăng ca | M86: Cơm tăng ca | O86: Cơm tăng ca | P86: Cơm tăng ca | Q86: Cơm tăng ca | R86: Cơm tăng ca | S86: Cơm tăng ca | T86: Cơm tăng ca | V86: Cơm tăng ca | W86: Cơm tăng ca | X86: Cơm tăng ca | Y86: Cơm tăng ca | Z86: Cơm tăng ca | AA86: Cơm tăng ca | AD86: Cơm tăng ca | AE86: Cơm tăng ca | AF86: Cơm tăng ca | AG86: Cơm tăng ca | AH86: Cơm tăng ca | AJ86: Cơm tăng ca | AK86: Cơm tăng ca | AL86: Cơm tăng ca | AM86: =COUNTA(I86:AL86) -> 23
A87: Active | B87: VCV0206 | C87: Đặng Văn Long | D87: COO - Maintenance | E87: COO Office | F87: Factory | I87: Cơm tăng ca | M87: Cơm tăng ca | O87: Cơm tăng ca | P87: Cơm tăng ca | Q87: Cơm tăng ca | R87: Cơm tăng ca | S87: Cơm tăng ca | T87: Cơm tăng ca | V87: Cơm ca 2 | W87: Cơm ca 2 | X87: Cơm ca 2 | Y87: Cơm ca 2 | Z87: Cơm ca 2 | AA87: Cơm ca 2 | AM87: =COUNTA(I87:AL87) -> 14
A88: Active | B88: VCV0208 | C88: Phạm Văn Tuân | D88: PMC - Quality | E88: PMC - Quality | F88: Factory | P88: Cơm tăng ca | W88: Cơm tăng ca | Y88: Cơm tăng ca | AM88: =COUNTA(I88:AL88) -> 3
A89: Active | B89: VCV0228 | C89: Nguyễn Duy Luân | D89: Pro - CNC | E89: Pro - CNC | F89: Factory | I89: Cơm tăng ca | M89: Cơm tăng ca | O89: Cơm tăng ca | P89: Cơm tăng ca | Q89: Cơm tăng ca | R89: Cơm tăng ca | S89: Cơm tăng ca | T89: Cơm tăng ca | V89: Cơm tăng ca | W89: Cơm tăng ca | X89: Cơm tăng ca | Y89: Cơm tăng ca | Z89: Cơm tăng ca | AA89: Cơm tăng ca | AD89: Cơm tăng ca | AE89: Cơm tăng ca | AF89: Cơm tăng ca | AG89: Cơm tăng ca | AH89: Cơm tăng ca | AJ89: Cơm tăng ca | AK89: Cơm tăng ca | AL89: Cơm tăng ca | AM89: =COUNTA(I89:AL89) -> 22
A90: Active | B90: VCV0229 | C90: Nguyễn Thị Chúc | D90: Pro - CNC | E90: Pro - CNC | F90: Factory | I90: Cơm tăng ca | L90: Cơm tăng ca | M90: Cơm tăng ca | O90: Cơm tăng ca | P90: Cơm tăng ca | Q90: Cơm tăng ca | R90: Cơm tăng ca | S90: Cơm tăng ca | T90: Cơm tăng ca | V90: Cơm tăng ca | W90: Cơm tăng ca | X90: Cơm tăng ca | Y90: Cơm tăng ca | Z90: Cơm tăng ca | AA90: Cơm tăng ca | AD90: Cơm tăng ca | AE90: Cơm tăng ca | AF90: Cơm tăng ca | AG90: Cơm tăng ca | AH90: Cơm tăng ca | AJ90: Cơm tăng ca | AK90: Cơm tăng ca | AL90: Cơm tăng ca | AM90: =COUNTA(I90:AL90) -> 23
A91: Active | B91: VCV0230 | C91: Phạm Quang Khải | D91: COO - Maintenance | E91: COO Office | F91: Factory | L91: Cơm tăng ca | O91: Cơm ca 2 | P91: Cơm ca 2 | Q91: Cơm ca 2 | R91: Cơm ca 2 | S91: Cơm ca 2 | T91: Cơm ca 2 | V91: Cơm tăng ca | W91: Cơm tăng ca | X91: Cơm tăng ca | Y91: Cơm tăng ca | Z91: Cơm tăng ca | AA91: Cơm tăng ca | AC91: Cơm tăng ca | AD91: Cơm tăng ca | AE91: Cơm tăng ca | AJ91: Cơm ca 2 | AK91: Cơm ca 2 | AL91: Cơm ca 2 | AM91: =COUNTA(I91:AL91) -> 19
A92: Active | B92: VCV0239 | C92: Trần Văn Nguyên | D92: Pro - CNC | E92: Pro - CNC | F92: Factory | I92: Cơm tăng ca | L92: Cơm tăng ca | M92: Cơm tăng ca | O92: Cơm tăng ca | P92: Cơm tăng ca | Q92: Cơm tăng ca | R92: Cơm tăng ca | S92: Cơm tăng ca | T92: Cơm tăng ca | V92: Cơm tăng ca | W92: Cơm tăng ca | X92: Cơm tăng ca | Y92: Cơm tăng ca | Z92: Cơm tăng ca | AA92: Cơm tăng ca | AD92: Cơm tăng ca | AE92: Cơm tăng ca | AF92: Cơm tăng ca | AG92: Cơm tăng ca | AH92: Cơm tăng ca | AJ92: Cơm tăng ca | AK92: Cơm tăng ca | AL92: Cơm tăng ca | AM92: =COUNTA(I92:AL92) -> 23
A93: Active | B93: VCV0244 | C93: Lý Văn Chống | D93: Pro - Polishing | E93: Pro - Polishing | F93: Factory | AC93: Cơm ca 2 | AD93: Cơm ca 2 | AE93: Cơm ca 2 | AG93: Cơm tăng ca | AH93: Cơm ca 2 | AJ93: Cơm ca 2 | AK93: Cơm ca 2 | AL93: Cơm tăng ca | AM93: =COUNTA(I93:AL93) -> 8
A94: Active | B94: VCV0258 | C94: Nguyễn Hoàng Hải | D94: Pro - Polishing | E94: Pro - Polishing | F94: Factory | P94: Cơm ca 2 | Q94: Cơm ca 2 | R94: Cơm ca 2 | S94: Cơm ca 2 | T94: Cơm Ca 2 | W94: Cơm ca 2 | X94: Cơm ca 2 | Y94: Cơm tăng ca | Z94: Cơm tăng ca | AD94: Cơm tăng ca | AG94: Cơm tăng ca | AL94: Cơm tăng ca | AM94: =COUNTA(I94:AL94) -> 12
A95: Active | B95: VCV0260 | C95: Nguyễn Văn Thuần | D95: PMC - Quality | E95: PMC - Quality | F95: Factory | L95: Cơm tăng ca | P95: Cơm tăng ca | V95: Cơm tăng ca | X95: Cơm tăng ca | Y95: Cơm tăng ca | Z95: Cơm tăng ca | AD95: Cơm tăng ca | AE95: Cơm tăng ca | AF95: Cơm tăng ca | AL95: Cơm tăng ca | AM95: =COUNTA(I95:AL95) -> 10
A96: Active | B96: VCV0266 | C96: Mai Huỳnh Phi Long | D96: PMC - Quality | E96: PMC - Quality | F96: Factory | L96: Cơm tăng ca | P96: Cơm tăng ca | Q96: Cơm tăng ca | R96: Cơm tăng ca | T96: Cơm tăng ca | V96: Cơm tăng ca | W96: Cơm tăng ca | X96: Cơm tăng ca | AA96: Cơm tăng ca | AC96: Cơm tăng ca | AD96: Cơm tăng ca | AE96: Cơm tăng ca | AF96: Cơm tăng ca | AG96: Cơm tăng ca | AH96: Cơm tăng ca | AJ96: Cơm tăng ca | AK96: Cơm tăng ca | AL96: Cơm tăng ca | AM96: =COUNTA(I96:AL96) -> 18
A97: Active | B97: VCV0268 | C97: Phạm Quỳnh Minh Quang | D97: Pro - Aging | E97: Pro - Aging | F97: Factory | W97: Cơm tăng ca | X97: Cơm tăng ca | Y97: Cơm tăng ca | AC97: Cơm tăng ca | AD97: Cơm tăng ca | AE97: Cơm tăng ca | AF97: Cơm tăng ca | AJ97: Cơm tăng ca | AK97: Cơm tăng ca | AM97: =COUNTA(I97:AL97) -> 9
A98: Active | B98: VCV0279 | C98: Trần Nhớ | D98: Pro - Polishing | E98: Pro - Polishing | F98: Factory | P98: Cơm tăng ca | R98: Cơm tăng ca | S98: Cơm tăng ca | V98: Cơm tăng ca | AC98: Cơm ca 2 | AD98: Cơm ca 2 | AE98: Cơm ca 2 | AF98: Cơm ca 2 | AG98: Cơm tăng ca | AH98: Cơm ca 2 | AJ98: Cơm ca 2 | AK98: Cơm ca 2 | AL98: Cơm tăng ca | AM98: =COUNTA(I98:AL98) -> 13
A99: Active | B99: VCV0292 | C99: Đàm Thị Hương | D99: Pro - Aging | E99: Pro - Aging | F99: Factory | W99: Cơm tăng ca | X99: Cơm tăng ca | Y99: Cơm tăng ca | AC99: Cơm tăng ca | AD99: Cơm tăng ca | AE99: Cơm tăng ca | AF99: Cơm tăng ca | AJ99: Cơm tăng ca | AK99: Cơm tăng ca | AM99: =COUNTA(I99:AL99) -> 9
A100: Active | B100: VCV0294 | C100: Nguyễn Duy Phương | D100: Pro - Aging | E100: Pro - Aging | F100: Factory | W100: Cơm tăng ca | X100: Cơm tăng ca | Y100: Cơm tăng ca | AC100: Cơm tăng ca | AD100: Cơm tăng ca | AE100: Cơm tăng ca | AF100: Cơm tăng ca | AJ100: Cơm tăng ca | AK100: Cơm tăng ca | AM100: =COUNTA(I100:AL100) -> 9
A101: Active | B101: VCV0297 | C101: Nguyễn Thị Kim Nga | D101: Pro - Aging | E101: Pro - Aging | F101: Factory | W101: Cơm tăng ca | X101: Cơm tăng ca | Y101: Cơm tăng ca | AC101: Cơm tăng ca | AD101: Cơm tăng ca | AE101: Cơm tăng ca | AF101: Cơm tăng ca | AJ101: Cơm tăng ca | AK101: Cơm tăng ca | AM101: =COUNTA(I101:AL101) -> 9
A102: Active | B102: VCV0298 | C102: Nguyễn Thị Ngọc Trinh | D102: Pro - Aging | E102: Pro - Aging | F102: Factory | W102: Cơm tăng ca | X102: Cơm tăng ca | Y102: Cơm tăng ca | AD102: Cơm tăng ca | AE102: Cơm tăng ca | AF102: Cơm tăng ca | AJ102: Cơm tăng ca | AK102: Cơm tăng ca | AM102: =COUNTA(I102:AL102) -> 8
A103: Active | B103: VCV0299 | C103: Ninh Xuân Trường | D103: Pro - Aging | E103: Pro - Aging | F103: Factory | W103: Cơm tăng ca | X103: Cơm tăng ca | Y103: Cơm tăng ca | AC103: Cơm tăng ca | AD103: Cơm tăng ca | AE103: Cơm tăng ca | AF103: Cơm tăng ca | AJ103: Cơm tăng ca | AK103: Cơm tăng ca | AM103: =COUNTA(I103:AL103) -> 9
...

Sheet HHVCV
I1: 46266 | J1: 46267 | K1: 46268 | L1: 46269 | M1: 46270 | N1: 46271 | O1: 46272 | P1: 46273 | Q1: 46274 | R1: 46275 | S1: 46276 | T1: 46277 | U1: 46278 | V1: 46279 | W1: 46280 | X1: 46281 | Y1: 46282 | Z1: 46283 | AA1: 46284 | AB1: 46285 | AC1: 46286 | AD1: 46287 | AE1: 46288 | AF1: 46289 | AG1: 46290 | AH1: 46291 | AI1: 46292 | AJ1: 46293 | AK1: 46294 | AL1: 46295
G2: Shift 1 + normal shift | H2: Ca sáng | I2: =SUM(I3:I5) -> 0 | J2: =SUM(J3:J5) -> 0 | K2: =SUM(K3:K5) -> 0 | L2: =SUM(L3:L5) -> 0 | M2: =SUM(M3:M5) -> 0 | N2: =SUM(N3:N5) -> 0 | O2: =SUM(O3:O5) -> 0 | P2: =SUM(P3:P5) -> 0 | ... AL2: =SUM(AL3:AL5) -> 37
G3: DS- CN food | H3: Sáng - Trung | I3: =COUNTIFS(I$11:I$460,$H3) -> 0 | J3: =COUNTIFS(J$11:J$460,$H3) -> 0 | K3: =COUNTIFS(K$11:K$460,$H3) -> 0 | L3: =COUNTIFS(L$11:L$460,$H3) -> 0 | M3: =COUNTIFS(M$11:M$460,$H3) -> 0 | N3: =COUNTIFS(N$11:N$460,$H3) -> 0 | O3: =COUNTIFS(O$11:O$460,$H3) -> 0 | P3: =COUNTIFS(P$11:P$460,$H3) -> 0 | ... AL3: =COUNTIFS(AL$11:AL$460,$H3) -> 9
G4: DS- VN food | H4: Sáng - Mặn - Xưởng | I4: =COUNTIFS(I$11:I$460,$H4)-I5 -> 0 | J4: =COUNTIFS(J$11:J$460,$H4)-J5 -> 0 | K4: =COUNTIFS(K$11:K$460,$H4)-K5 -> 0 | L4: =COUNTIFS(L$11:L$460,$H4)-L5 -> 0 | M4: =COUNTIFS(M$11:M$460,$H4)-M5 -> 0 | N4: =COUNTIFS(N$11:N$460,$H4)-N5 -> 0 | O4: =COUNTIFS(O$11:O$460,$H4)-O5 -> 0 | P4: =COUNTIFS(P$11:P$460,$H4)-P5 -> 0 | ... AL4: =COUNTIFS(AL$11:AL$460,$H4)-AL5 -> 28
G5: DS- Vegetarian rice | H5: Sáng - Chay - Xưởng | AI5: =8 -> 8
E6: =SUM(I6:AL6) -> 430 | I6: =SUM(I7:I8) -> 0 | J6: =SUM(J7:J8) -> 0 | K6: =SUM(K7:K8) -> 0 | L6: =SUM(L7:L8) -> 0 | M6: =SUM(M7:M8) -> 0 | N6: =SUM(N7:N8) -> 0 | O6: =SUM(O7:O8) -> 0 | P6: =SUM(P7:P8) -> 0 | ... AL6: =SUM(AL7:AL8) -> 37
D7: 57 | E7: =SUM(I7:AL7) -> 107 | G7: Total Expat Meals | I7: =I3 -> 0 | J7: =J3 -> 0 | K7: =K3 -> 0 | L7: =L3 -> 0 | M7: =M3 -> 0 | N7: =N3 -> 0 | O7: =O3 -> 0 | P7: =P3 -> 0 | ... AL7: =AL3 -> 9
E8: =SUM(I8:AL8) -> 323 | G8: Total Vietnamese Meals | I8: =I2-I3 -> 0 | J8: =J2-J3 -> 0 | K8: =K2-K3 -> 0 | L8: =L2-L3 -> 0 | M8: =M2-M3 -> 0 | N8: =N2-N3 -> 0 | O8: =O2-O3 -> 0 | P8: =P2-P3 -> 0 | ... AL8: =AL2-AL3 -> 28
AM10: =E6-SUM(AM12:AM352) -> 0
A11: Status | B11: Code | C11: Fullname VN | D11: Department | E11: Section | F11: Place | H11: Last day | AM11: Total meals per day
A12: Active | B12: 26000 | C12: Nguyễn Thị Ngọc Nữ | D12: HHVCV | F12: Dầu Giây | AD12: Sáng - Mặn - Xưởng | AE12: Sáng - Mặn - Xưởng | AF12: Sáng - Mặn - Xưởng | AG12: Sáng - Mặn - Xưởng | AH12: Sáng - Mặn - Xưởng | AJ12: Sáng - Mặn - Xưởng | AK12: Sáng - Mặn - Xưởng | AL12: Sáng - Mặn - Xưởng | AM12: =COUNTA(I12:AL12)-COUNTIF(I12:AL12,"CT") -> 8
A13: Active | B13: 26001 | C13: Trần Minh Thiện | D13: HHVCV | F13: Dầu Giây | AD13: Sáng - Mặn - Xưởng | AE13: Sáng - Mặn - Xưởng | AF13: Sáng - Mặn - Xưởng | AG13: Sáng - Mặn - Xưởng | AH13: Sáng - Mặn - Xưởng | AJ13: Sáng - Mặn - Xưởng | AK13: Sáng - Mặn - Xưởng | AL13: Sáng - Mặn - Xưởng | AM13: =COUNTA(I13:AL13)-COUNTIF(I13:AL13,"CT") -> 8
A14: Active | B14: 26004 | C14: Trần Thị Oanh Đào | D14: HHVCV | F14: Dầu Giây | AD14: Sáng - Mặn - Xưởng | AE14: Sáng - Mặn - Xưởng | AF14: Sáng - Mặn - Xưởng | AG14: Sáng - Mặn - Xưởng | AH14: Sáng - Mặn - Xưởng | AK14: Sáng - Mặn - Xưởng | AL14: Sáng - Mặn - Xưởng | AM14: =COUNTA(I14:AL14)-COUNTIF(I14:AL14,"CT") -> 7
A15: Active | B15: 26005 | C15: Nguyễn Minh Lâm | D15: HHVCV | F15: Dầu Giây | AD15: Sáng - Mặn - Xưởng | AE15: Sáng - Mặn - Xưởng | AF15: Sáng - Mặn - Xưởng | AG15: Sáng - Mặn - Xưởng | AH15: Sáng - Mặn - Xưởng | AJ15: Sáng - Mặn - Xưởng | AK15: Sáng - Mặn - Xưởng | AL15: Sáng - Mặn - Xưởng | AM15: =COUNTA(I15:AL15)-COUNTIF(I15:AL15,"CT") -> 8
A16: Active | B16: 26006 | C16: Nguyễn Ngọc Quỳnh Như | D16: HHVCV | F16: Dầu Giây | AD16: Sáng - Mặn - Xưởng | AE16: Sáng - Mặn - Xưởng | AF16: Sáng - Mặn - Xưởng | AG16: Sáng - Mặn - Xưởng | AH16: Sáng - Mặn - Xưởng | AJ16: Sáng - Mặn - Xưởng | AK16: Sáng - Mặn - Xưởng | AL16: Sáng - Mặn - Xưởng | AM16: =COUNTA(I16:AL16)-COUNTIF(I16:AL16,"CT") -> 8
A17: Active | B17: 26007 | C17: Nguyễn Văn Duyên | D17: HHVCV | F17: Dầu Giây | AD17: Sáng - Mặn - Xưởng | AE17: Sáng - Mặn - Xưởng | AF17: Sáng - Mặn - Xưởng | AG17: Sáng - Mặn - Xưởng | AH17: Sáng - Mặn - Xưởng | AJ17: Sáng - Mặn - Xưởng | AK17: Sáng - Mặn - Xưởng | AL17: Sáng - Mặn - Xưởng | AM17: =COUNTA(I17:AL17)-COUNTIF(I17:AL17,"CT") -> 8
A18: Active | B18: 26009 | C18: Trần Minh Kim | D18: HHVCV | F18: Dầu Giây | AD18: Sáng - Mặn - Xưởng | AE18: Sáng - Mặn - Xưởng | AF18: Sáng - Mặn - Xưởng | AG18: Sáng - Mặn - Xưởng | AH18: Sáng - Mặn - Xưởng | AJ18: Sáng - Mặn - Xưởng | AK18: Sáng - Mặn - Xưởng | AL18: Sáng - Mặn - Xưởng | AM18: =COUNTA(I18:AL18)-COUNTIF(I18:AL18,"CT") -> 8
A19: Active | B19: 26010 | C19: Phan Huynh Ngọc Diễm | D19: HHVCV | F19: Dầu Giây | AD19: Sáng - Mặn - Xưởng | AE19: Sáng - Mặn - Xưởng | AF19: Sáng - Mặn - Xưởng | AG19: Sáng - Mặn - Xưởng | AH19: Sáng - Mặn - Xưởng | AJ19: Sáng - Mặn - Xưởng | AK19: Sáng - Mặn - Xưởng | AM19: =COUNTA(I19:AL19)-COUNTIF(I19:AL19,"CT") -> 7
A20: Active | B20: 26011 | C20: Lê Đức Quyền | D20: HHVCV | F20: Dầu Giây | AD20: Sáng - Mặn - Xưởng | AE20: Sáng - Mặn - Xưởng | AF20: Sáng - Mặn - Xưởng | AG20: Sáng - Mặn - Xưởng | AH20: Sáng - Mặn - Xưởng | AK20: Sáng - Mặn - Xưởng | AL20: Sáng - Mặn - Xưởng | AM20: =COUNTA(I20:AL20)-COUNTIF(I20:AL20,"CT") -> 7
A21: Active | B21: 26012 | C21: Nguyễn Văn Thông | D21: HHVCV | F21: Dầu Giây | AD21: Sáng - Mặn - Xưởng | AE21: Sáng - Mặn - Xưởng | AF21: Sáng - Mặn - Xưởng | AG21: Sáng - Mặn - Xưởng | AH21: Sáng - Mặn - Xưởng | AK21: Sáng - Mặn - Xưởng | AL21: Sáng - Mặn - Xưởng | AM21: =COUNTA(I21:AL21)-COUNTIF(I21:AL21,"CT") -> 7
A22: Active | B22: 26013 | C22: Lê Phạm Như Quỳnh | D22: HHVCV | F22: Dầu Giây | AD22: Sáng - Mặn - Xưởng | AE22: Sáng - Mặn - Xưởng | AF22: Sáng - Mặn - Xưởng | AG22: Sáng - Mặn - Xưởng | AH22: Sáng - Mặn - Xưởng | AJ22: Sáng - Mặn - Xưởng | AK22: Sáng - Mặn - Xưởng | AL22: Sáng - Mặn - Xưởng | AM22: =COUNTA(I22:AL22)-COUNTIF(I22:AL22,"CT") -> 8
A23: Active | B23: 26014 | C23: Trương Vũ Thiên Nhi | D23: HHVCV | F23: Dầu Giây | AE23: Sáng - Mặn - Xưởng | AF23: Sáng - Mặn - Xưởng | AK23: Sáng - Mặn - Xưởng | AL23: Sáng - Mặn - Xưởng | AM23: =COUNTA(I23:AL23)-COUNTIF(I23:AL23,"CT") -> 4
A24: Active | B24: 26016 | C24: Phạm Anh Vũ | D24: HHVCV | F24: Dầu Giây | AD24: Sáng - Mặn - Xưởng | AE24: Sáng - Mặn - Xưởng | AF24: Sáng - Mặn - Xưởng | AG24: Sáng - Mặn - Xưởng | AH24: Sáng - Mặn - Xưởng | AJ24: Sáng - Mặn - Xưởng | AK24: Sáng - Mặn - Xưởng | AL24: Sáng - Mặn - Xưởng | AM24: =COUNTA(I24:AL24)-COUNTIF(I24:AL24,"CT") -> 8
A25: Active | B25: 26017 | C25: Bùi Vũ Bảo Trâm | D25: HHVCV | F25: Dầu Giây | AD25: Sáng - Mặn - Xưởng | AF25: Sáng - Mặn - Xưởng | AG25: Sáng - Mặn - Xưởng | AH25: Sáng - Mặn - Xưởng | AK25: Sáng - Mặn - Xưởng | AL25: Sáng - Mặn - Xưởng | AM25: =COUNTA(I25:AL25)-COUNTIF(I25:AL25,"CT") -> 6
A26: Active | B26: 26003 | C26: Thòng Hoàng Long | D26: HHVCV | F26: Dầu Giây | AD26: Sáng - Mặn - Xưởng | AE26: Sáng - Mặn - Xưởng | AF26: Sáng - Mặn - Xưởng | AG26: Sáng - Mặn - Xưởng | AH26: Sáng - Mặn - Xưởng | AJ26: Sáng - Mặn - Xưởng | AK26: Sáng - Mặn - Xưởng | AL26: Sáng - Mặn - Xưởng | AM26: =COUNTA(I26:AL26)-COUNTIF(I26:AL26,"CT") -> 8
A27: Active | B27: 26002 | C27: Trần Hoài Yến Nhi | D27: HHVCV | F27: Dầu Giây | AD27: Sáng - Mặn - Xưởng | AE27: Sáng - Mặn - Xưởng | AF27: Sáng - Mặn - Xưởng | AG27: Sáng - Mặn - Xưởng | AH27: Sáng - Mặn - Xưởng | AJ27: Sáng - Mặn - Xưởng | AK27: Sáng - Mặn - Xưởng | AL27: Sáng - Mặn - Xưởng | AM27: =COUNTA(I27:AL27)-COUNTIF(I27:AL27,"CT") -> 8
A28: Active | C28: Phạm Thị Thuỳ Tiên | D28: HHVCV | F28: Dầu Giây | AD28: Sáng - Mặn - Xưởng | AE28: Sáng - Mặn - Xưởng | AF28: Sáng - Mặn - Xưởng | AG28: Sáng - Mặn - Xưởng | AH28: Sáng - Mặn - Xưởng | AJ28: Sáng - Mặn - Xưởng | AK28: Sáng - Mặn - Xưởng | AL28: Sáng - Mặn - Xưởng | AM28: =COUNTA(I28:AL28)-COUNTIF(I28:AL28,"CT") -> 8
A29: Active | C29: Võ Minh Đạt | D29: HHVCV | F29: Dầu Giây | AD29: Sáng - Mặn - Xưởng | AE29: Sáng - Mặn - Xưởng | AF29: Sáng - Mặn - Xưởng | AK29: Sáng - Mặn - Xưởng | AL29: Sáng - Mặn - Xưởng | AM29: =COUNTA(I29:AL29)-COUNTIF(I29:AL29,"CT") -> 5
A30: Active | B30: VCV0320 | C30: Đõ Lệ Ngọc | D30: PMC - WH | E30: PMC - WH | F30: Dầu Giây | AD30: Sáng - Mặn - Xưởng | AE30: Sáng - Mặn - Xưởng | AF30: Sáng - Mặn - Xưởng | AG30: Sáng - Mặn - Xưởng | AH30: Sáng - Mặn - Xưởng | AJ30: Sáng - Mặn - Xưởng | AK30: Sáng - Mặn - Xưởng | AL30: Sáng - Mặn - Xưởng | AM30: =COUNTA(I30:AL30)-COUNTIF(I30:AL30,"CT") -> 8
A31: Active | B31: VCV0788 | C31: Diệu Ngọc | D31: PMC - WH | E31: PMC - WH | F31: Dầu Giây | AD31: Sáng - Mặn - Xưởng | AE31: Sáng - Mặn - Xưởng | AF31: Sáng - Mặn - Xưởng | AG31: Sáng - Mặn - Xưởng | AH31: Sáng - Mặn - Xưởng | AJ31: Sáng - Mặn - Xưởng | AK31: Sáng - Mặn - Xưởng | AL31: Sáng - Mặn - Xưởng | AM31: =COUNTA(I31:AL31)-COUNTIF(I31:AL31,"CT") -> 8
A32: Active | B32: VCV0719 | C32: Trịnh Xuân Trường | D32: PMC - WH | E32: PMC - WH | F32: Dầu Giây | AD32: Sáng - Mặn - Xưởng | AE32: Sáng - Mặn - Xưởng | AF32: Sáng - Mặn - Xưởng | AG32: Sáng - Mặn - Xưởng | AH32: Sáng - Mặn - Xưởng | AJ32: Sáng - Mặn - Xưởng | AK32: Sáng - Mặn - Xưởng | AL32: Sáng - Mặn - Xưởng | AM32: =COUNTA(I32:AL32)-COUNTIF(I32:AL32,"CT") -> 8
A33: Active | B33: VCV0750 | C33: Huỳnh Khang Duy | D33: PMC - WH | E33: PMC - WH | F33: Dầu Giây | AD33: Sáng - Mặn - Xưởng | AE33: Sáng - Mặn - Xưởng | AF33: Sáng - Mặn - Xưởng | AG33: Sáng - Mặn - Xưởng | AH33: Sáng - Mặn - Xưởng | AJ33: Sáng - Mặn - Xưởng | AK33: Sáng - Mặn - Xưởng | AL33: Sáng - Mặn - Xưởng | AM33: =COUNTA(I33:AL33)-COUNTIF(I33:AL33,"CT") -> 8
A34: Active | B34: VCV0623 | C34: Phạm Văn Tuấn | D34: PMC - WH | E34: PMC - WH | F34: Dầu Giây | AD34: Sáng - Mặn - Xưởng | AE34: Sáng - Mặn - Xưởng | AF34: Sáng - Mặn - Xưởng | AG34: Sáng - Mặn - Xưởng | AJ34: Sáng - Mặn - Xưởng | AK34: Sáng - Mặn - Xưởng | AL34: Sáng - Mặn - Xưởng | AM34: =COUNTA(I34:AL34)-COUNTIF(I34:AL34,"CT") -> 7
A35: Active | B35: VCV0787 | C35: Nguyễn Phúc Ân | D35: PMC - WH | E35: PMC - WH | F35: Dầu Giây | AD35: Sáng - Mặn - Xưởng | AE35: Sáng - Mặn - Xưởng | AL35: Sáng - Mặn - Xưởng | AM35: =COUNTA(I35:AL35)-COUNTIF(I35:AL35,"CT") -> 3
A36: Active | B36: VCV0756 | C36: Lường Chắn Hoa | D36: PMC - WH | E36: PMC - WH | F36: Dầu Giây | AD36: Sáng - Mặn - Xưởng | AE36: Sáng - Mặn - Xưởng | AF36: Sáng - Mặn - Xưởng | AG36: Sáng - Mặn - Xưởng | AH36: Sáng - Mặn - Xưởng | AJ36: Sáng - Mặn - Xưởng | AK36: Sáng - Mặn - Xưởng | AL36: Sáng - Mặn - Xưởng | AM36: =COUNTA(I36:AL36)-COUNTIF(I36:AL36,"CT") -> 8
A37: Active | C37: Trần Minh Hiếu | D37: PMC - WH | E37: PMC - WH | F37: Dầu Giây | AD37: Sáng - Mặn - Xưởng | AE37: Sáng - Mặn - Xưởng | AF37: Sáng - Mặn - Xưởng | AG37: Sáng - Mặn - Xưởng | AH37: Sáng - Mặn - Xưởng | AJ37: Sáng - Mặn - Xưởng | AK37: Sáng - Mặn - Xưởng | AL37: Sáng - Mặn - Xưởng | AM37: =COUNTA(I37:AL37)-COUNTIF(I37:AL37,"CT") -> 8
A38: Active | B38: VCV0444 | C38: Lê Doãn Hội | D38: PMC - WH | E38: PMC - WH | F38: Dầu Giây | AE38: Sáng - Mặn - Xưởng | AG38: Sáng - Mặn - Xưởng | AH38: Sáng - Mặn - Xưởng | AJ38: Sáng - Mặn - Xưởng | AK38: Sáng - Mặn - Xưởng | AL38: Sáng - Mặn - Xưởng | AM38: =COUNTA(I38:AL38)-COUNTIF(I38:AL38,"CT") -> 6
A39: Active | B39: VCV0501 | C39: Nguyễn Văn Phước | D39: PMC - WH | E39: PMC - WH | F39: Dầu Giây | AD39: Sáng - Mặn - Xưởng | AG39: Sáng - Mặn - Xưởng | AH39: Sáng - Mặn - Xưởng | AJ39: Sáng - Mặn - Xưởng | AK39: Sáng - Mặn - Xưởng | AM39: =COUNTA(I39:AL39)-COUNTIF(I39:AL39,"CT") -> 5
A40: Active | B40: VCV0770 | C40: Tsần Thị Hồng Linh | D40: PMC - WH | E40: PMC - WH | F40: Dầu Giây | AG40: Sáng - Mặn - Xưởng | AM40: =COUNTA(I40:AL40)-COUNTIF(I40:AL40,"CT") -> 1
A41: Active | C41: Vũ Đại Thắng | D41: PMC - WH | E41: PMC - WH | F41: Dầu Giây | AK41: Sáng - Mặn - Xưởng | AM41: =COUNTA(I41:AL41)-COUNTIF(I41:AL41,"CT") -> 1
A42: Active | B42: VCV0807 | C42: Mã Cắm Phùng | D42: PMC - WH | E42: PMC - WH | F42: Dầu Giây | AG42: Sáng - Mặn - Xưởng | AM42: =COUNTA(I42:AL42)-COUNTIF(I42:AL42,"CT") -> 1
A43: Active | C43: Phạm Song Quý | D43: Subcontractor | E43: Driver | F43: Dầu Giây | AD43: Sáng - Mặn - Xưởng | AE43: Sáng - Mặn - Xưởng | AJ43: Sáng - Mặn - Xưởng | AM43: =COUNTA(I43:AL43)-COUNTIF(I43:AL43,"CT") -> 3
A44: Active | C44: Đỗ Đông Đức | D44: Subcontractor | E44: Driver | F44: Dầu Giây | AD44: Sáng - Mặn - Xưởng | AE44: Sáng - Mặn - Xưởng | AG44: Sáng - Mặn - Xưởng | AH44: Sáng - Mặn - Xưởng | AJ44: Sáng - Mặn - Xưởng | AL44: Sáng - Mặn - Xưởng | AM44: =COUNTA(I44:AL44)-COUNTIF(I44:AL44,"CT") -> 6
A45: Active | C45: Nguyễn Ngân | D45: Subcontractor | E45: Driver | F45: Dầu Giây | AD45: Sáng - Mặn - Xưởng | AG45: Sáng - Mặn - Xưởng | AH45: Sáng - Mặn - Xưởng | AJ45: Sáng - Mặn - Xưởng | AK45: Sáng - Mặn - Xưởng | AM45: =COUNTA(I45:AL45)-COUNTIF(I45:AL45,"CT") -> 5
A46: Active | C46: Nguyễn Đức Ân | D46: Subcontractor | E46: Driver | F46: Dầu Giây | AG46: Sáng - Mặn - Xưởng | AM46: =COUNTA(I46:AL46)-COUNTIF(I46:AL46,"CT") -> 1
A47: Active | C47: Lã Công Trung | D47: PMC - Quality | E47: PMC - Quality | F47: Dầu Giây | AD47: Sáng - Mặn - Xưởng | AG47: Sáng - Mặn - Xưởng | AJ47: Sáng - Mặn - Xưởng | AM47: =COUNTA(I47:AL47)-COUNTIF(I47:AL47,"CT") -> 3
A48: Active | C48: Phạm Quan Thái | D48: COO - Maintenance | E48: COO - Maintenance | F48: Dầu Giây | AD48: Sáng - Mặn - Xưởng | AE48: Sáng - Mặn - Xưởng | AF48: Sáng - Mặn - Xưởng | AG48: Sáng - Mặn - Xưởng | AH48: Sáng - Mặn - Xưởng | AM48: =COUNTA(I48:AL48)-COUNTIF(I48:AL48,"CT") -> 5
A49: Active | C49: Nguyễn Hoàng Khang | D49: COO - Maintenance | E49: COO - Maintenance | F49: Dầu Giây | AD49: Sáng - Mặn - Xưởng | AE49: Sáng - Mặn - Xưởng | AF49: Sáng - Mặn - Xưởng | AG49: Sáng - Mặn - Xưởng | AH49: Sáng - Mặn - Xưởng | AJ49: Sáng - Mặn - Xưởng | AM49: =COUNTA(I49:AL49)-COUNTIF(I49:AL49,"CT") -> 6
A50: Active | C50: Đặng Văn Long | D50: COO - Maintenance | E50: COO - Maintenance | F50: Dầu Giây | AF50: Sáng - Mặn - Xưởng | AJ50: Sáng - Mặn - Xưởng | AM50: =COUNTA(I50:AL50)-COUNTIF(I50:AL50,"CT") -> 2
A51: Active | C51: Trần Kim Hải | D51: Subcontractor | E51: Security | F51: Dầu Giây | AK51: Sáng - Mặn - Xưởng | AL51: Sáng - Mặn - Xưởng | AM51: =COUNTA(I51:AL51)-COUNTIF(I51:AL51,"CT") -> 2
A52: Active | C52: Lý Văn Trung | D52: Subcontractor | E52: Security | F52: Dầu Giây | AM52: =COUNTA(I52:AL52)-COUNTIF(I52:AL52,"CT") -> 0
A53: Active | C53: Shipping fee | D53: Pro - Expat | E53: Pro - Expat | F53: Dầu Giây | AD53: Sáng - Trung | AE53: Sáng - Trung | AF53: Sáng - Trung | AG53: Sáng - Trung | AH53: Sáng - Trung | AJ53: Sáng - Trung | AK53: Sáng - Trung | AL53: Sáng - Trung | AM53: =COUNTA(I53:AL53)-COUNTIF(I53:AL53,"CT") -> 8
A54: Active | C54: Shipping fee | D54: Pro - Expat | E54: Pro - Expat | F54: Dầu Giây | AD54: Sáng - Trung | AE54: Sáng - Trung | AF54: Sáng - Trung | AG54: Sáng - Trung | AH54: Sáng - Trung | AJ54: Sáng - Trung | AK54: Sáng - Trung | AL54: Sáng - Trung | AM54: =COUNTA(I54:AL54)-COUNTIF(I54:AL54,"CT") -> 8
A55: Active | C55: ZHANG LANG XING | D55: Pro - Expat | E55: Pro - Expat | F55: Dầu Giây | AD55: Sáng - Trung | AE55: Sáng - Trung | AF55: Sáng - Trung | AG55: Sáng - Trung | AH55: Sáng - Trung | AI55: Sáng - Trung | AJ55: Sáng - Trung | AM55: =COUNTA(I55:AL55)-COUNTIF(I55:AL55,"CT") -> 7
A56: Active | C56: ZHANG FANXING | D56: Pro - Expat | E56: Pro - Expat | F56: Dầu Giây | AD56: Sáng - Trung | AE56: Sáng - Trung | AF56: Sáng - Trung | AG56: Sáng - Trung | AH56: Sáng - Trung | AI56: Sáng - Trung | AJ56: Sáng - Trung | AM56: =COUNTA(I56:AL56)-COUNTIF(I56:AL56,"CT") -> 7
A57: Active | C57: ZHANG CHUMING | D57: Pro - Expat | E57: Pro - Expat | F57: Dầu Giây | AD57: Sáng - Trung | AE57: Sáng - Trung | AF57: Sáng - Trung | AG57: Sáng - Trung | AH57: Sáng - Trung | AI57: Sáng - Trung | AJ57: Sáng - Trung | AK57: Sáng - Trung | AL57: Sáng - Trung | AM57: =COUNTA(I57:AL57)-COUNTIF(I57:AL57,"CT") -> 9
A58: Active | C58: ZHANG WEXING | D58: Pro - Expat | E58: Pro - Expat | F58: Dầu Giây | AD58: Sáng - Trung | AE58: Sáng - Trung | AF58: Sáng - Trung | AG58: Sáng - Trung | AH58: Sáng - Trung | AJ58: Sáng - Trung | AK58: Sáng - Trung | AL58: Sáng - Trung | AM58: =COUNTA(I58:AL58)-COUNTIF(I58:AL58,"CT") -> 8
A59: Active | C59: MA JIANJIE | D59: Pro - Expat | E59: Pro - Expat | F59: Dầu Giây | AD59: Sáng - Trung | AE59: Sáng - Trung | AF59: Sáng - Trung | AG59: Sáng - Trung | AH59: Sáng - Trung | AJ59: Sáng - Trung | AK59: Sáng - Trung | AL59: Sáng - Trung | AM59: =COUNTA(I59:AL59)-COUNTIF(I59:AL59,"CT") -> 8
A60: Active | C60: WANG GUANRONG | D60: Pro - Expat | E60: Pro - Expat | F60: Dầu Giây | AD60: Sáng - Trung | AE60: Sáng - Trung | AF60: Sáng - Trung | AG60: Sáng - Trung | AH60: Sáng - Trung | AJ60: Sáng - Trung | AK60: Sáng - Trung | AL60: Sáng - Trung | AM60: =COUNTA(I60:AL60)-COUNTIF(I60:AL60,"CT") -> 8
A61: Active | C61: HU ZONG | D61: Pro - Expat | E61: Pro - Expat | F61: Dầu Giây | AD61: Sáng - Trung | AE61: Sáng - Trung | AF61: Sáng - Trung | AG61: Sáng - Trung | AH61: Sáng - Trung | AJ61: Sáng - Trung | AK61: Sáng - Trung | AM61: =COUNTA(I61:AL61)-COUNTIF(I61:AL61,"CT") -> 7
A62: Active | C62: LU CHANG XI | D62: Pro - Expat | E62: Pro - Expat | F62: Dầu Giây | AE62: Sáng - Trung | AF62: Sáng - Trung | AG62: Sáng - Trung | AJ62: Sáng - Trung | AK62: Sáng - Trung | AL62: Sáng - Trung | AM62: =COUNTA(I62:AL62)-COUNTIF(I62:AL62,"CT") -> 6
A63: Active | C63: Pro - Expat | D63: Pro - Expat | E63: Pro - Expat | F63: Dầu Giây | AD63: Sáng - Trung | AE63: Sáng - Trung | AF63: Sáng - Trung | AG63: Sáng - Trung | AH63: Sáng - Trung | AJ63: Sáng - Trung | AK63: Sáng - Trung | AL63: Sáng - Trung | AM63: =COUNTA(I63:AL63)-COUNTIF(I63:AL63,"CT") -> 8
A64: Active | C64: Pro - Expat | D64: Pro - Expat | E64: Pro - Expat | F64: Dầu Giây | AD64: Sáng - Trung | AE64: Sáng - Trung | AF64: Sáng - Trung | AG64: Sáng - Trung | AH64: Sáng - Trung | AJ64: Sáng - Trung | AK64: Sáng - Trung | AL64: Sáng - Trung | AM64: =COUNTA(I64:AL64)-COUNTIF(I64:AL64,"CT") -> 8
A65: Active | C65: Pro - Expat | D65: Pro - Expat | E65: Pro - Expat | F65: Dầu Giây | AD65: Sáng - Trung | AE65: Sáng - Trung | AF65: Sáng - Trung | AG65: Sáng - Trung | AH65: Sáng - Trung | AJ65: Sáng - Trung | AK65: Sáng - Trung | AM65: =COUNTA(I65:AL65)-COUNTIF(I65:AL65,"CT") -> 7
A66: Active | C66: Pro - Expat | D66: Pro - Expat | E66: Pro - Expat | F66: Dầu Giây | AM66: =COUNTA(I66:AL66)-COUNTIF(I66:AL66,"CT") -> 0
A67: Active | F67: Dầu Giây | AM67: =COUNTA(I67:AL67)-COUNTIF(I67:AL67,"CT") -> 0
A68: Active | C68: Nguyễn Quang Khải | D68: Pro - Aging | E68: Pro - Aging | F68: Factory | AD68: Sáng - Mặn - Xưởng | AM68: =COUNTA(I68:AL68)-COUNTIF(I68:AL68,"CT") -> 1
A69: Active | C69: Nguyễn Phạm Kim Ngân | D69: Pro - Aging | E69: Pro - Aging | F69: Factory | AD69: Sáng - Mặn - Xưởng | AM69: =COUNTA(I69:AL69)-COUNTIF(I69:AL69,"CT") -> 1
A70: Active | C70: Phan Thị Ngọc Mai | D70: Pro - Painting | E70: Pro - Painting | F70: Factory | AD70: Sáng - Mặn - Xưởng | AM70: =COUNTA(I70:AL70)-COUNTIF(I70:AL70,"CT") -> 1
A71: Active | C71: Phan Tấn Hữu | D71: Pro - Packaging | E71: Pro - Packaging | F71: Factory | AD71: Sáng - Mặn - Xưởng | AM71: =COUNTA(I71:AL71)-COUNTIF(I71:AL71,"CT") -> 1
A72: Active | C72: Bùi Long Phi | D72: Pro - Polishing | E72: Pro - Polishing | F72: Factory | AD72: Sáng - Mặn - Xưởng | AM72: =COUNTA(I72:AL72)-COUNTIF(I72:AL72,"CT") -> 1
A73: Active | C73: Trần Minh Công | D73: Pro - CNC | E73: Pro - CNC | F73: Factory | AD73: Sáng - Mặn - Xưởng | AM73: =COUNTA(I73:AL73)-COUNTIF(I73:AL73,"CT") -> 1
A74: Active | C74: Vòng Quyền Chi | D74: Pro - Polishing | E74: Pro - Polishing | F74: Factory | AD74: Sáng - Mặn - Xưởng | AM74: =COUNTA(I74:AL74)-COUNTIF(I74:AL74,"CT") -> 1
A75: Active | C75: Nguyễn Văn Giang | D75: PMC - Quality | E75: PMC - Quality | F75: Factory | AD75: Sáng - Mặn - Xưởng | AM75: =COUNTA(I75:AL75)-COUNTIF(I75:AL75,"CT") -> 1
A76: Active | C76: Phạm Văn Khoai | D76: Pro - Polishing | E76: Pro - Polishing | F76: Factory | AD76: Sáng - Mặn - Xưởng | AM76: =COUNTA(I76:AL76)-COUNTIF(I76:AL76,"CT") -> 1
A77: Active | C77: Đào Văn Tuyển | D77: Pro - CNC | E77: Pro - CNC | F77: Factory | AD77: Sáng - Mặn - Xưởng | AM77: =COUNTA(I77:AL77)-COUNTIF(I77:AL77,"CT") -> 1
A78: Active | C78: Nguyễn Duy Luân | D78: Pro - CNC | E78: Pro - CNC | F78: Factory | AD78: Sáng - Mặn - Xưởng | AM78: =COUNTA(I78:AL78)-COUNTIF(I78:AL78,"CT") -> 1
A79: Active | C79: Nguyễn Thị Chúc | D79: Pro - CNC | E79: Pro - CNC | F79: Factory | AD79: Sáng - Mặn - Xưởng | AM79: =COUNTA(I79:AL79)-COUNTIF(I79:AL79,"CT") -> 1
A80: Active | C80: Trần Văn Nguyên | D80: Pro - CNC | E80: Pro - CNC | F80: Factory | AD80: Sáng - Mặn - Xưởng | AI80: Sáng - Mặn - Xưởng | AM80: =COUNTA(I80:AL80)-COUNTIF(I80:AL80,"CT") -> 2
A81: Active | C81: Lý Văn Chống | D81: Pro - Polishing | E81: Pro - Polishing | F81: Factory | AD81: Sáng - Mặn - Xưởng | AI81: Sáng - Mặn - Xưởng | AM81: =COUNTA(I81:AL81)-COUNTIF(I81:AL81,"CT") -> 2
A82: Active | C82: Mai Huỳnh Phi Long | D82: PMC - Quality | E82: PMC - Quality | F82: Factory | AD82: Sáng - Mặn - Xưởng | AI82: Sáng - Mặn - Xưởng | AM82: =COUNTA(I82:AL82)-COUNTIF(I82:AL82,"CT") -> 2
A83: Active | C83: Trần Nhớ | D83: Pro - Polishing | E83: Pro - Polishing | F83: Factory | AD83: Sáng - Mặn - Xưởng | AM83: =COUNTA(I83:AL83)-COUNTIF(I83:AL83,"CT") -> 1
A84: Active | C84: Lê Văn Tâm | D84: Pro - Polishing | E84: Pro - Polishing | F84: Factory | AD84: Sáng - Mặn - Xưởng | AM84: =COUNTA(I84:AL84)-COUNTIF(I84:AL84,"CT") -> 1
A85: Active | C85: Nguyễn Văn Tuấn | D85: Pro - Polishing | E85: Pro - Polishing | F85: Factory | AD85: Sáng - Mặn - Xưởng | AM85: =COUNTA(I85:AL85)-COUNTIF(I85:AL85,"CT") -> 1
A86: Active | C86: Trịnh Hải Nam | D86: PMC - Quality | E86: PMC - Quality | F86: Factory | AD86: Sáng - Mặn - Xưởng | AM86: =COUNTA(I86:AL86)-COUNTIF(I86:AL86,"CT") -> 1
A87: Active | C87: Nguyễn Minh Đức | D87: Pro - CNC | E87: Pro - CNC | F87: Factory | AD87: Sáng - Mặn - Xưởng | AM87: =COUNTA(I87:AL87)-COUNTIF(I87:AL87,"CT") -> 1
A88: Active | C88: Vũ Ngọc Đức | D88: Pro - CNC | E88: Pro - CNC | F88: Factory | AD88: Sáng - Mặn - Xưởng | AM88: =COUNTA(I88:AL88)-COUNTIF(I88:AL88,"CT") -> 1
A89: Active | C89: Vũ Đình Duy | D89: Pro - CNC | E89: Pro - CNC | F89: Factory | AD89: Sáng - Mặn - Xưởng | AM89: =COUNTA(I89:AL89)-COUNTIF(I89:AL89,"CT") -> 1
A90: Active | C90: Nguyễn Văn Lâm | D90: Pro - CNC | E90: Pro - CNC | F90: Factory | AD90: Sáng - Mặn - Xưởng | AM90: =COUNTA(I90:AL90)-COUNTIF(I90:AL90,"CT") -> 1
A91: Active | C91: Sercurity | D91: SubContractor | E91: SubContractor | F91: Factory | AD91: Sáng - Mặn - Xưởng | AM91: =COUNTA(I91:AL91)-COUNTIF(I91:AL91,"CT") -> 1
A92: Active | C92: Sercurity | D92: SubContractor | E92: SubContractor | F92: Factory | AD92: Sáng - Mặn - Xưởng | AM92: =COUNTA(I92:AL92)-COUNTIF(I92:AL92,"CT") -> 1
A93: Active | C93: Nguyễn Minh Thi | D93: Pro - Data | E93: Pro - Data | F93: Factory | AD93: Sáng - Mặn - Xưởng | AM93: =COUNTA(I93:AL93)-COUNTIF(I93:AL93,"CT") -> 1
A94: Active | C94: Chu Quang Tiến | D94: Pro - CNC | E94: Pro - CNC | F94: Factory | AD94: Sáng - Mặn - Xưởng | AM94: =COUNTA(I94:AL94)-COUNTIF(I94:AL94,"CT") -> 1
A95: Active | F95: Dầu Giây | AM95: =COUNTA(I95:AL95)-COUNTIF(I95:AL95,"CT") -> 0
A96: Active | C96: Khưu Thị Cẩm Lai | D96: Pro - Packaging | E96: Pro - Packaging | F96: Factory | AI96: Sáng - Mặn - Xưởng | AM96: =COUNTA(I96:AL96)-COUNTIF(I96:AL96,"CT") -> 1
A97: Active | C97: Trần Thị Quỳnh Như | D97: Pro - Packaging | E97: Pro - Packaging | F97: Factory | AI97: Sáng - Mặn - Xưởng | AM97: =COUNTA(I97:AL97)-COUNTIF(I97:AL97,"CT") -> 1
A98: Active | C98: Phạm Thị Ngọc Diễm | D98: Pro - Data | E98: Pro - Data | F98: Office | AI98: Sáng - Mặn - Xưởng | AM98: =COUNTA(I98:AL98)-COUNTIF(I98:AL98,"CT") -> 1
A99: Active | C99: Đoàn Thị Chút | D99: Pro - Packaging | E99: Pro - Packaging | F99: Factory | AI99: Sáng - Mặn - Xưởng | AM99: =COUNTA(I99:AL99)-COUNTIF(I99:AL99,"CT") -> 1
A100: Active | C100: Xu Jingang | D100: Pro - Expat | E100: Pro - Expat | F100: Chinese | AI100: Sáng - Trung | AM100: =COUNTA(I100:AL100)-COUNTIF(I100:AL100,"CT") -> 1
A101: Active | C101: Li WenQiang | D101: Pro - Expat | E101: Pro - Expat | F101: Chinese | AI101: Sáng - Trung | AM101: =COUNTA(I101:AL101)-COUNTIF(I101:AL101,"CT") -> 1
...

Sheet HHVCV - Tăng ca
I1: 46266 | J1: 46267 | K1: 46268 | L1: 46269 | M1: 46270 | N1: 46271 | O1: 46272 | P1: 46273 | Q1: 46274 | R1: 46275 | S1: 46276 | T1: 46277 | U1: 46278 | V1: 46279 | W1: 46280 | X1: 46281 | Y1: 46282 | Z1: 46283 | AA1: 46284 | AB1: 46285 | AC1: 46286 | AD1: 46287 | AE1: 46288 | AF1: 46289 | AG1: 46290 | AH1: 46291 | AI1: 46292 | AJ1: 46293 | AK1: 46294 | AL1: 46295
J2: =SUM(J3:J7) -> 0 | K2: =SUM(K3:K7) -> 0 | L2: =SUM(L3:L7) -> 0 | N2: =SUM(N3:N7) -> 0 | O2: =SUM(O3:O7) -> 0 | P2: =SUM(P3:P7) -> 0 | Q2: =SUM(Q3:Q7) -> 0 | R2: =SUM(R3:R7) -> 0 | S2: =SUM(S3:S7) -> 0 | T2: =SUM(T3:T7) -> 0 | U2: =SUM(U3:U7) -> 0 | ... AK2: =SUM(AK3:AK7) -> 0
I3: =COUNTIFS(I$15:I$102,$H3) -> 0 | J3: =COUNTIFS(J$15:J$102,$H3) -> 0 | K3: =COUNTIFS(K$15:K$102,$H3) -> 0 | L3: =COUNTIFS(L$15:L$102,$H3) -> 0 | N3: =COUNTIFS(N$15:N$102,$H3) -> 0 | O3: =COUNTIFS(O$15:O$102,$H3) -> 0 | P3: =COUNTIFS(P$15:P$102,$H3) -> 0 | Q3: =COUNTIFS(Q$15:Q$102,$H3) -> 0 | R3: =COUNTIFS(R$15:R$102,$H3) -> 0 | S3: =COUNTIFS(S$15:S$102,$H3) -> 0 | T3: =COUNTIFS(T$15:T$102,$H3) -> 0 | U3: =COUNTIFS(U$15:U$102,$H3) -> 0 | ... AK3: =COUNTIFS(AK$15:AK$102,$H3) -> 0
I4: =COUNTIFS(I$15:I$102,$H4)-I5 -> 0 | J4: =COUNTIFS(J$15:J$102,$H4)-J5 -> 0 | K4: =COUNTIFS(K$15:K$102,$H4)-K5 -> 0 | L4: =COUNTIFS(L$15:L$102,$H4)-L5 -> 0 | N4: =COUNTIFS(N$15:N$102,$H4)-N5 -> 0 | O4: =COUNTIFS(O$15:O$102,$H4)-O5 -> 0 | P4: =COUNTIFS(P$15:P$102,$H4)-P5 -> 0 | Q4: =COUNTIFS(Q$15:Q$102,$H4)-Q5 -> 0 | R4: =COUNTIFS(R$15:R$102,$H4)-R5 -> 0 | S4: =COUNTIFS(S$15:S$102,$H4)-S5 -> 0 | T4: =COUNTIFS(T$15:T$102,$H4)-T5 -> 0 | U4: =COUNTIFS(U$15:U$102,$H4)-U5 -> 0 | ... AK4: =COUNTIFS(AK$15:AK$102,$H4)-AK5 -> 0
G7: DS- Vegetarian rice | H7: Cơm ca đêm
G8: Shift 2 | H8: Ca chiều | I8: =I9+I12 -> 0 | J8: =J9+J12 -> 0 | K8: =K9+K12 -> 0 | L8: =L9+L12 -> 0 | M8: =M9+M12 -> 0 | N8: =N9+N12 -> 0 | O8: =O9+O12 -> 0 | P8: =P9+P12 -> 0 | ... AK8: =AK9+AK12 -> 24
G9: Savory Dinner | H9: Cơm Chiều Mặn | I9: =SUM(I10:I11)-I12 -> 0 | J9: =SUM(J10:J11)-J12 -> 0 | K9: =SUM(K10:K11)-K12 -> 0 | L9: =SUM(L10:L11)-L12 -> 0 | M9: =SUM(M10:M11)-M12 -> 0 | N9: =SUM(N10:N11)-N12 -> 0 | O9: =SUM(O10:O11)-O12 -> 0 | P9: =SUM(P10:P11)-P12 -> 0 | ... AL9: =SUM(AL10:AL11)-AL12 -> 21
E10: 45 | F10: =SUM(I10:AL10) -> 67 | G10: Overtime meal | H10: Cơm tăng Ca - TQ | I10: =COUNTIFS($I15:I$456,$H$10) -> 0 | J10: =COUNTIFS(J16:J456,$H$10) -> 0 | K10: =COUNTIFS(K16:K281,$H$10) -> 0 | L10: =COUNTIFS(L16:L480,$H$10) -> 0 | M10: =COUNTIFS(M16:M480,$H$10) -> 0 | N10: =COUNTIFS(N16:N480,$H$10) -> 0 | O10: =COUNTIFS(O16:O480,$H$10) -> 0 | P10: =COUNTIFS(P16:P480,$H$10) -> 0 | Q10: =COUNTIFS(Q16:Q553,$H$10) -> 0 | R10: =COUNTIFS(R16:R480,$H$10) -> 0 | S10: =COUNTIFS(S16:S480,$H$10) -> 0 | T10: =COUNTIFS(T16:T480,$H$10) -> 0 | U10: =COUNTIFS(U16:U480,$H$10) -> 0 | V10: =COUNTIFS(V16:V480,$H$10) -> 0 | W10: =COUNTIFS(W16:W480,$H$10) -> 0 | X10: =COUNTIFS(X16:X480,$H$10) -> 0 | Y10: =COUNTIFS(Y16:Y480,$H$10) -> 0 | ... AL10: =COUNTIFS(AL16:AL480,$H$10) -> 5
F11: =SUM(I11:AL11) -> 65 | G11: Overtime meal | H11: Cơm Tăng Ca | I11: =COUNTIFS(I16:I456,$H$11) -> 0 | J11: =COUNTIFS(J16:J281,$H$11) -> 0 | K11: =COUNTIFS(K16:K281,$H$11) -> 0 | L11: =COUNTIFS(L16:L480,$H$11) -> 0 | M11: =COUNTIFS(M16:M480,$H$11) -> 0 | N11: =COUNTIFS(N16:N480,$H$11) -> 0 | O11: =COUNTIFS(O16:O480,$H$11) -> 0 | P11: =COUNTIFS(P16:P480,$H$11) -> 0 | Q11: =COUNTIFS(Q16:Q553,$H$11) -> 0 | R11: =COUNTIFS(R16:R480,$H$11) -> 0 | S11: =COUNTIFS(S16:S480,$H$11) -> 0 | T11: =COUNTIFS(T16:T480,$H$11) -> 0 | U11: =COUNTIFS(U16:U480,$H$11) -> 0 | V11: =COUNTIFS(V16:V480,$H$11) -> 0 | W11: =COUNTIFS(W16:W480,$H$11) -> 0 | X11: =COUNTIFS(X16:X480,$H$11) -> 0 | Y11: =COUNTIFS(Y16:Y480,$H$11) -> 0 | ... AL11: =COUNTIFS(AL16:AL480,$H$11) -> 16
G12: Vegan Dinner | H12: Cơm Chiều Chay
F13: =SUM(I13:AL13) -> 132 | G13: Total | H13: Total | I13: =I9+I12 -> 0 | J13: =J9+J12 -> 0 | K13: =K9+K12 -> 0 | L13: =L9+L12 -> 0 | M13: =M9+M12 -> 0 | N13: =N9+N12 -> 0 | O13: =O9+O12 -> 0 | P13: =P9+P12 -> 0 | ... AL13: =AL9+AL12 -> 21 | AM13: =SUM(I13:AL13) -> 132
A15: Status | B15: Code | C15: Fullname VN | D15: Department | E15: Section | F15: Place | I15: 34 | J15: 35 | K15: 36 | L15: 37 | N15: 40 | O15: 41 | P15: 42 | Q15: 43 | R15: 43 | S15: 44 | T15: 45 | U15: 46 | V15: 47 | W15: 48 | X15: 49 | Y15: 50 | Z15: 51 | AA15: 52 | AB15: 53 | AC15: 54 | AD15: 55 | AE15: 56 | AF15: 57 | AG15: 58 | AH15: 59 | AI15: 60 | AJ15: 61 | AK15: 62 | AM15: Total meals per day
A16: Active | B16: 26000 | C16: Nguyễn Thị Ngọc Nữ | D16: HHVCV | F16: Dầu Giây | AE16: Cơm tăng ca | AJ16: Cơm tăng ca | AK16: Cơm tăng ca | AL16: Cơm Tăng Ca | AM16: =COUNTA(I16:AL16) -> 4
A17: Active | B17: 26001 | C17: Trần Minh Thiện | D17: HHVCV | F17: Dầu Giây | AJ17: Cơm tăng ca | AK17: Cơm tăng ca | AL17: Cơm Tăng Ca | AM17: =COUNTA(I17:AL17) -> 3
A18: Active | B18: 26004 | C18: Trần Thị Oanh Đào | D18: HHVCV | F18: Dầu Giây | AE18: Cơm tăng ca | AK18: Cơm tăng ca | AL18: Cơm Tăng Ca | AM18: =COUNTA(I18:AL18) -> 3
A19: Active | B19: 26005 | C19: Nguyễn Minh Lâm | D19: HHVCV | F19: Dầu Giây | AE19: Cơm tăng ca | AJ19: Cơm tăng ca | AK19: Cơm tăng ca | AL19: Cơm Tăng Ca | AM19: =COUNTA(I19:AL19) -> 4
A20: Active | B20: 26006 | C20: Nguyễn Ngọc Quỳnh Như | D20: HHVCV | F20: Dầu Giây | AE20: Cơm tăng ca | AJ20: Cơm tăng ca | AK20: Cơm tăng ca | AL20: Cơm Tăng Ca | AM20: =COUNTA(I20:AL20) -> 4
A21: Active | B21: 26007 | C21: Nguyễn Văn Duyên | D21: HHVCV | F21: Dầu Giây | AE21: Cơm tăng ca | AJ21: Cơm tăng ca | AK21: Cơm tăng ca | AL21: Cơm Tăng Ca | AM21: =COUNTA(I21:AL21) -> 4
A22: Active | B22: 26009 | C22: Trần Minh Kim | D22: HHVCV | F22: Dầu Giây | AE22: Cơm tăng ca | AJ22: Cơm tăng ca | AK22: Cơm tăng ca | AL22: Cơm Tăng Ca | AM22: =COUNTA(I22:AL22) -> 4
A23: Active | B23: 26010 | C23: Phan Huynh Ngọc Diễm | D23: HHVCV | F23: Dầu Giây | AJ23: Cơm tăng ca | AL23: Cơm Tăng Ca | AM23: =COUNTA(I23:AL23) -> 2
A24: Active | B24: 26011 | C24: Lê Đức Quyền | D24: HHVCV | F24: Dầu Giây | AE24: Cơm tăng ca | AK24: Cơm tăng ca | AL24: Cơm Tăng Ca | AM24: =COUNTA(I24:AL24) -> 3
A25: Active | B25: 26012 | C25: Nguyễn Văn Thông | D25: HHVCV | F25: Dầu Giây | AE25: Cơm tăng ca | AK25: Cơm tăng ca | AL25: Cơm Tăng Ca | AM25: =COUNTA(I25:AL25) -> 3
A26: Active | B26: 26013 | C26: Lê Phạm Như Quỳnh | D26: HHVCV | F26: Dầu Giây | AJ26: Cơm tăng ca | AK26: Cơm tăng ca | AL26: Cơm Tăng Ca | AM26: =COUNTA(I26:AL26) -> 3
A27: Active | B27: 26014 | C27: Trương Vũ Thiên Nhi | D27: HHVCV | F27: Dầu Giây | AE27: Cơm tăng ca | AJ27: Cơm tăng ca | AL27: Cơm Tăng Ca | AM27: =COUNTA(I27:AL27) -> 3
A28: Active | B28: 26016 | C28: Phạm Anh Vũ | D28: HHVCV | F28: Dầu Giây | AE28: Cơm tăng ca | AJ28: Cơm tăng ca | AK28: Cơm tăng ca | AL28: Cơm Tăng Ca | AM28: =COUNTA(I28:AL28) -> 4
A29: Active | B29: 26017 | C29: Bùi Vũ Bảo Trâm | D29: HHVCV | F29: Dầu Giây | AE29: Cơm tăng ca | AK29: Cơm tăng ca | AL29: Cơm Tăng Ca | AM29: =COUNTA(I29:AL29) -> 3
A30: Active | B30: 26003 | C30: Thòng Hoàng Long | D30: HHVCV | F30: Dầu Giây | AE30: Cơm tăng ca | AJ30: Cơm tăng ca | AL30: Cơm Tăng Ca | AM30: =COUNTA(I30:AL30) -> 3
A31: Active | B31: 26002 | C31: Trần Hoài Yến Nhi | D31: HHVCV | F31: Dầu Giây | AK31: Cơm tăng ca | AM31: =COUNTA(I31:AL31) -> 1
A32: Active | C32: Nguyễn Minh Phụng | D32: HHVCV | F32: Dầu Giây | AK32: Cơm tăng ca | AM32: =COUNTA(I32:AL32) -> 1
A33: Active | C33: Phạm Thị Thuỳ Tiên | D33: HHVCV | F33: Dầu Giây | AJ33: Cơm tăng ca | AK33: Cơm tăng ca | AM33: =COUNTA(I33:AL33) -> 2
A34: Active | C34: Võ Minh Đạt | D34: HHVCV | F34: Dầu Giây | AE34: Cơm tăng ca | AM34: =COUNTA(I34:AL34) -> 1
A35: Active | B35: VCV0320 | C35: Đõ Lệ Ngọc | D35: PMC - WH | E35: PMC - WH | F35: Dầu Giây | AJ35: Cơm tăng ca | AM35: =COUNTA(I35:AL35) -> 1
A36: Active | B36: VCV0788 | C36: Diệu Ngọc | D36: PMC - WH | E36: PMC - WH | F36: Dầu Giây | AJ36: Cơm tăng ca | AM36: =COUNTA(I36:AL36) -> 1
A37: Active | B37: VCV0719 | C37: Trịnh Xuân Trường | D37: PMC - WH | E37: PMC - WH | F37: Dầu Giây | AJ37: Cơm tăng ca | AM37: =COUNTA(I37:AL37) -> 1
A38: Active | B38: VCV0750 | C38: Huỳnh Khánh Duy | D38: PMC - WH | E38: PMC - WH | F38: Dầu Giây | AJ38: Cơm tăng ca | AM38: =COUNTA(I38:AL38) -> 1
A39: Active | B39: VCV0623 | C39: Phạm Văn Tuấn | D39: PMC - WH | E39: PMC - WH | F39: Dầu Giây | AJ39: Cơm tăng ca | AM39: =COUNTA(I39:AL39) -> 1
A40: Active | B40: VCV0787 | C40: Nguyễn Phúc Ân | D40: PMC - WH | E40: PMC - WH | F40: Dầu Giây | AM40: =COUNTA(I40:AL40) -> 0
A41: Active | B41: VCV0756 | C41: Lường Chắn Hoa | D41: PMC - WH | E41: PMC - WH | F41: Dầu Giây | AJ41: Cơm tăng ca | AM41: =COUNTA(I41:AL41) -> 1
A42: Active | C42: Trần Minh Hiếu | D42: PMC - WH | E42: PMC - WH | F42: Dầu Giây | AJ42: Cơm tăng ca | AM42: =COUNTA(I42:AL42) -> 1
A43: Active | B43: VCV0444 | C43: Lê Doãn Hội | D43: PMC - WH | E43: PMC - WH | F43: Dầu Giây | AM43: =COUNTA(I43:AL43) -> 0
A44: Active | B44: VCV0501 | C44: Nguyễn Văn Phước | D44: PMC - WH | E44: PMC - WH | F44: Dầu Giây | AJ44: Cơm tăng ca | AM44: =COUNTA(I44:AL44) -> 1
A45: Active | B45: VCV0770 | C45: Tsần Thị Hồng Linh | D45: PMC - WH | E45: PMC - WH | F45: Dầu Giây | AM45: =COUNTA(I45:AL45) -> 0
A46: Active | B46: VCV0807 | C46: Mã Cắm Phùng | D46: PMC - WH | E46: PMC - WH | F46: Dầu Giây | AM46: =COUNTA(I46:AL46) -> 0
A47: Active | C47: Phạm Song Quý | D47: Subcontractor | E47: Driver | F47: Dầu Giây | AM47: =COUNTA(I47:AL47) -> 0
A48: Active | C48: Đỗ Đông Đức | D48: Subcontractor | E48: Driver | F48: Dầu Giây | AM48: =COUNTA(I48:AL48) -> 0
A49: Active | C49: Nguyễn Ngân | D49: Subcontractor | E49: Driver | F49: Dầu Giây | AM49: =COUNTA(I49:AL49) -> 0
A50: Active | C50: Nguyễn Đức Ân | D50: Subcontractor | E50: Driver | F50: Dầu Giây | AM50: =COUNTA(I50:AL50) -> 0
A51: Active | C51: Lã Công Trung | D51: PMC - Quality | E51: PMC - Quality | F51: Dầu Giây | AM51: =COUNTA(I51:AL51) -> 0
A52: Active | C52: Phạm Quan Thái | D52: COO - Maintenance | E52: COO - Maintenance | F52: Dầu Giây | AM52: =COUNTA(I52:AL52) -> 0
A53: Active | C53: Nguyễn Hoàng Khang | D53: COO - Maintenance | E53: COO - Maintenance | F53: Dầu Giây | AM53: =COUNTA(I53:AL53) -> 0
A54: Active | C54: Đặng Văn Long | D54: COO - Maintenance | E54: COO - Maintenance | F54: Dầu Giây | AM54: =COUNTA(I54:AL54) -> 0
A55: Active | C55: Trần Kim Hải | D55: Subcontractor | E55: Security | F55: Dầu Giây | AK55: Cơm tăng ca | AL55: Cơm Tăng Ca | AM55: =COUNTA(I55:AL55) -> 2
A56: Active | C56: Lý Văn Trung | D56: Subcontractor | E56: Security | F56: Dầu Giây | AM56: =COUNTA(I56:AL56) -> 0
A57: Active | C57: Shipping fee | D57: Pro - Expat | E57: Pro - Expat | F57: Dầu Giây | AM57: =COUNTA(I57:AL57) -> 0
A58: Active | C58: Shipping fee | D58: Pro - Expat | E58: Pro - Expat | F58: Dầu Giây | AM58: =COUNTA(I58:AL58) -> 0
A59: Active | C59: ZHANG LANG XING | D59: Pro - Expat | E59: Pro - Expat | F59: Dầu Giây | AD59: Cơm tăng Ca - TQ | AE59: Cơm tăng Ca - TQ | AF59: Cơm tăng Ca - TQ | AH59: Cơm tăng Ca - TQ | AJ59: Cơm tăng Ca - TQ | AM59: =COUNTA(I59:AL59) -> 5
A60: Active | C60: ZHANG FANXING | D60: Pro - Expat | E60: Pro - Expat | F60: Dầu Giây | AD60: Cơm tăng Ca - TQ | AE60: Cơm tăng Ca - TQ | AF60: Cơm tăng Ca - TQ | AH60: Cơm tăng Ca - TQ | AJ60: Cơm tăng Ca - TQ | AM60: =COUNTA(I60:AL60) -> 5
A61: Active | C61: ZHANG CHUMING | D61: Pro - Expat | E61: Pro - Expat | F61: Dầu Giây | AD61: Cơm tăng Ca - TQ | AE61: Cơm tăng Ca - TQ | AF61: Cơm tăng Ca - TQ | AH61: Cơm tăng Ca - TQ | AJ61: Cơm tăng Ca - TQ | AK61: Cơm tăng Ca - TQ | AL61: Cơm tăng Ca - TQ | AM61: =COUNTA(I61:AL61) -> 7
A62: Active | C62: ZHANG WEXING | D62: Pro - Expat | E62: Pro - Expat | F62: Dầu Giây | AD62: Cơm tăng Ca - TQ | AE62: Cơm tăng Ca - TQ | AF62: Cơm tăng Ca - TQ | AH62: Cơm tăng Ca - TQ | AJ62: Cơm tăng Ca - TQ | AK62: Cơm tăng Ca - TQ | AL62: Cơm tăng Ca - TQ | AM62: =COUNTA(I62:AL62) -> 7
A63: Active | C63: MA JIANJIE | D63: Pro - Expat | E63: Pro - Expat | F63: Dầu Giây | AD63: Cơm tăng Ca - TQ | AE63: Cơm tăng Ca - TQ | AF63: Cơm tăng Ca - TQ | AH63: Cơm tăng Ca - TQ | AJ63: Cơm tăng Ca - TQ | AK63: Cơm tăng Ca - TQ | AL63: Cơm tăng Ca - TQ | AM63: =COUNTA(I63:AL63) -> 7
A64: Active | C64: WANG GUANRONG | D64: Pro - Expat | E64: Pro - Expat | F64: Dầu Giây | AD64: Cơm tăng Ca - TQ | AE64: Cơm tăng Ca - TQ | AF64: Cơm tăng Ca - TQ | AH64: Cơm tăng Ca - TQ | AJ64: Cơm tăng Ca - TQ | AK64: Cơm tăng Ca - TQ | AL64: Cơm tăng Ca - TQ | AM64: =COUNTA(I64:AL64) -> 7
A65: Active | C65: HU ZONG | D65: Pro - Expat | E65: Pro - Expat | F65: Dầu Giây | AM65: =COUNTA(I65:AL65) -> 0
A66: Active | C66: LU CHANG XI | D66: Pro - Expat | E66: Pro - Expat | F66: Dầu Giây | AD66: Cơm tăng Ca - TQ | AE66: Cơm tăng Ca - TQ | AF66: Cơm tăng Ca - TQ | AH66: Cơm tăng Ca - TQ | AI66: Cơm tăng Ca - TQ | AJ66: Cơm tăng Ca - TQ | AK66: Cơm tăng Ca - TQ | AL66: Cơm tăng Ca - TQ | AM66: =COUNTA(I66:AL66) -> 8
A67: Active | C67: Pro - Expat | D67: Pro - Expat | E67: Pro - Expat | F67: Dầu Giây | AD67: Cơm tăng Ca - TQ | AE67: Cơm tăng Ca - TQ | AF67: Cơm tăng Ca - TQ | AH67: Cơm tăng Ca - TQ | AI67: Cơm tăng Ca - TQ | AJ67: Cơm tăng Ca - TQ | AK67: Cơm tăng Ca - TQ | AM67: =COUNTA(I67:AL67) -> 7
A68: Active | C68: Pro - Expat | D68: Pro - Expat | E68: Pro - Expat | F68: Dầu Giây | AD68: Cơm tăng Ca - TQ | AE68: Cơm tăng Ca - TQ | AF68: Cơm tăng Ca - TQ | AH68: Cơm tăng Ca - TQ | AI68: Cơm tăng Ca - TQ | AJ68: Cơm tăng Ca - TQ | AK68: Cơm tăng Ca - TQ | AM68: =COUNTA(I68:AL68) -> 7
A69: Active | C69: Pro - Expat | D69: Pro - Expat | E69: Pro - Expat | F69: Dầu Giây | AD69: Cơm tăng Ca - TQ | AE69: Cơm tăng Ca - TQ | AF69: Cơm tăng Ca - TQ | AH69: Cơm tăng Ca - TQ | AI69: Cơm tăng Ca - TQ | AJ69: Cơm tăng Ca - TQ | AK69: Cơm tăng Ca - TQ | AM69: =COUNTA(I69:AL69) -> 7
A70: Active | AM70: =COUNTA(I70:AL70) -> 0
A71: Active | AM71: =COUNTA(I71:AL71) -> 0
A72: Active | AM72: =COUNTA(I72:AL72) -> 0
A73: Active | AM73: =COUNTA(I73:AL73) -> 0
A74: Active | AM74: =COUNTA(I74:AL74) -> 0
A75: Active | AM75: =COUNTA(I75:AL75) -> 0
A76: Active | AM76: =COUNTA(I76:AL76) -> 0
A77: Active | AM77: =COUNTA(I77:AL77) -> 0
A78: Active | AM78: =COUNTA(I78:AL78) -> 0
A79: Active | AM79: =COUNTA(I79:AL79) -> 0
A80: Active | AM80: =COUNTA(I80:AL80) -> 0
A81: Active | AM81: =COUNTA(I81:AL81) -> 0
... A355: Active | AM355: =COUNTA(I355:AL355) -> 0
AM358: =COUNTA(I358:AL358) -> 0
AM359: =COUNTA(I359:AL359) -> 0
AM360: =COUNTA(I360:AL360) -> 0
AM361: =COUNTA(I361:AL361) -> 0
AM362: =COUNTA(I362:AL362) -> 0
AM363: =COUNTA(I363:AL363) -> 0
AM364: =COUNTA(I364:AL364) -> 0
AM365: =COUNTA(I365:AL365) -> 0
AM366: =COUNTA(I366:AL366) -> 0
AM367: =COUNTA(I367:AL367) -> 0
AM368: =COUNTA(I368:AL368) -> 0
AM369: =COUNTA(I369:AL369) -> 0
... AM427: =COUNTA(I427:AL427) -> 0
AM428: =COUNTA(I428:AL428)-COUNTIF(I428:AL428,"CT") -> 0

Sheet Payment
A1: Meal Consumption & Cost Summary on May 2026
A3: 1. Meal Summary by Date
A5: Date | B5: Expat Meals Cơm chuyên gia Trung Quốc | C5: Expat Meals - Overtime Cơm chuyên gia Trung Quốc - Tăng ca | D5: Shift 1+ Nomal Meals Cơm ca 1 + Cơm hành chính | E5: Shift 2 Meals Cơm ca 2 | F5: Overtime Meals Cơm tăng ca | G5: Total Meals per day Tổng phần ăn
A6: 46266 | B6: ='VP SÁNG '!I9 -> 25 | C6: 0 | D6: ='VP SÁNG '!I10 -> 336 | E6: ='CHIỀU '!I10 -> 3 | F6: ='CHIỀU '!I11 -> 13 | G6: =SUM(B6:F6) -> 377
A7: 46267 | B7: ='VP SÁNG '!J9 -> 0 | C7: 0 | D7: ='VP SÁNG '!J10 -> 0 | E7: ='CHIỀU '!J10 -> 0 | F7: ='CHIỀU '!J11 -> 0 | G7: =SUM(B7:F7) -> 0
A8: 46268 | B8: ='VP SÁNG '!K9 -> 0 | C8: 0 | D8: ='VP SÁNG '!K10 -> 0 | E8: ='CHIỀU '!K10 -> 0 | F8: ='CHIỀU '!K11 -> 0 | G8: =SUM(B8:F8) -> 0
A9: 46269 | B9: ='VP SÁNG '!L9 -> 25 | C9: 0 | D9: ='VP SÁNG '!L10 -> 333 | E9: ='CHIỀU '!L10 -> 3 | F9: ='CHIỀU '!L11 -> 127 | G9: =SUM(B9:F9) -> 488
A10: 46270 | B10: ='VP SÁNG '!M9 -> 24 | C10: 0 | D10: ='VP SÁNG '!M10 -> 339 | E10: ='CHIỀU '!M10 -> 3 | F10: ='CHIỀU '!M11 -> 15 | G10: =SUM(B10:F10) -> 381
A11: 46271 | B11: ='VP SÁNG '!N9 -> 5 | C11: 0 | D11: ='VP SÁNG '!N10 -> 67 | E11: ='CHIỀU '!N10 -> 0 | F11: ='CHIỀU '!N11 -> 0 | G11: =SUM(B11:F11) -> 72
A12: 46272 | B12: ='VP SÁNG '!O9 -> 25 | C12: 0 | D12: ='VP SÁNG '!O10 -> 345 | E12: ='CHIỀU '!O10 -> 3 | F12: ='CHIỀU '!O11 -> 121 | G12: =SUM(B12:F12) -> 494
A13: 46273 | B13: ='VP SÁNG '!P9 -> 25 | C13: 0 | D13: ='VP SÁNG '!P10 -> 304 | E13: ='CHIỀU '!P10 -> 10 | F13: ='CHIỀU '!P11 -> 123 | G13: =SUM(B13:F13) -> 462
A14: 46274 | B14: ='VP SÁNG '!Q9 -> 23 | C14: 0 | D14: ='VP SÁNG '!Q10 -> 306 | E14: ='CHIỀU '!Q10 -> 11 | F14: ='CHIỀU '!Q11 -> 131 | G14: =SUM(B14:F14) -> 471
A15: 46275 | B15: ='VP SÁNG '!R9 -> 26 | C15: 0 | D15: ='VP SÁNG '!R10 -> 316 | E15: ='CHIỀU '!R10 -> 10 | F15: ='CHIỀU '!R11 -> 103 | G15: =SUM(B15:F15) -> 455
A16: 46276 | B16: ='VP SÁNG '!S9 -> 25 | C16: 0 | D16: ='VP SÁNG '!S10 -> 290 | E16: ='CHIỀU '!S10 -> 7 | F16: ='CHIỀU '!S11 -> 108 | G16: =SUM(B16:F16) -> 430
A17: 46277 | B17: ='VP SÁNG '!T9 -> 23 | C17: 0 | D17: ='VP SÁNG '!T10 -> 288 | E17: ='CHIỀU '!T10 -> 11 | F17: ='CHIỀU '!T11 -> 17 | G17: =SUM(B17:F17) -> 339
A18: 46278 | B18: ='VP SÁNG '!U9 -> 0 | C18: 0 | D18: ='VP SÁNG '!U10 -> 0 | E18: ='CHIỀU '!U10 -> 0 | F18: ='CHIỀU '!U11 -> 0 | G18: =SUM(B18:F18) -> 0
A19: 46279 | B19: ='VP SÁNG '!V9 -> 27 | C19: 0 | D19: ='VP SÁNG '!V10 -> 340 | E19: ='CHIỀU '!V10 -> 3 | F19: ='CHIỀU '!V11 -> 116 | G19: =SUM(B19:F19) -> 486
A20: 46280 | B20: ='VP SÁNG '!W9 -> 27 | C20: 0 | D20: ='VP SÁNG '!W10 -> 343 | E20: ='CHIỀU '!W10 -> 11 | F20: ='CHIỀU '!W11 -> 215 | G20: =SUM(B20:F20) -> 596
A21: 46281 | B21: ='VP SÁNG '!X9 -> 26 | C21: 0 | D21: ='VP SÁNG '!X10 -> 345 | E21: ='CHIỀU '!X10 -> 9 | F21: ='CHIỀU '!X11 -> 221 | G21: =SUM(B21:F21) -> 601
A22: 46282 | B22: ='VP SÁNG '!Y9 -> 25 | C22: 0 | D22: ='VP SÁNG '!Y10 -> 350 | E22: ='CHIỀU '!Y10 -> 9 | F22: ='CHIỀU '!Y11 -> 229 | G22: =SUM(B22:F22) -> 613
A23: 46283 | B23: ='VP SÁNG '!Z9 -> 24 | C23: 0 | D23: ='VP SÁNG '!Z10 -> 353 | E23: ='CHIỀU '!Z10 -> 3 | F23: ='CHIỀU '!Z11 -> 134 | G23: =SUM(B23:F23) -> 514
A24: 46284 | B24: ='VP SÁNG '!AA9 -> 22 | C24: 0 | D24: ='VP SÁNG '!AA10 -> 341 | E24: ='CHIỀU '!AA10 -> 3 | F24: ='CHIỀU '!AA11 -> 27 | G24: =SUM(B24:F24) -> 393
A25: 46285 | B25: ='VP SÁNG '!AB9 -> 6 | C25: 0 | D25: ='VP SÁNG '!AB10 -> 67 | E25: ='CHIỀU '!AB10 -> 0 | F25: ='CHIỀU '!AB11 -> 0 | G25: =SUM(B25:F25) -> 73
A26: 46286 | B26: ='VP SÁNG '!AC9 -> 25 | C26: 0 | D26: ='VP SÁNG '!AC10 -> 336 | E26: ='CHIỀU '!AC10 -> 10 | F26: ='CHIỀU '!AC11 -> 209 | G26: =SUM(B26:F26) -> 580
A27: 46287 | B27: ='VP SÁNG '!AD9+HHVCV!AD7 -> 38 | C27: ='HHVCV - Tăng ca'!AD10 -> 10 | D27: ='VP SÁNG '!AD10+HHVCV!AD8 -> 410 | E27: ='CHIỀU '!AD10 -> 10 | F27: ='CHIỀU '!AD11+'HHVCV - Tăng ca'!AD11 -> 235 | G27: =SUM(B27:F27) -> 703
A28: 46288 | B28: ='VP SÁNG '!AE9+HHVCV!AE7 -> 39 | C28: ='HHVCV - Tăng ca'!AE10 -> 10 | D28: ='VP SÁNG '!AE10+HHVCV!AE8 -> 371 | E28: ='CHIỀU '!AE10 -> 10 | F28: ='CHIỀU '!AE11+'HHVCV - Tăng ca'!AE11 -> 244 | G28: =SUM(B28:F28) -> 674
A29: 46289 | B29: ='VP SÁNG '!AF9+HHVCV!AF7 -> 39 | C29: ='HHVCV - Tăng ca'!AF10 -> 10 | D29: ='VP SÁNG '!AF10+HHVCV!AF8 -> 370 | E29: ='CHIỀU '!AF10 -> 9 | F29: ='CHIỀU '!AF11+'HHVCV - Tăng ca'!AF11 -> 229 | G29: =SUM(B29:F29) -> 657
A30: 46290 | B30: ='VP SÁNG '!AG9+HHVCV!AG7 -> 38 | C30: ='HHVCV - Tăng ca'!AG10 -> 0 | D30: ='VP SÁNG '!AG10+HHVCV!AG8 -> 378 | E30: ='CHIỀU '!AG10 -> 3 | F30: ='CHIỀU '!AG11+'HHVCV - Tăng ca'!AG11 -> 85 | G30: =SUM(B30:F30) -> 504
A31: 46291 | B31: ='VP SÁNG '!AH9+HHVCV!AH7 -> 37 | C31: ='HHVCV - Tăng ca'!AH10 -> 10 | D31: ='VP SÁNG '!AH10+HHVCV!AH8 -> 362 | E31: ='CHIỀU '!AH10 -> 10 | F31: ='CHIỀU '!AH11+'HHVCV - Tăng ca'!AH11 -> 17 | G31: =SUM(B31:F31) -> 436
A32: 46292 | B32: ='VP SÁNG '!AI9+HHVCV!AI7 -> 20 | C32: ='HHVCV - Tăng ca'!AI10 -> 4 | D32: ='VP SÁNG '!AI10+HHVCV!AI8 -> 120 | E32: ='CHIỀU '!AI10 -> 0 | F32: ='CHIỀU '!AI11+'HHVCV - Tăng ca'!AI11 -> 0 | G32: =SUM(B32:F32) -> 144
A33: 46293 | B33: ='VP SÁNG '!AJ9+HHVCV!AJ7 -> 37 | C33: ='HHVCV - Tăng ca'!AJ10 -> 10 | D33: ='VP SÁNG '!AJ10+HHVCV!AJ8 -> 365 | E33: ='CHIỀU '!AJ10 -> 10 | F33: ='CHIỀU '!AJ11+'HHVCV - Tăng ca'!AJ11 -> 235 | G33: =SUM(B33:F33) -> 657
A34: 46294 | B34: ='VP SÁNG '!AK9+HHVCV!AK7 -> 36 | C34: ='HHVCV - Tăng ca'!AK10 -> 8 | D34: ='VP SÁNG '!AK10+HHVCV!AK8 -> 374 | E34: ='CHIỀU '!AK10 -> 10 | F34: ='CHIỀU '!AK11+'HHVCV - Tăng ca'!AK11 -> 242 | G34: =SUM(B34:F34) -> 670
A35: 46295 | B35: ='VP SÁNG '!AL9+HHVCV!AL7 -> 34 | C35: ='HHVCV - Tăng ca'!AL10 -> 5 | D35: ='VP SÁNG '!AL10+HHVCV!AL8 -> 367 | E35: ='CHIỀU '!AL10 -> 3 | F35: ='CHIỀU '!AL11+'HHVCV - Tăng ca'!AL11 -> 164 | G35: =SUM(B35:F35) -> 573
A36: Total Meals Tổng phần ăn | B36: =SUM(B6:B35) -> 726 | C36: =SUM(C6:C35) -> 67 | D36: =SUM(D6:D35) -> 8516 | E36: =SUM(E6:E35) -> 174 | F36: =SUM(F6:F35) -> 3360 | G36: =SUM(G6:G35) -> 12843
A39: 2. Cost Summary
A40: Category | B40: Cost per Meal (VND) | C40: Total Meals | D40: Total Amount (VND)
A41: Expat Meals | B41: 50000 | C41: =B36+C36 -> 793 | D41: =C41*B41 -> 39650000
A42: Vietnamese Meals ( Shift 1, Nomal, Overtime, and Shift 2) | B42: 25000 | C42: =SUM(D36:F36) -> 12050 | D42: =C42*B42 -> 301250000
A43: Amount to pay | C43: =SUM(C41:C42) -> 12843 | D43: =SUM(D41:D42) -> 340900000
A45: 3. Cost per Department
A47: Deparment | B47: Total Meal per deaprtment | C47: Cos per Meal | D47: Total Amount per Department
A48: COO - Assistant | B48: =SUMIF(PRIOVOT!$A:$A,$A48,PRIOVOT!$B:$B) +SUMIF(PRIOVOT!$D:$D,$A48,PRIOVOT!$E:$E) +SUMIF(PRIOVOT!$G:$G,$A48,PRIOVOT!$H:$H) -> 23 | C48: 25000 | D48: =C48*B48 -> 575000
A49: COO - Exim | B49: =SUMIF(PRIOVOT!$A:$A,$A49,PRIOVOT!$B:$B) +SUMIF(PRIOVOT!$D:$D,$A49,PRIOVOT!$E:$E) +SUMIF(PRIOVOT!$G:$G,$A49,PRIOVOT!$H:$H) -> 23 | C49: 25000 | D49: =C49*B49 -> 575000
A50: COO - IT | B50: =SUMIF(PRIOVOT!$A:$A,$A50,PRIOVOT!$B:$B) +SUMIF(PRIOVOT!$D:$D,$A50,PRIOVOT!$E:$E) +SUMIF(PRIOVOT!$G:$G,$A50,PRIOVOT!$H:$H) -> 39 | C50: 25000 | D50: =C50*B50 -> 975000
A51: COO - Maintenance | B51: =SUMIF(PRIOVOT!$A:$A,$A51,PRIOVOT!$B:$B) +SUMIF(PRIOVOT!$D:$D,$A51,PRIOVOT!$E:$E) +SUMIF(PRIOVOT!$G:$G,$A51,PRIOVOT!$H:$H) -> 134 | C51: 25000 | D51: =C51*B51 -> 3350000
A52: COO - Purchasing | B52: =SUMIF(PRIOVOT!$A:$A,$A52,PRIOVOT!$B:$B) +SUMIF(PRIOVOT!$D:$D,$A52,PRIOVOT!$E:$E) +SUMIF(PRIOVOT!$G:$G,$A52,PRIOVOT!$H:$H) -> 71 | C52: 25000 | D52: =C52*B52 -> 1775000
A53: COO - WWT | B53: =SUMIF(PRIOVOT!$A:$A,$A53,PRIOVOT!$B:$B) +SUMIF(PRIOVOT!$D:$D,$A53,PRIOVOT!$E:$E) +SUMIF(PRIOVOT!$G:$G,$A53,PRIOVOT!$H:$H) -> 26 | C53: 25000 | D53: =C53*B53 -> 650000
A54: COO Assistant | B54: =SUMIF(PRIOVOT!$A:$A,$A54,PRIOVOT!$B:$B) +SUMIF(PRIOVOT!$D:$D,$A54,PRIOVOT!$E:$E) +SUMIF(PRIOVOT!$G:$G,$A54,PRIOVOT!$H:$H) -> 24 | C54: 25000 | D54: =C54*B54 -> 600000
A55: COO Office | B55: =SUMIF(PRIOVOT!$A:$A,$A55,PRIOVOT!$B:$B) +SUMIF(PRIOVOT!$D:$D,$A55,PRIOVOT!$E:$E) +SUMIF(PRIOVOT!$G:$G,$A55,PRIOVOT!$H:$H) -> 112 | C55: 25000 | D55: =C55*B55 -> 2800000
A56: Finance - Accounting | B56: =SUMIF(PRIOVOT!$A:$A,$A56,PRIOVOT!$B:$B) +SUMIF(PRIOVOT!$D:$D,$A56,PRIOVOT!$E:$E) +SUMIF(PRIOVOT!$G:$G,$A56,PRIOVOT!$H:$H) -> 148 | C56: 25000 | D56: =C56*B56 -> 3700000
A57: HR Admin | B57: =SUMIF(PRIOVOT!$A:$A,$A57,PRIOVOT!$B:$B) +SUMIF(PRIOVOT!$D:$D,$A57,PRIOVOT!$E:$E) +SUMIF(PRIOVOT!$G:$G,$A57,PRIOVOT!$H:$H) -> 92 | C57: 25000 | D57: =C57*B57 -> 2300000
A58: HHVCV | B58: =SUMIF(PRIOVOT!$A:$A,$A58,PRIOVOT!$B:$B) +SUMIF(PRIOVOT!$D:$D,$A58,PRIOVOT!$E:$E) +SUMIF(PRIOVOT!$G:$G,$A58,PRIOVOT!$H:$H) -> 186 | C58: 25000 | D58: =C58*B58 -> 4650000
A59: PMC - Plan | B59: =SUMIF(PRIOVOT!$A:$A,$A59,PRIOVOT!$B:$B) +SUMIF(PRIOVOT!$D:$D,$A59,PRIOVOT!$E:$E) +SUMIF(PRIOVOT!$G:$G,$A59,PRIOVOT!$H:$H) -> 46 | C59: 25000 | D59: =C59*B59 -> 1150000
... A78: Subcontractor | B78: =SUMIF(PRIOVOT!$A:$A,$A78,PRIOVOT!$B:$B) +SUMIF(PRIOVOT!$D:$D,$A78,PRIOVOT!$E:$E) +SUMIF(PRIOVOT!$G:$G,$A78,PRIOVOT!$H:$H) -> 244 | C78: 25000 | D78: =C78*B78 -> 6100000
A79: Total Amount (VND) | D79: =SUM(D48:D78) -> 340900000

Sheet HG confirm
A1: BIÊN BẢN XÁC NHẬN SUẤT ĂN MEAL QUANTITY CONFIRMATION MINUTES
A2: Căn cứ Hợp đồng dịch vụ cung cấp suất ăn công nghiệp ký ngày 01/08/2026 giữa Công ty TNHH Visual Comfort Việt Nam và Công ty TNHH Hoàng Giang Food; Pursuant to the Industrial Catering Meal Supply Service Contract dated August 01, 2026 between Visual Comfort VietNam Co., Ltd and Hoang Giang Food Co., Ltd.;
A3: Căn cứ số lượng suất ăn thực tế phát sinh trong tháng 09/2026; Based on the actual meal quantities incurred in September 2026;
A4: Hôm nay, ngày 30 tháng 09 năm 2026, hai bên cùng xác nhận số lượng suất ăn và giá trị thanh toán trong tháng 09/2026 như sau: Today, on September 30th, 2026, both parties confirm the meal quantities and payment amount for September 2026 as follows:
A6: 1. CHI TIẾT SỐ LƯỢNG SUẤT ĂN / MEAL QUANTITY DETAILS
A8: Date | B8: Expat Meals Cơm chuyên gia Trung Quốc | C8: Vietnamese Meals Cơm người Việt | D8: Total Meals per day Tổng phần ăn | F8: Tổng phần hoàn OT không giao (VN) | G8: Tổng phần hoàn Dầu Giây (VN) | H8: Tổng phần hoàn Dầu Giây (TQ)
A9: 46266 | B9: =SUM(Payment!B6:C6) -> 25 | C9: =SUM(Payment!D6:F6) -> 352 | D9: =SUM(B9:C9) -> 377 | F9: 8 | G9: =HHVCV!E8+'HHVCV - Tăng ca'!F11 -> 388 | H9: =HHVCV!E7+'HHVCV - Tăng ca'!F10 -> 174
A10: 46267 | B10: =SUM(Payment!B7:C7) -> 0 | C10: =SUM(Payment!D7:F7) -> 0 | D10: =SUM(B10:C10) -> 0 | F10: 0
A11: 46268 | B11: =SUM(Payment!B8:C8) -> 0 | C11: =SUM(Payment!D8:F8) -> 0 | D11: =SUM(B11:C11) -> 0 | F11: ='CHIỀU '!K14 -> 0
A12: 46269 | B12: =SUM(Payment!B9:C9) -> 25 | C12: =SUM(Payment!D9:F9) -> 463 | D12: =SUM(B12:C12) -> 488 | F12: 8
A13: 46270 | B13: =SUM(Payment!B10:C10) -> 24 | C13: =SUM(Payment!D10:F10) -> 357 | D13: =SUM(B13:C13) -> 381 | F13: 8
A14: 46271 | B14: =SUM(Payment!B11:C11) -> 5 | C14: =SUM(Payment!D11:F11) -> 67 | D14: =SUM(B14:C14) -> 72 | F14: ='CHIỀU '!I18 -> 0
A15: 46272 | B15: =SUM(Payment!B12:C12) -> 25 | C15: =SUM(Payment!D12:F12) -> 469 | D15: =SUM(B15:C15) -> 494 | F15: 8
A16: 46273 | B16: =SUM(Payment!B13:C13) -> 25 | C16: =SUM(Payment!D13:F13) -> 437 | D16: =SUM(B16:C16) -> 462 | F16: 10
A17: 46274 | B17: =SUM(Payment!B14:C14) -> 23 | C17: =SUM(Payment!D14:F14) -> 448 | D17: =SUM(B17:C17) -> 471 | F17: 10
A18: 46275 | B18: =SUM(Payment!B15:C15) -> 26 | C18: =SUM(Payment!D15:F15) -> 429 | D18: =SUM(B18:C18) -> 455 | F18: 10
A19: 46276 | B19: =SUM(Payment!B16:C16) -> 25 | C19: =SUM(Payment!D16:F16) -> 405 | D19: =SUM(B19:C19) -> 430 | F19: 10
A20: 46277 | B20: =SUM(Payment!B17:C17) -> 23 | C20: =SUM(Payment!D17:F17) -> 316 | D20: =SUM(B20:C20) -> 339 | F20: 10
A21: 46278 | B21: =SUM(Payment!B18:C18) -> 0 | C21: =SUM(Payment!D18:F18) -> 0 | D21: =SUM(B21:C21) -> 0 | F21: 0
A22: 46279 | B22: =SUM(Payment!B19:C19) -> 27 | C22: =SUM(Payment!D19:F19) -> 459 | D22: =SUM(B22:C22) -> 486 | F22: 10
A23: 46280 | B23: =SUM(Payment!B20:C20) -> 27 | C23: =SUM(Payment!D20:F20) -> 569 | D23: =SUM(B23:C23) -> 596 | F23: 10
A24: 46281 | B24: =SUM(Payment!B21:C21) -> 26 | C24: =SUM(Payment!D21:F21) -> 575 | D24: =SUM(B24:C24) -> 601 | F24: 10
A25: 46282 | B25: =SUM(Payment!B22:C22) -> 25 | C25: =SUM(Payment!D22:F22) -> 588 | D25: =SUM(B25:C25) -> 613 | F25: 10
A26: 46283 | B26: =SUM(Payment!B23:C23) -> 24 | C26: =SUM(Payment!D23:F23) -> 490 | D26: =SUM(B26:C26) -> 514 | F26: 10
... A33: 46290 | B33: =SUM(Payment!B30:C30) -> 38 | C33: =SUM(Payment!D30:F30) -> 466 | D33: =SUM(B33:C33) -> 504 | F33: 10
A34: 46291 | B34: =SUM(Payment!B31:C31) -> 47 | C34: =SUM(Payment!D31:F31) -> 389 | D34: =SUM(B34:C34) -> 436 | F34: =10 -> 10
A35: 46292 | B35: =SUM(Payment!B32:C32) -> 24 | C35: =SUM(Payment!D32:F32) -> 120 | D35: =SUM(B35:C35) -> 144
A36: 46293 | B36: =SUM(Payment!B33:C33) -> 47 | C36: =SUM(Payment!D33:F33) -> 610 | D36: =SUM(B36:C36) -> 657 | F36: 10
A37: 46294 | B37: =SUM(Payment!B34:C34) -> 44 | C37: =SUM(Payment!D34:F34) -> 626 | D37: =SUM(B37:C37) -> 670 | F37: 10
A38: 46295 | B38: =SUM(Payment!B35:C35) -> 39 | C38: =SUM(Payment!D35:F35) -> 534 | D38: =SUM(B38:C38) -> 573 | F38: 10
A39: Total Meals Tổng phần ăn | B39: =SUM(B9:B38) -> 793 | C39: =SUM(C9:C38) -> 12050 | D39: =SUM(D9:D38) -> 12843 | F39: =SUM(F9:F38) -> 232 | G39: =SUM(G9:G38) -> 388 | H39: =SUM(H9:H38) -> 174
F40: =F39*25000 -> 5800000 | G40: =G39*25000 -> 9700000 | H40: =H39*50000 -> 8700000
F41: Tổng cộng | H41: =SUM(F40:H40) -> 24200000
A42: 2. XÁC NHẬN GIÁ TRỊ THANH TOÁN / PAYMENT VALUE CONFIRMATION | F42: VAT | H42: =H41*8% -> 1936000
F43: Tổng hoàn | H43: =SUM(H41:H42) -> 26136000
A44: Category | B44: Cost per Meal (VND) | C44: Total Meals | D44: Total Amount (VND)
A45: Expat Meals | B45: 50000 | C45: =B39 -> 793 | D45: =C45*B45 -> 39650000
A46: Vietnamese Meals ( Shift 1, Nomal, Overtime, and Shift 2) | B46: 25000 | C46: =C39 -> 12050 | D46: =C46*B46 -> 301250000
A47: Amount to pay | C47: =SUM(C45:C46) -> 12843 | D47: =SUM(D45:D46) -> 340900000
A48: VAT | D48: =D47*8% -> 27272000
A49: Total Amount (exclude VAT) | D49: =SUM(D47:D48) -> 368172000
A51: Hai bên thống nhất xác nhận số liệu nêu trên là căn cứ để Bên cung cấp lập hóa đơn và thực hiện thủ tục thanh toán theo Hợp đồng đã ký kết. Both parties agree that the above figures shall serve as the basis for the Supplier to issue the invoice and proceed with payment procedures in accordance with the signed Contract.
A53: ĐẠI DIỆN BÊN MUA BUYER'S REPRESENTATIVE | C53: ĐẠI DIỆN BÊN BÁN SELLER'S REPRESENTATIVE
A60: DƯƠNG ANH THƯ | C60: NGUYỄN THỊ THU HƯƠNG

Sheet Sheet1
B2: Họ và tên | D2: Số lượng | E2: Tổng thanh toán
B3: Trần Minh Công | C3: VCV0061 | D3: =COUNTIF($B$18:$AC$28,"Trần Minh Công") -> 9 | E3: =D3*25000 -> 225000
B4: Vũ Ngọc Đức | C4: VCV0435 | D4: =COUNTIF($B$18:$AC$28,"Vũ Ngọc Đức") -> 9 | E4: =D4*25000 -> 225000
B5: Đào Văn Tuyển | C5: VCV0201 | D5: =COUNTIF($B$18:$AC$28,B5) -> 10 | E5: =D5*25000 -> 250000
B6: Nguyễn Minh Đức | C6: VCV0409 | D6: =COUNTIF($B$18:$AC$28,"Nguyễn Minh Đức") -> 10 | E6: =D6*25000 -> 250000
B7: Nguyễn Văn Lâm | C7: VCV0657 | D7: =COUNTIF($B$18:$AC$28,"Nguyễn Văn Lâm") -> 10 | E7: =D7*25000 -> 250000
B8: Trần Văn Nguyên | C8: VCV0239 | D8: =COUNTIF($B$18:$AC$28,"Trần Văn Nguyên") -> 10 | E8: =D8*25000 -> 250000
B9: Nguyễn Duy Luân | C9: VCV0228 | D9: =COUNTIF($B$18:$AC$28,"Nguyễn Duy Luân") -> 10 | E9: =D9*25000 -> 250000
B10: Vũ Đình Duy | C10: VCV0542 | D10: =COUNTIF($B$18:$AC$28,"Vũ Đình Duy") -> 10 | E10: =D10*25000 -> 250000
B11: Chu Quang Tiến | C11: VCV0746 | D11: =COUNTIF($B$18:$AC$28,"Chu Quang Tiến") -> 15 | E11: =D11*25000 -> 375000
E13: =SUM(E3:E11) -> 2325000
D17: 46260 | E17: 46261 | F17: 46262 | G17: 46263 | H17: 46264 | I17: 46265 | J17: 46266 | K17: 46267 | L17: 46268 | M17: 46269 | N17: 46270 | O17: 46271 | P17: 46272 | Q17: 46273 | R17: 46274 | S17: 46275 | T17: 46276 | U17: 46277 | V17: 46278 | W17: 46279 | X17: 46280 | Y17: 46281 | Z17: 46282 | AA17: 46283 | AB17: 46284 | AC17: 46285
D18: Đào Văn Tuyển | E18: Đào Văn Tuyển | F18: Đào Văn Tuyển | G18: Đào Văn Tuyển | I18: Trần Văn Nguyên | J18: Trần Văn Nguyên | M18: Trần Văn Nguyên | N18: Trần Văn Nguyên | P18: Đào Văn Tuyển | Q18: Đào Văn Tuyển | R18: Đào Văn Tuyển | S18: Đào Văn Tuyển | T18: Đào Văn Tuyển | U18: Đào Văn Tuyển | W18: Trần Văn Nguyên | X18: Trần Văn Nguyên | Y18: Trần Văn Nguyên | Z18: Trần Văn Nguyên | AA18: Nguyễn Duy Luân | AB18: Nguyễn Duy Luân
D19: Trần Minh Công | E19: Trần Minh Công | F19: Trần Minh Công | G19: Trần Minh Công | I19: Nguyễn Duy Luân | J19: Nguyễn Duy Luân | M19: Nguyễn Duy Luân | N19: Nguyễn Duy Luân | P19: Trần Minh Công | Q19: Trần Minh Công | R19: Trần Minh Công | S19: Trần Minh Công | T19: Nguyễn Minh Đức | U19: Trần Minh Công | W19: Nguyễn Duy Luân | X19: Nguyễn Duy Luân | Y19: Nguyễn Duy Luân | Z19: Nguyễn Duy Luân | AA19: Trần Văn Nguyên | AB19: Trần Văn Nguyên
D20: Nguyễn Minh Đức | E20: Nguyễn Minh Đức | F20: Nguyễn Minh Đức | G20: Nguyễn Minh Đức | I20: Vũ Ngọc Đức | J20: Vũ Ngọc Đức | M20: Vũ Ngọc Đức | N20: Vũ Ngọc Đức | P20: Nguyễn Minh Đức | Q20: Nguyễn Minh Đức | R20: Nguyễn Minh Đức | S20: Nguyễn Minh Đức | T20: Nguyễn Văn Lâm | U20: Nguyễn Minh Đức | W20: Vũ Ngọc Đức | X20: Vũ Đình Duy | Y20: Vũ Ngọc Đức | Z20: Vũ Ngọc Đức | AA20: Vũ Ngọc Đức | AB20: Vũ Ngọc Đức
D21: Nguyễn Văn Lâm | E21: Nguyễn Văn Lâm | F21: Nguyễn Văn Lâm | G21: Nguyễn Văn Lâm | I21: Vũ Đình Duy | J21: Vũ Đình Duy | M21: Vũ Đình Duy | N21: Vũ Đình Duy | P21: Nguyễn Văn Lâm | Q21: Nguyễn Văn Lâm | R21: Nguyễn Văn Lâm | S21: Nguyễn Văn Lâm | T21: Chu Quang Tiến | U21: Nguyễn Văn Lâm | W21: Vũ Đình Duy | X21: Chu Quang Tiến | Y21: Vũ Đình Duy | Z21: Vũ Đình Duy | AA21: Vũ Đình Duy | AB21: Vũ Đình Duy
D22: Chu Quang Tiến | F22: Chu Quang Tiến | G22: Chu Quang Tiến | P22: Chu Quang Tiến | Q22: Chu Quang Tiến | R22: Chu Quang Tiến | S22: Chu Quang Tiến | U22: Chu Quang Tiến | W22: Chu Quang Tiến | Y22: Chu Quang Tiến | Z22: Chu Quang Tiến | AA22: Chu Quang Tiến | AB22: Chu Quang Tiến
